Workbook

Sheet Pressupostos
B2: Pressupostos para o Projeto Financeiro
B4: Promotor | C4: AGRITORRES
B5: Tipologia do Projeto | C5: INTERNACIONALIZAÇÃO
B6: NUTS II
B8: Taxa de Comparticipação Internacionalização | C8: 0.45
B9: Taxa de Comparticipação Inovação (fundo Perdido) | C9: 0.3
B10: Ano pré-projeto | C10: 2018
B11: Estamos no ano de | C11: 2020
B12: Ano de início do projeto | C12: 2020
B13: Ano Pós-Projeto | C13: 2023
B14: Dias de operação anuais | C14: 360
C16: =C11 -> 2020 | D16: =C16+1 -> 2021 | E16: =D16+1 -> 2022 | F16: =E16+1 -> 2023 | G16: =F16+1 -> 2024 | H16: =G16+1 -> 2025 | I16: =H16+1 -> 2026 | J16: =I16+1 -> 2027 | K16: =J16+1 -> 2028 | L16: =K16+1 -> 2029 | M16: Perpet.
B17: Inflação anual prevista | C17: 0.01 | D17: 0.01 | E17: 0.01 | F17: 0.01 | G17: 0.01 | H17: 0.01 | I17: 0.01 | J17: 0.01 | K17: 0.01 | L17: 0.01 | M17: 0.01
B19: Crescimento Real das Vendas | C19: =C11 -> 2020 | D19: =$C$19+1 -> 2021 | E19: =$C$19+2 -> 2022 | F19: =+E19+1 -> 2023 | G19: =+F19+1 -> 2024 | H19: =+G19+1 -> 2025 | I19: =+H19+1 -> 2026 | J19: =+I19+1 -> 2027 | K19: =+J19+1 -> 2028 | L19: =+K19+1 -> 2029 | M19: Perpet.
B20: Vendas | C20: 1.05 | D20: 1.05 | E20: 1.05 | F20: 1.05 | G20: 1.01 | H20: 1.01 | I20: 1.01 | J20: 1.01 | K20: 1.01 | L20: 1.01 | M20: 1
B21: Prestação de Serviços | C21: 1.05 | D21: 1.05 | E21: 1.05 | F21: 1.05 | G21: 1.01 | H21: 1.01 | I21: 1.01 | J21: 1.01 | K21: 1.01 | L21: 1.01 | M21: 1
B23: Quantos meses de trabalho a considerar | C23: 14 | D23: =C23 -> 14 | E23: =D23 -> 14 | F23: =E23 -> 14 | G23: =F23 -> 14 | H23: =G23 -> 14 | I23: =H23 -> 14 | J23: =I23 -> 14 | K23: =J23 -> 14 | ... M23: =L23 -> 14
B24: Taxa de crescimento nominal dos Salários | C24: 1.02 | D24: 1.02 | E24: 1.02 | F24: 1.02 | G24: 1.02 | H24: 1.02 | I24: 1.02 | J24: 1.02 | K24: 1.02 | L24: 1.02 | M24: 1.02
B25: Taxa Social (23,75%) mais seguros diversos (2.5%) | C25: =0.2375+0.025 -> 0.2625 | D25: =C25 -> 0.2625 | E25: =D25 -> 0.2625 | F25: =E25 -> 0.2625 | G25: =F25 -> 0.2625 | H25: =G25 -> 0.2625 | I25: =H25 -> 0.2625 | J25: =I25 -> 0.2625 | K25: =J25 -> 0.2625 | ... M25: =L25 -> 0.2625
B26: Qual é o diferimento da SS (meses) | C26: 2 | D26: =C26 -> 2 | E26: =D26 -> 2 | F26: =E26 -> 2 | G26: =F26 -> 2 | H26: =G26 -> 2 | I26: =H26 -> 2 | J26: =I26 -> 2 | K26: =J26 -> 2 | ... M26: =L26 -> 2
B27: Qual é a Taxa do IVA | C27: 0.23 | D27: =C27 -> 0.23 | E27: =D27 -> 0.23 | F27: =E27 -> 0.23 | G27: =F27 -> 0.23 | H27: =G27 -> 0.23 | I27: =H27 -> 0.23 | J27: =I27 -> 0.23 | K27: =J27 -> 0.23 | ... M27: =L27 -> 0.23
B28: Qual é o diferimento do IVA (meses) | C28: 1 | D28: =C28 -> 1 | E28: =D28 -> 1 | F28: =E28 -> 1 | G28: =F28 -> 1 | H28: =G28 -> 1 | I28: =H28 -> 1 | J28: =I28 -> 1 | K28: =J28 -> 1 | ... M28: =L28 -> 1
B30: Qual é o imposto de selo | C30: 0.005
B32: Tx. Sem risco (10y OTs) | C32: 0.0035 | D32: German Government Bonds 10Y (25/10/2018)
B33: Prémio risco mercado | C33: 0.0665 | D33: Prémio globalmente aceite para países desenvolvidos
B34: Beta dos ativos | C34: 1
B35: Taxa de Atualização (Ra) | C35: =C32+C33*C34 -> 0.07 | D35: CAPM
B37: IRC | C37: 0.21
B38: Derrama (Porto) | C38: 0.015
B39: Taxa Imposto (IRC+Derrama) | C39: =C37+C38 -> 0.225
B41: Prazos Médios (dias)
B42: Clientes - PMR | C42: 90
B43: Fornecedores - PMP | C43: 60
B44: Existências | C44: 30
B46: Taxa Juro Empréstimo Normal | C46: =C47+C48 -> 0.04765
B47: Taxa | C47: -0.00235 | D47: Euribor 6 meses - 02/01/2019
B48: Spread | C48: 0.05
B49: Taxa Juro Bonificada | C49: 0

Sheet DR
B2: DEMONSTRAÇÃO DE RESULTADOS DO PROMOTOR
B3: DEMONSTRAÇÃO DOS RESULTADOS POR NATUREZAS | C3: UNIDADE: EUROS
B4: RÚBRICAS | C4: CÓDIGO | D4: =Pressupostos!C11-3 -> 2017 | E4: =D4+1 -> 2018 | F4: =E4+1 -> 2019
C5: SNC
B6: Vendas e serviços prestados | D6: =D36+D39 -> 0 | E6: =E36+E39 -> 0 | F6: =+F39 -> 3479532.1
B7: Subsídios à exploração | F7: 49.26
B8: Ganhos/perdas imputados de subsidiárias, associadas e empreendimentos conjuntos | F8: 0
B9: Variação nos inventários da produção
B10: Trabalhos para a própria entidade
B11: Custo das mercadorias vendidas e das matérias consumidas | F11: 2780591.1 | I11: =+F11/F6 -> 0.79912788
B12: Fornecimentos e serviços externos | F12: 506782.86 | G12: =D12/D6 -> #DIV/0! | H12: =E12/E6 -> #DIV/0! | I12: =F12/F6 -> 0.14564684
B13: Gastos com o pessoal | F13: 169363.3
B14: Imparidade de inventários (perdas/reversões) | F14: 0
B15: Imparidade de dívidas a receber (perdas/reversões) | F15: 40.26
B16: Provisões (aumentos/reduções)
B17: Imparidade de investimentos não depreciáveis/amortizáveis (perdas/reversões)
B18: Outras imparidades (perdas/reversões)/Imparidades
B19: Aumentos/reduções de justo valor
B20: Outros rendimentos e ganhos | F20: 73417.34
B21: Outros gastos e perdas | F21: 37622.48
B22: Resultado antes de depreciações, gastos de financiamento e impostos | D22: =D6+D7+D8+D9+D10-D11-D12-D13-D14-D15-D16-D17-D18+D19+D20-D21 -> 0 | E22: =E6+E7+E8+E9+E10-E11-E12-E13-E14-E15-E16-E17-E18+E19+E20-E21 -> 0 | F22: =F6+F7+F8+F9+F10-F11-F12-F13-F14-F15-F16-F17-F18+F19+F20-F21 -> 58598.69 | G22: =58598.69-F22 -> 0
B23: Gastos/reversões de depreciação e de amortização | F23: 15247.25
B24: Imparidade de investimentos depreciáveis/amortizáveis
B25: Resultado operacional (antes de gastos de financiamento e impostos) | D25: =D22-D23-D24 -> 0 | E25: =E22-E23-E24 -> 0 | F25: =F22-F23-F24 -> 43351.44
B26: Juros e rendimentos similares obtidos | F26: 0
B27: Juros e gastos similares suportados | F27: 1053
B28: Resultado antes de impostos | D28: =D25+D26-D27 -> 0 | E28: =E25+E26-E27 -> 0 | F28: =F25+F26-F27 -> 42298.44
B29: Imposto sobre o rendimento do período | F29: 10443.87
B30: Resultado líquido do período | D30: =D28-D29 -> 0 | E30: =E28-E29 -> 0 | F30: =F28-F29 -> 31854.57 | G30: =+F30/F6 -> 0.0091548429 | I30: =+Balanço!E22/DR!F6 -> 0.21786974 | J30: =+I30*12 -> 2.6144369
B32: Compras | D32: 0 | E32: 0 | F32: 0
B34: Meios Libertos | D34: =D30+D23+D24 -> 0 | E34: =E30+E23+E24+(E16-D16) -> 0 | F34: =F30+F23+F24+(F16-E16) -> 47101.82
B36: Vendas | D36: =D37+D38 -> 0 | E36: =E37+E38 -> 0 | F36: =F37+F38 -> 0
B37: Produtos
B38: Mercadorias
B39: Prestação de Serviços | F39: =80.52+3479451.62 -> 3479532.1
B40: Diferença | D40: =(D37+D38+D39)-D6 -> 0 | E40: =(E37+E38+E39)-E6 -> 0 | F40: =(F37+F38+F39)-F6 -> 0
D84: 40405.59
C85: 0 | D85: 0
C86: 1348.55 | D86: 1348.55

Sheet Balanço
B2: BALANÇOS DO PROMOTOR
B3: UNIDADE: EUROS
B4: RÚBRICAS | C4: =Pressupostos!C11-3 -> 2017 | D4: =C4+1 -> 2018 | E4: =D4+1 -> 2019
B5: ATIVO
B6: Ativo não corrente
B7: Ativos fixos tangíveis | E7: 84625.24
B8: Propriedades de investimento | E8: 102152.86
B9: Goodwill
B10: Ativos intangíveis
B11: Ativos biológicos
B12: Participações financeiras - método da equivalência patrimonial
B13: Participações financeiras - outros métodos
B14: Acionistas/sócios
B15: Outros ativos financeiros | E15: 347.82
B16: Ativos por impostos diferidos
B17: Investimentos financeiros (utilização exclusiva pelas pequenas entidades e microentidades)
B18: SOMA | C18: =SUM(C7:C17) -> 0 | D18: =SUM(D7:D17) -> 0 | E18: =SUM(E7:E17) -> 187125.92
B19: Ativo Corrente
B20: Inventários | E20: 343630.82
B21: Ativos biológicos | E21: 0
B22: Clientes | E22: 758084.77
B23: Adiantamentos a fornecedores
B24: Estado e outros entes públicos | E24: 21003.43
B25: Acionistas/sócios
B26: Outras contas a receber | E26: 80826.21
B27: Diferimentos | E27: 955.33
B28: Ativos financeiros detidos para negociação
B29: Outros ativos financeiros
B30: Ativos não correntes detidos para venda
B31: Outros ativos correntes
B32: Caixa e depósitos bancários | E32: 215805.41
B33: SOMA | C33: =SUM(C20:C32) -> 0 | D33: =SUM(D20:D32) -> 0 | E33: =SUM(E20:E32) -> 1420306
B34: TOTAL DO ATIVO | C34: =C18+C33 -> 0 | D34: =D18+D33 -> 0 | E34: =E18+E33 -> 1607431.9
B35: CAPITAL PRÓPRIO E PASSIVO
B36: Capital Próprio
B37: Capital realizado | E37: 300000
B38: Ações (quotas) próprias
B39: Outros instrumentos de capital próprio
B40: Prémios de emissão
B41: Reservas legais | E41: 14785.57
B42: Outras reservas
B43: Resultados transitados | E43: 254627.19
B44: Ajustamentos em ativos financeiros
B45: Excedentes de revalorização
B46: Outras variações no capital próprio
B47: SOMA | C47: =SUM(C37:C46) -> 0 | D47: =SUM(D37:D46) -> 0 | E47: =SUM(E37:E46) -> 569412.76
B48: Resultado líquido do período | C48: =DR!D30 -> 0 | D48: =DR!E30 -> 0 | E48: =DR!F30 -> 31854.57
B49: Dividendos antecipados
B50: TOTAL DO CAPITAL PRÓPRIO | C50: =C47+C48+C49 -> 0 | D50: =D47+D48+D49 -> 0 | E50: =E47+E48+E49 -> 601267.33
B51: PASSIVO
B52: Passivo Não Corrente
B53: Provisões
B54: Financiamentos obtidos
B55: Responsabilidades por benefícios pós-emprego
B56: Passivos por impostos diferidos
B57: Outras contas a pagar
B58: SOMA | C58: =SUM(C53:C57) -> 0 | D58: =SUM(D53:D57) -> 0 | E58: =SUM(E53:E57) -> 0
B59: Passivo Corrente
B60: Fornecedores | E60: 760538.01
B61: Adiantamentos de clientes
B62: Estado e outros entes públicos | E62: 4173.5
B63: Acionistas/sócios
B64: Financiamentos obtidos
B65: Outras contas a pagar | E65: 241453.05
B66: Diferimentos
B67: Passivos financeiros detidos para negociação
B68: Outros passivos financeiros
B69: Passivos não correntes detidos para venda
B70: Outros passivos correntes
B71: SOMA | C71: =SUM(C60:C70) -> 0 | D71: =SUM(D60:D70) -> 0 | E71: =SUM(E60:E70) -> 1006164.6
B72: TOTAL DO PASSIVO | C72: =C58+C71 -> 0 | D72: =D58+D71 -> 0 | E72: =E58+E71 -> 1006164.6
B73: TOTAL DO CAPITAL PRÓPRIO E DO PASSIVO | C73: =C50+C72 -> 0 | D73: =D50+D72 -> 0 | E73: =E50+E72 -> 1607431.9
B75: Diferença | C75: =C73-C34 -> 0 | D75: =D73-D34 -> 0 | E75: =E73-E34 -> 0
B76: Autonomia Financeira | C76: =C50/C34 -> #DIV/0! | D76: =D50/D34 -> #DIV/0! | E76: =E50/E34 -> 0.37405462
B78: Ativo Bruto
B79: Imobilizado Tangível | C79: =C84+C7 -> 0 | D79: =D84+D7 -> 0 | E79: =E84+E7 -> 84625.24
B80: Imobilizado Tangível - Biológico | C80: =C85+C11 -> 0 | D80: =D85+D11 -> 0 | E80: =E85+E11 -> 0
B81: Imobilizado Intangível | C81: =C86+C10 -> 0 | D81: =D86+D10 -> 0 | E81: =E86+E10 -> 0
B83: Amortizações Acumuladas | C83: =SUM(C84:C86) -> 0 | D83: =SUM(D84:D86) -> 0 | E83: =SUM(E84:E86) -> 0
B84: Imobilizado Tangível
B85: Imobilizado Tangível - Biológico | C85: 0 | D85: 0 | E85: 0
B86: Imobilizado Intangível | C86: 0 | D86: 0 | E86: 0
B88: PMR | C88: =(C22/DR!D6)*Pressupostos!$C$14 -> #DIV/0! | D88: =(D22/DR!E6)*Pressupostos!$C$14 -> #DIV/0! | E88: =(E22/DR!F6)*Pressupostos!$C$14 -> 78.433107
B89: PMP | C89: =C60/DR!D6*Pressupostos!$C$14 -> #DIV/0! | D89: =D60/DR!E6*Pressupostos!$C$14 -> #DIV/0! | E89: =E60/DR!F6*Pressupostos!$C$14 -> 78.686925
B90: Existências | C90: =IFERROR(C20/DR!D32*Pressupostos!$C$14,"0") -> 0 | D90: =IFERROR(D20/DR!E32*Pressupostos!$C$14,"0") -> 0 | E90: =IFERROR(E20/DR!F32*Pressupostos!$C$14,"0") -> 0
B91: Cash Convertion Cycle | C91: =IFERROR(C88+C90-C89,"-") -> - | D91: =IFERROR(D88+D90-D89,"-") -> - | E91: =IFERROR(E88+E90-E89,"-") -> -0.25381757

Sheet Vendas+PrestServ
B2: VENDAS DE PRODUTOS (TRANSFORMADOS / COMERCIALIZADOS)
B3: Designação | C3: UNIDADE | D3: =Pressupostos!C11 -> 2020 | E3: =D3+1 -> 2021 | F3: =E3+1 -> 2022 | G3: =F3+1 -> 2023 | H3: =G3+1 -> 2024 | I3: =H3+1 -> 2025 | J3: =I3+1 -> 2026 | K3: =J3+1 -> 2027 | L3: =K3+1 -> 2028 | M3: =L3+1 -> 2029
B4: Vários | C4: Valor euros | D4: =DR!F37*Pressupostos!C20*(1+Pressupostos!C17) -> 0 | E4: =D4*Pressupostos!D20*(1+Pressupostos!D17) -> 0 | F4: =E4*Pressupostos!E20*(1+Pressupostos!E17) -> 0 | G4: =F4*Pressupostos!F20*(1+Pressupostos!F17) -> 0 | H4: =G4*Pressupostos!G20*(1+Pressupostos!G17) -> 0 | I4: =H4*Pressupostos!H20*(1+Pressupostos!H17) -> 0 | J4: =I4*Pressupostos!I20*(1+Pressupostos!I17) -> 0 | K4: =J4*Pressupostos!J20*(1+Pressupostos!J17) -> 0 | L4: =K4*Pressupostos!K20*(1+Pressupostos!K17) -> 0 | M4: =L4*Pressupostos!L20*(1+Pressupostos!L17) -> 0
C5: Valor euros
C6: Valor euros
C7: Valor euros
B8: TOTAL DO VALOR | D8: =SUM(D4:D7) -> 0 | E8: =SUM(E4:E7) -> 0 | F8: =SUM(F4:F7) -> 0 | G8: =SUM(G4:G7) -> 0 | H8: =SUM(H4:H7) -> 0 | I8: =SUM(I4:I7) -> 0 | J8: =SUM(J4:J7) -> 0 | K8: =SUM(K4:K7) -> 0 | ... M8: =SUM(M4:M7) -> 0
B10: VENDAS DE MERCADORIAS
B11: Designação | C11: UNIDADE | D11: =D3 -> 2020 | E11: =D11+1 -> 2021 | F11: =E11+1 -> 2022 | G11: =F11+1 -> 2023 | H11: =G11+1 -> 2024 | I11: =H11+1 -> 2025 | J11: =I11+1 -> 2026 | K11: =J11+1 -> 2027 | L11: =K11+1 -> 2028 | M11: =L11+1 -> 2029
B12: Vários | C12: Valor euros | E12: =D12*Pressupostos!D20*(1+Pressupostos!D17) -> 0 | F12: =E12*Pressupostos!E20*(1+Pressupostos!E17) -> 0 | G12: =F12*Pressupostos!F20*(1+Pressupostos!F17) -> 0 | H12: =G12*Pressupostos!G20*(1+Pressupostos!G17) -> 0 | I12: =H12*Pressupostos!H20*(1+Pressupostos!H17) -> 0 | J12: =I12*Pressupostos!I20*(1+Pressupostos!I17) -> 0 | K12: =J12*Pressupostos!J20*(1+Pressupostos!J17) -> 0 | L12: =K12*Pressupostos!K20*(1+Pressupostos!K17) -> 0 | M12: =L12*Pressupostos!L20*(1+Pressupostos!L17) -> 0
C13: Valor euros
C14: Valor euros
C15: Valor euros
B16: TOTAL DO VALOR | D16: =SUM(D12:D15) -> 0 | E16: =SUM(E12:E15) -> 0 | F16: =SUM(F12:F15) -> 0 | G16: =SUM(G12:G15) -> 0 | H16: =SUM(H12:H15) -> 0 | I16: =SUM(I12:I15) -> 0 | J16: =SUM(J12:J15) -> 0 | K16: =SUM(K12:K15) -> 0 | ... M16: =SUM(M12:M15) -> 0
B18: TOTAL DAS VENDAS | C18: EUROS | D18: =D8+D16 -> 0 | E18: =E8+E16 -> 0 | F18: =F8+F16 -> 0 | G18: =G8+G16 -> 0 | H18: =H8+H16 -> 0 | I18: =I8+I16 -> 0 | J18: =J8+J16 -> 0 | K18: =K8+K16 -> 0 | ... M18: =M8+M16 -> 0
B20: PRESTAÇÃO DE SERVIÇOS
B21: Designação | C21: UNIDADE | D21: =D3 -> 2020 | E21: =D21+1 -> 2021 | F21: =E21+1 -> 2022 | G21: =F21+1 -> 2023 | H21: =G21+1 -> 2024 | I21: =H21+1 -> 2025 | J21: =I21+1 -> 2026 | K21: =J21+1 -> 2027 | L21: =K21+1 -> 2028 | M21: =L21+1 -> 2029
B22: Vários | C22: EUROS | D22: =DR!F39*Pressupostos!C21*(1+Pressupostos!C17) -> 3690043.8 | E22: =D22*Pressupostos!D21*(1+Pressupostos!D17) -> 3913291.5 | F22: =E22*Pressupostos!E21*(1+Pressupostos!E17) -> 4150045.6 | G22: =F22*Pressupostos!F21*(1+Pressupostos!F17) -> 4401123.4 | H22: =G22*Pressupostos!G21*(1+Pressupostos!G17) -> 4489586 | I22: =H22*Pressupostos!H21*(1+Pressupostos!H17) -> 4579826.6 | J22: =I22*Pressupostos!I21*(1+Pressupostos!I17) -> 4671881.2 | K22: =J22*Pressupostos!J21*(1+Pressupostos!J17) -> 4765786 | L22: =K22*Pressupostos!K21*(1+Pressupostos!K17) -> 4861578.3 | M22: =L22*Pressupostos!L21*(1+Pressupostos!L17) -> 4959296
C23: EUROS
C24: EUROS
C25: EUROS
C26: EUROS
B27: TOTAL DA PRESTAÇÃO DE SERVIÇOS | D27: =SUM(D22:D26) -> 3690043.8 | E27: =SUM(E22:E26) -> 3913291.5 | F27: =SUM(F22:F26) -> 4150045.6 | G27: =SUM(G22:G26) -> 4401123.4 | H27: =SUM(H22:H26) -> 4489586 | I27: =SUM(I22:I26) -> 4579826.6 | J27: =SUM(J22:J26) -> 4671881.2 | K27: =SUM(K22:K26) -> 4765786 | ... M27: =SUM(M22:M26) -> 4959296
B29: VENDAS + PRESTAÇÃO DE SERVIÇOS | C29: =D29-1 -> 2019 | D29: =D3 -> 2020 | E29: =E3 -> 2021 | F29: =F3 -> 2022 | G29: =G3 -> 2023 | H29: =H3 -> 2024 | I29: =I3 -> 2025 | J29: =J3 -> 2026 | K29: =K3 -> 2027 | ... M29: =M3 -> 2029
C30: =DR!F6 -> 3479532.1 | D30: =D18+D27 -> 3690043.8 | E30: =E18+E27 -> 3913291.5 | F30: =F18+F27 -> 4150045.6 | G30: =G18+G27 -> 4401123.4 | H30: =H18+H27 -> 4489586 | I30: =I18+I27 -> 4579826.6 | J30: =J18+J27 -> 4671881.2 | K30: =K18+K27 -> 4765786 | ... M30: =M18+M27 -> 4959296

Sheet CMVMC
B2: CUSTO DAS MERCADORIAS VENDIDAS E MATÉRIAS CONSUMIDAS
C3: UNIDADE | D3: =Pressupostos!C11 -> 2020 | E3: =D3+1 -> 2021 | F3: =E3+1 -> 2022 | G3: =F3+1 -> 2023 | H3: =G3+1 -> 2024 | I3: =H3+1 -> 2025 | J3: =I3+1 -> 2026 | K3: =J3+1 -> 2027 | L3: =K3+1 -> 2028 | M3: =L3+1 -> 2029
B4: PRODUTOS | C4: Valor euros | D4: =D11*D12 -> 2896684.4 | E4: =E11*E12 -> 3071933.8 | F4: =F11*F12 -> 3237035.6 | G4: =G11*G12 -> 3432876.2 | H4: =H11*H12 -> 3501877 | I4: =I11*I12 -> 3572264.8 | J4: =J11*J12 -> 3644067.3 | K4: =K11*K12 -> 3717313.1 | ... M4: =M11*M12 -> 3868250.9
B5: MERCADORIAS | C5: Valor euros | D5: =IFERROR(D9*'Vendas+PrestServ'!D16,"0") -> 0 | E5: =IFERROR(E9*'Vendas+PrestServ'!E16,"0") -> 0 | F5: =IFERROR(F9*'Vendas+PrestServ'!F16,"0") -> 0 | G5: =IFERROR(G9*'Vendas+PrestServ'!G16,"0") -> 0 | H5: =IFERROR(H9*'Vendas+PrestServ'!H16,"0") -> 0 | I5: =IFERROR(I9*'Vendas+PrestServ'!I16,"0") -> 0 | J5: =IFERROR(J9*'Vendas+PrestServ'!J16,"0") -> 0 | K5: =IFERROR(K9*'Vendas+PrestServ'!K16,"0") -> 0 | ... M5: =IFERROR(M9*'Vendas+PrestServ'!M16,"0") -> 0
B6: TOTAL DO VALOR | D6: =D4+D5 -> 2896684.4 | E6: =E4+E5 -> 3071933.8 | F6: =F4+F5 -> 3237035.6 | G6: =G4+G5 -> 3432876.2 | H6: =H4+H5 -> 3501877 | I6: =I4+I5 -> 3572264.8 | J6: =J4+J5 -> 3644067.3 | K6: =K4+K5 -> 3717313.1 | ... M6: =M4+M5 -> 3868250.9
B8: Produtos | D8: =IFERROR(DR!F11/DR!F37,0) -> 0 | E8: =D8 -> 0 | F8: =E8 -> 0 | G8: =F8 -> 0 | H8: =G8 -> 0 | I8: =H8 -> 0 | J8: =I8 -> 0 | K8: =J8 -> 0 | L8: =K8 -> 0 | M8: =L8 -> 0
B9: Mercadorias (representatividade sobre as vendas de produtos) | D9: =IFERROR(DR!F11/DR!F38,0) -> 0 | E9: =D9 -> 0 | F9: =E9 -> 0 | G9: =F9 -> 0 | H9: =G9 -> 0 | I9: =H9 -> 0 | J9: =I9 -> 0 | K9: =J9 -> 0 | L9: =K9 -> 0 | M9: =L9 -> 0
B11: VN | D11: ='DR Empresa'!C5 -> 3690043.8 | E11: ='DR Empresa'!D5 -> 3913291.5 | F11: ='DR Empresa'!E5 -> 4150045.6 | G11: ='DR Empresa'!F5 -> 4401123.4 | H11: ='DR Empresa'!G5 -> 4489586 | I11: ='DR Empresa'!H5 -> 4579826.6 | J11: ='DR Empresa'!I5 -> 4671881.2 | K11: ='DR Empresa'!J5 -> 4765786 | ... M11: ='DR Empresa'!L5 -> 4959296
B12: % | D12: 0.785 | E12: 0.785 | F12: 0.78 | G12: 0.78 | H12: 0.78 | I12: 0.78 | J12: 0.78 | K12: 0.78 | L12: 0.78 | M12: 0.78

Sheet FSE
B2: FORNECIMENTOS E SERVIÇOS EXTERNOS | M2: UNIDADE: EUROS
D3: =Pressupostos!C11 -> 2020 | E3: =D3+1 -> 2021 | F3: =E3+1 -> 2022 | G3: =F3+1 -> 2023 | H3: =G3+1 -> 2024 | I3: =H3+1 -> 2025 | J3: =I3+1 -> 2026 | K3: =J3+1 -> 2027 | L3: =K3+1 -> 2028 | M3: =L3+1 -> 2029
B4: FSE sem projeto | D4: =DR!F12*(1+Pressupostos!C17) -> 511850.69 | E4: =E12*'Vendas+PrestServ'!E30 -> 528294.35 | F4: =F12*'Vendas+PrestServ'!F30 -> 560256.16 | G4: =G12*'Vendas+PrestServ'!G30 -> 594151.66 | H4: =H12*'Vendas+PrestServ'!H30 -> 606094.1 | I4: =I12*'Vendas+PrestServ'!I30 -> 618276.6 | J4: =J12*'Vendas+PrestServ'!J30 -> 630703.96 | K4: =K12*'Vendas+PrestServ'!K30 -> 643381.11 | L4: =L12*'Vendas+PrestServ'!L30 -> 656313.07 | M4: =M12*'Vendas+PrestServ'!M30 -> 669504.96
B5: FSE do Projeto | D5: =Faturas!E310 -> 20625.25 | E5: =Faturas!E311 -> 18340 | F5: =Faturas!E312 -> 14800 | G5: =Faturas!E313 -> 0 | H5: 0 | I5: 0 | J5: 0 | K5: 0 | L5: 0 | M5: 0
B6: TOTAL DO VALOR | D6: =SUM(D4:D5) -> 532475.94 | E6: =SUM(E4:E5) -> 546634.35 | F6: =SUM(F4:F5) -> 575056.16 | G6: =SUM(G4:G5) -> 594151.66 | H6: =SUM(H4:H5) -> 606094.1 | I6: =SUM(I4:I5) -> 618276.6 | J6: =SUM(J4:J5) -> 630703.96 | K6: =SUM(K4:K5) -> 643381.11 | ... M6: =SUM(M4:M5) -> 669504.96
B8: Volume de Negócios | D8: ='DR Empresa'!C5 -> 3690043.8 | E8: ='DR Empresa'!D5 -> 3913291.5 | F8: ='DR Empresa'!E5 -> 4150045.6 | G8: ='DR Empresa'!F5 -> 4401123.4 | H8: ='DR Empresa'!G5 -> 4489586 | I8: ='DR Empresa'!H5 -> 4579826.6 | J8: ='DR Empresa'!I5 -> 4671881.2 | K8: ='DR Empresa'!J5 -> 4765786 | ... M8: ='DR Empresa'!L5 -> 4959296
B9: FSE / Vlolume Negócios | D9: =D6/D8 -> 0.14430071 | E9: =E6/E8 -> 0.13968659 | F9: =F6/F8 -> 0.13856623 | G9: =G6/G8 -> 0.135 | H9: =H6/H8 -> 0.135 | I9: =I6/I8 -> 0.135 | J9: =J6/J8 -> 0.135 | K9: =K6/K8 -> 0.135 | ... M9: =M6/M8 -> 0.135
B11: % FSE / VN | C11: =D11-1 -> 2019 | D11: =D3 -> 2020 | E11: =E3 -> 2021 | F11: =F3 -> 2022 | G11: =G3 -> 2023 | H11: =H3 -> 2024 | I11: =I3 -> 2025 | J11: =J3 -> 2026 | K11: =K3 -> 2027 | ... M11: =M3 -> 2029
C12: =DR!F12/DR!F6 -> 0.14564684 | D12: 0.135 | E12: =+D12 -> 0.135 | F12: =+E12 -> 0.135 | G12: =+F12 -> 0.135 | H12: =+G12 -> 0.135 | I12: =+H12 -> 0.135 | J12: =+I12 -> 0.135 | K12: =+J12 -> 0.135 | L12: =+K12 -> 0.135 | M12: =+L12 -> 0.135

Sheet RH
B2: RECURSOS HUMANOS - CUSTOS | O2: Administração/Direção
D3: =Pressupostos!C11 -> 2020 | E3: =D3+1 -> 2021 | F3: =E3+1 -> 2022 | G3: =F3+1 -> 2023 | H3: =G3+1 -> 2024 | I3: =H3+1 -> 2025 | J3: =I3+1 -> 2026 | K3: =J3+1 -> 2027 | L3: =K3+1 -> 2028 | M3: =L3+1 -> 2029 | O3: Administrativa/Financeira
B4: Remunerações | D4: =(DR!F13*Pressupostos!C24)+K13 -> 172750.57 | E4: =(D4*Pressupostos!D24)+K14+M13 -> 201405.58 | F4: =(E4*Pressupostos!E24)+K15+M14 -> 213833.69 | G4: =(F4*Pressupostos!F24)+K16+M15 -> 218110.36 | H4: =(G4*Pressupostos!G24)+K17+M16 -> 222472.57 | I4: =(H4*Pressupostos!H24)+K18+M17 -> 226922.02 | J4: =(I4*Pressupostos!I24)+M18 -> 231460.46 | K4: =(J4*Pressupostos!J24) -> 236089.67 | L4: =(K4*Pressupostos!K24) -> 240811.46 | M4: =(L4*Pressupostos!L24) -> 245627.69 | O4: Aprovisionamento
B5: Encargos Sociais | D5: =D4*Pressupostos!$C$25 -> 45347.024 | E5: =E4*Pressupostos!$C$25 -> 52868.964 | F5: =F4*Pressupostos!$C$25 -> 56131.343 | G5: =G4*Pressupostos!$C$25 -> 57253.97 | H5: =H4*Pressupostos!$C$25 -> 58399.05 | I5: =I4*Pressupostos!$C$25 -> 59567.031 | J5: =J4*Pressupostos!$C$25 -> 60758.371 | K5: =K4*Pressupostos!$C$25 -> 61973.539 | ... M5: =M4*Pressupostos!$C$25 -> 64477.27 | O5: Comercial/Marketing
B6: TOTAL | D6: =SUM(D4:D5) -> 218097.59 | E6: =SUM(E4:E5) -> 254274.54 | F6: =SUM(F4:F5) -> 269965.03 | G6: =SUM(G4:G5) -> 275364.33 | H6: =SUM(H4:H5) -> 280871.62 | I6: =SUM(I4:I5) -> 286489.05 | J6: =SUM(J4:J5) -> 292218.83 | K6: =SUM(K4:K5) -> 298063.21 | ... M6: =SUM(M4:M5) -> 310104.96 | O6: Engenharia, Conceção e Projeto
O7: Investigação
B8: Nº RHs | C8: =D3-1 -> 2019 | D8: =F56 -> 0 | O8: Qualidade
B9: Nº RHs Pós-Projeto | D9: =I56 -> 0 | O9: Operacional (Produtiva)
B10: Falta acrescentar no quadro infra | D10: =-(COUNTA(E13:E24)+D8)+D9 -> -2 | O10: Operacional (Turismo) - Receção/Portaria
B11: RHs a Contratar (dentro e fora do âmbito do projeto) | O11: Operacional (Turismo) - Quartos/Limpeza
B12: Quantidade | C12: Área / Função | D12: Ano de Entrada | E12: Mês de Entrada | F12: Vencim. Base (€) | G12: Total | J12: Nº RHs a entar | O12: Operacional (Turismo) - Restaurante/Bar
B13: 1 | C13: Comercial/Marketing | D13: 2021 | E13: 4 | F13: 1200 | G13: =(13-E13)*F13+(F13*1/6)*(13-E13) -> 12600 | H13: =F13*14 -> 16800 | I13: =D3 -> 2020 | J13: =COUNTIF(D13:D24,D3) -> 0 | K13: =SUMIF(D13:D24,D3,G13:G24) -> 0 | L13: =SUMIF($D$13:$D$24,D3,$G$13:$G$24) -> 0 | M13: =L13-K13 -> 0 | O13: Operacional (Turismo) - Cozinha
B14: 2 | C14: Comercial/Marketing | D14: 2021 | E14: 4 | F14: 1200 | G14: =(13-E14)*F14+(F14*1/6)*(13-E14) -> 12600 | H14: =F14*14 -> 16800 | I14: =I13+1 -> 2021 | J14: =COUNTIF(D13:D24,E3) -> 2 | K14: =SUMIF(D13:D24,E3,G13:G24) -> 25200 | L14: =SUMIF($D$13:$D$24,E3,$H$13:$H$24) -> 33600 | M14: =L14-K14 -> 8400 | O14: Operacional (Turismo) - Animação
B15: 3 | G15: =(13-E15)*F15+(F15*1/6)*(13-E15) -> 0 | H15: =F15*14 -> 0 | I15: =I14+1 -> 2022 | J15: =COUNTIF(D13:D24,F3) -> 0 | K15: =SUMIF(D13:D24,F3,G13:G24) -> 0 | L15: =SUMIF($D$13:$D$24,F3,$H$13:$H$24) -> 0 | M15: =L15-K15 -> 0 | O15: Operacional (Turismo) - Outras
B16: 4 | G16: =(13-E16)*F16+(F16*1/6)*(13-E16) -> 0 | H16: =F16*14 -> 0 | I16: =I15+1 -> 2023 | J16: =COUNTIF(D13:D24,G3) -> 0 | K16: =SUMIF(D13:D24,G3,G13:G24) -> 0 | L16: =SUMIF($D$13:$D$24,G3,$H$13:$H$24) -> 0 | M16: =L16-K16 -> 0 | O16: Outros
B17: 5 | G17: =(13-E17)*F17+(F17*1/6)*(13-E17) -> 0 | H17: =F17*14 -> 0 | I17: =I16+1 -> 2024 | J17: =COUNTIF(D13:D24,H3) -> 0 | K17: =SUMIF(D13:D24,H3,G13:G24) -> 0 | L17: =SUMIF($D$13:$D$24,H3,$H$13:$H$24) -> 0 | M17: =L17-K17 -> 0
B18: 6 | G18: =(13-E18)*F18+(F18*1/6)*(13-E18) -> 0 | H18: =F18*14 -> 0 | I18: =I17+1 -> 2025 | J18: =COUNTIF(D13:D24,I3) -> 0 | K18: =SUMIF(D13:D24,I3,G13:G24) -> 0 | L18: =SUMIF($D$13:$D$24,I3,$H$13:$H$24) -> 0 | M18: =L18-K18 -> 0
B19: 7 | G19: =(13-E19)*F19+(F19*1/6)*(13-E19) -> 0 | H19: =F19*14 -> 0 | O19: Nível 1
B20: 8 | G20: =(13-E20)*F20+(F20*1/6)*(13-E20) -> 0 | H20: =F20*14 -> 0 | O20: Nível 2
B21: 9 | G21: =(13-E21)*F21+(F21*1/6)*(13-E21) -> 0 | H21: =F21*14 -> 0 | O21: Nível 3
B22: 10 | G22: =(13-E22)*F22+(F22*1/6)*(13-E22) -> 0 | H22: =F22*14 -> 0 | O22: Nível 4
B23: 11 | G23: =(13-E23)*F23+(F23*1/6)*(13-E23) -> 0 | H23: =F23*14 -> 0 | O23: Nível 5
B24: 12 | G24: =(13-E24)*F24+(F24*1/6)*(13-E24) -> 0 | H24: =F24*14 -> 0 | O24: Nível 6
O25: Nível 7
O26: Nível 8
B27: Área Funcional | C27: Nível de Qualificação | D27: Ano Pré-Projeto | G27: Ano Pós-Projeto
D28: Mulheres | E28: Homens | F28: Total | G28: Mulheres | H28: Homens | I28: Total
F29: =D29+E29 -> 0 | I29: =G29+H29 -> 0
F30: =D30+E30 -> 0 | I30: =G30+H30 -> 0
F31: =D31+E31 -> 0 | I31: =G31+H31 -> 0
F32: =D32+E32 -> 0 | I32: =G32+H32 -> 0
F33: =D33+E33 -> 0 | I33: =G33+H33 -> 0
F34: =D34+E34 -> 0 | I34: =G34+H34 -> 0
F35: =D35+E35 -> 0 | I35: =G35+H35 -> 0
F36: =D36+E36 -> 0 | I36: =G36+H36 -> 0
F37: =D37+E37 -> 0 | I37: =G37+H37 -> 0
F38: =D38+E38 -> 0 | I38: =G38+H38 -> 0
F39: =D39+E39 -> 0 | I39: =G39+H39 -> 0
F40: =D40+E40 -> 0 | I40: =G40+H40 -> 0
... F55: =D55+E55 -> 0 | I55: =G55+H55 -> 0
F56: =SUM(F29:F55) -> 0 | I56: =SUM(I29:I55) -> 0
B58: Contratação de Quadros Técnicos
B60: Nº | C60: Área Funcional | D60: Área de Formação | E60: Nível Qualif. | F60: Data Prevista entra | G60: Duração (meses) | H60: Estabelecimento | I60: Remuneração | J60: Tx. S. Social
B61: 1
B62: 2
B63: 3
B64: 4
B65: 5
B66: 6
B67: 7
B68: 8
B69: 9
B70: 10
B71: 11
B72: 12
... B74: 14

Sheet Faturas
B2: FATURAS PRÓFORMA / ORÇAMENTOS - INVESTIMENTO
F3: (Em Euros)
B4: Nº | C4: DESCRIÇÃO | D4: Data (mês/ano) | E4: VALOR | F4: ANO
B6: Nº | C6: OBRAS | D6: Data (mês/ano) | E6: VALOR | F6: ANO
B7: 1 | F7: =YEAR(D7) -> 1900
B8: 2 | F8: =YEAR(D8) -> 1900
B9: 3 | F9: =YEAR(D9) -> 1900
B10: 4 | F10: =YEAR(D10) -> 1900
B11: 5 | F11: =YEAR(D11) -> 1900
B12: 6 | F12: =YEAR(D12) -> 1900
B13: 7 | F13: =YEAR(D13) -> 1900
B14: 8 | F14: =YEAR(D14) -> 1900
B15: 9 | F15: =YEAR(D15) -> 1900
B16: 10 | F16: =YEAR(D16) -> 1900
B17: 11 | F17: =YEAR(D17) -> 1900
B18: 12 | F18: =YEAR(D18) -> 1900
... B22: 16 | F22: =YEAR(D22) -> 1900
E23: =SUM(E7:E22) -> 0
B25: Nº | C25: EQUIPAMENTO | D25: Data (mês/ano) | E25: VALOR | F25: ANO | G25: É Biológico?
B26: 1 | C26: Ativos 2020 | D26: 43831 | F26: =YEAR(D26) -> 2020 | G26: Não
B27: =B26+1 -> 2 | C27: Ativos 2021 | D27: 44197 | E27: =+[1]Folha2!$H$42 -> 40000 | F27: =YEAR(D27) -> 2021 | G27: Não
B28: =B27+1 -> 3 | C28: Ativos 2022 | D28: 44562 | E28: 0 | F28: =YEAR(D28) -> 2022 | G28: Não
B29: =B28+1 -> 4 | F29: =YEAR(D29) -> 1900 | G29: Não
B30: =B29+1 -> 5 | F30: =YEAR(D30) -> 1900 | G30: Não
B31: =B30+1 -> 6 | F31: =YEAR(D31) -> 1900 | G31: Não
B32: =B31+1 -> 7 | F32: =YEAR(D32) -> 1900 | G32: Não
B33: =B32+1 -> 8 | F33: =YEAR(D33) -> 1900 | G33: Não
B34: =B33+1 -> 9 | F34: =YEAR(D34) -> 1900 | G34: Não
B35: =B34+1 -> 10 | F35: =YEAR(D35) -> 1900 | G35: Não
B36: =B35+1 -> 11 | F36: =YEAR(D36) -> 1900 | G36: Não
B37: =B36+1 -> 12 | F37: =YEAR(D37) -> 1900 | G37: Não
B38: =B37+1 -> 13 | F38: =YEAR(D38) -> 1900 | G38: Não
B39: =B38+1 -> 14 | F39: =YEAR(D39) -> 1900 | G39: Não
B40: =B39+1 -> 15 | F40: =YEAR(D40) -> 1900 | G40: Não
... B60: =B59+1 -> 35 | F60: =YEAR(D60) -> 1900 | G60: Não
E61: =SUM(E26:E60) -> 40000
B63: Nº | C63: INTANGÍVEL | D63: Data (mês/ano) | E63: VALOR | F63: ANO
B64: 1 | F64: =YEAR(D64) -> 1900
B65: 2 | F65: =YEAR(D65) -> 1900
B66: 3 | F66: =YEAR(D66) -> 1900
B67: 4 | F67: =YEAR(D67) -> 1900
B68: 5 | F68: =YEAR(D68) -> 1900
B69: 6 | F69: =YEAR(D69) -> 1900
B70: 7 | F70: =YEAR(D70) -> 1900
B71: 8 | F71: =YEAR(D71) -> 1900
B72: 9 | F72: =YEAR(D72) -> 1900
B73: 10 | F73: =YEAR(D73) -> 1900
B74: 11 | F74: =YEAR(D74) -> 1900
B75: 12 | F75: =YEAR(D75) -> 1900
... B78: 15 | F78: =YEAR(D78) -> 1900
B79: =B78+1 -> 16 | F79: =YEAR(D79) -> 1900
E80: =SUM(E64:E79) -> 0
B82: Nº | C82: OUTROS ATIVOS FINANCEIROS | D82: Data (mês/ano) | E82: VALOR | F82: ANO
B83: 1 | F83: =YEAR(D83) -> 1900
B84: 2 | F84: =YEAR(D84) -> 1900
B85: 3 | F85: =YEAR(D85) -> 1900
B86: 4 | F86: =YEAR(D86) -> 1900
B87: 5 | F87: =YEAR(D87) -> 1900
B88: 6 | F88: =YEAR(D88) -> 1900
B89: 7 | F89: =YEAR(D89) -> 1900
B90: 8 | F90: =YEAR(D90) -> 1900
B91: 9 | F91: =YEAR(D91) -> 1900
B92: 10 | F92: =YEAR(D92) -> 1900
E93: =SUM(E83:E92) -> 0
B95: Nº | C95: FSE | D95: Data (mês/ano) | E95: VALOR | F95: ANO
B96: 1 | C96: FSE 2020 | D96: 43831 | E96: =+[1]Folha2!$G$43 -> 20625.25 | F96: =YEAR(D96) -> 2020
B97: 2 | C97: FSE 2021 | D97: 44197 | E97: =+[1]Folha2!$H$43 -> 18340 | F97: =YEAR(D97) -> 2021
B98: 3 | C98: FSE 2022 | D98: 44562 | E98: =+[1]Folha2!$I$43 -> 14800 | F98: =YEAR(D98) -> 2022
B99: 4 | F99: =YEAR(D99) -> 1900
B100: 5 | F100: =YEAR(D100) -> 1900
B101: 6 | F101: =YEAR(D101) -> 1900
B102: 7 | F102: =YEAR(D102) -> 1900
B103: 8 | F103: =YEAR(D103) -> 1900
B104: 9 | F104: =YEAR(D104) -> 1900
B105: 10 | F105: =YEAR(D105) -> 1900
B106: 11 | F106: =YEAR(D106) -> 1900
B107: 12 | F107: =YEAR(D107) -> 1900
B108: 13 | F108: =YEAR(D108) -> 1900
B109: 14 | F109: =YEAR(D109) -> 1900
B110: 15 | F110: =YEAR(D110) -> 1900
... B258: 163 | F258: =YEAR(D258) -> 1900
E259: =SUM(E96:E258) -> 53765.25
B261: Nº | C261: Contratação RHs | D261: Data (mês/ano) | E261: VALOR | F261: ANO
B262: 1 | F262: =YEAR(D262) -> 1900
B263: 2 | F263: =YEAR(D263) -> 1900
B264: 3 | F264: =YEAR(D264) -> 1900
B265: 4 | F265: =YEAR(D265) -> 1900
B266: 5 | F266: =YEAR(D266) -> 1900
B267: 6 | F267: =YEAR(D267) -> 1900
B268: 7 | F268: =YEAR(D268) -> 1900
B269: 8 | F269: =YEAR(D269) -> 1900
B270: 9 | F270: =YEAR(D270) -> 1900
B271: 10 | F271: =YEAR(D271) -> 1900
B272: 11 | F272: =YEAR(D272) -> 1900
B273: 12 | F273: =YEAR(D273) -> 1900
... B282: 21 | F282: =YEAR(D282) -> 1900
E283: =SUM(E262:E282) -> 0
B285: TOTAL INVESTIMENTOS GLOBAL | E285: =E283+E259+E93+E80+E61+E23 -> 93765.25
E288: Investimento Total | F288: Investimento Intern | G288: Investimento Inov | H288: Incentivo inter | I288: Incentivo Inov
B289: Obras | D289: =Pressupostos!C11 -> 2020 | E289: =SUMIF(F7:F22,D289,E7:E22) -> 0 | F289: =E289 -> 0 | G289: =E289-F289 -> 0 | H289: =F289*Pressupostos!$C$8 -> 0 | I289: =G289*Pressupostos!$C$9 -> 0
...

Sheet PlanoInvest
B2: PLANO DE INVESTIMENTO | D2: UNIDADE: EUROS
B3: RUBRICAS DO INVESTIMENTO | C3: Sujeito a iva | D3: CUSTO TOTAL DO INVESTIMENTO | E3: =Pressupostos!C11 -> 2020 | G3: =E3+1 -> 2021 | I3: =G3+1 -> 2022 | K3: =I3+1 -> 2023 | M3: =K3+1 -> 2024 | O3: =M3+1 -> 2025 | Q3: =O3+1 -> 2026 | S3: =Q3+1 -> 2027 | U3: =S3+1 -> 2028 | W3: =U3+1 -> 2029
E4: 1º SEM | F4: 2º SEM | G4: 1º SEM | H4: 2º SEM | I4: 1º SEM | J4: 2º SEM | K4: 1º SEM | L4: 2º SEM | M4: 1º SEM | N4: 2º SEM | O4: 1º SEM | P4: 2º SEM | Q4: 1º SEM | R4: 2º SEM | S4: 1º SEM | T4: 2º SEM | U4: 1º SEM | V4: 2º SEM | W4: 1º SEM | X4: 2º SEM
B5: OBRAS
A6: 1 | B6: =IF(Faturas!C7=0,"",Faturas!C7) | C6: Não | D6: =IF(Faturas!E7=0,"",Faturas!E7) | F6: =IF(Faturas!F7=$E$3,Faturas!E7,"0") -> 0 | H6: =IF(Faturas!F7=$G$3,Faturas!E7,"0") -> 0 | J6: =IF(Faturas!F7=$I$3,Faturas!E7,"0") -> 0 | L6: =IF(Faturas!F7=$K$3,Faturas!E7,"0") -> 0
A7: 2 | B7: =IF(Faturas!C8=0,"",Faturas!C8) | C7: Não | D7: =IF(Faturas!E8=0,"",Faturas!E8) | F7: =IF(Faturas!F8=$E$3,Faturas!E8,"0") -> 0 | H7: =IF(Faturas!F8=$G$3,Faturas!E8,"0") -> 0 | J7: =IF(Faturas!F8=$I$3,Faturas!E8,"0") -> 0 | L7: =IF(Faturas!F8=$K$3,Faturas!E8,"0") -> 0
A8: 3 | B8: =IF(Faturas!C9=0,"",Faturas!C9) | C8: Não | D8: =IF(Faturas!E9=0,"",Faturas!E9) | F8: =IF(Faturas!F9=$E$3,Faturas!E9,"0") -> 0 | H8: =IF(Faturas!F9=$G$3,Faturas!E9,"0") -> 0 | J8: =IF(Faturas!F9=$I$3,Faturas!E9,"0") -> 0 | L8: =IF(Faturas!F9=$K$3,Faturas!E9,"0") -> 0
A9: 4 | B9: =IF(Faturas!C10=0,"",Faturas!C10) | C9: Não | D9: =IF(Faturas!E10=0,"",Faturas!E10) | F9: =IF(Faturas!F10=$E$3,Faturas!E10,"0") -> 0 | H9: =IF(Faturas!F10=$G$3,Faturas!E10,"0") -> 0 | J9: =IF(Faturas!F10=$I$3,Faturas!E10,"0") -> 0 | L9: =IF(Faturas!F10=$K$3,Faturas!E10,"0") -> 0
A10: 5 | B10: =IF(Faturas!C11=0,"",Faturas!C11) | C10: Não | D10: =IF(Faturas!E11=0,"",Faturas!E11) | F10: =IF(Faturas!F11=$E$3,Faturas!E11,"0") -> 0 | H10: =IF(Faturas!F11=$G$3,Faturas!E11,"0") -> 0 | J10: =IF(Faturas!F11=$I$3,Faturas!E11,"0") -> 0 | L10: =IF(Faturas!F11=$K$3,Faturas!E11,"0") -> 0
A11: 6 | B11: =IF(Faturas!C12=0,"",Faturas!C12) | C11: Não | D11: =IF(Faturas!E12=0,"",Faturas!E12) | F11: =IF(Faturas!F12=$E$3,Faturas!E12,"0") -> 0 | H11: =IF(Faturas!F12=$G$3,Faturas!E12,"0") -> 0 | J11: =IF(Faturas!F12=$I$3,Faturas!E12,"0") -> 0 | L11: =IF(Faturas!F12=$K$3,Faturas!E12,"0") -> 0
A12: 7 | B12: =IF(Faturas!C13=0,"",Faturas!C13) | C12: Não | D12: =IF(Faturas!E13=0,"",Faturas!E13) | F12: =IF(Faturas!F13=$E$3,Faturas!E13,"0") -> 0 | H12: =IF(Faturas!F13=$G$3,Faturas!E13,"0") -> 0 | J12: =IF(Faturas!F13=$I$3,Faturas!E13,"0") -> 0 | L12: =IF(Faturas!F13=$K$3,Faturas!E13,"0") -> 0
A13: 8 | B13: =IF(Faturas!C14=0,"",Faturas!C14) | C13: Não | D13: =IF(Faturas!E14=0,"",Faturas!E14) | F13: =IF(Faturas!F14=$E$3,Faturas!E14,"0") -> 0 | H13: =IF(Faturas!F14=$G$3,Faturas!E14,"0") -> 0 | J13: =IF(Faturas!F14=$I$3,Faturas!E14,"0") -> 0 | L13: =IF(Faturas!F14=$K$3,Faturas!E14,"0") -> 0
A14: 9 | B14: =IF(Faturas!C15=0,"",Faturas!C15) | C14: Não | D14: =IF(Faturas!E15=0,"",Faturas!E15) | F14: =IF(Faturas!F15=$E$3,Faturas!E15,"0") -> 0 | H14: =IF(Faturas!F15=$G$3,Faturas!E15,"0") -> 0 | J14: =IF(Faturas!F15=$I$3,Faturas!E15,"0") -> 0 | L14: =IF(Faturas!F15=$K$3,Faturas!E15,"0") -> 0
A15: 10 | B15: =IF(Faturas!C16=0,"",Faturas!C16) | C15: Não | D15: =IF(Faturas!E16=0,"",Faturas!E16) | F15: =IF(Faturas!F16=$E$3,Faturas!E16,"0") -> 0 | H15: =IF(Faturas!F16=$G$3,Faturas!E16,"0") -> 0 | J15: =IF(Faturas!F16=$I$3,Faturas!E16,"0") -> 0 | L15: =IF(Faturas!F16=$K$3,Faturas!E16,"0") -> 0
A16: 11 | B16: =IF(Faturas!C17=0,"",Faturas!C17) | C16: Não | D16: =IF(Faturas!E17=0,"",Faturas!E17) | F16: =IF(Faturas!F17=$E$3,Faturas!E17,"0") -> 0 | H16: =IF(Faturas!F17=$G$3,Faturas!E17,"0") -> 0 | J16: =IF(Faturas!F17=$I$3,Faturas!E17,"0") -> 0 | L16: =IF(Faturas!F17=$K$3,Faturas!E17,"0") -> 0
A17: 12 | B17: =IF(Faturas!C18=0,"",Faturas!C18) | C17: Não | D17: =IF(Faturas!E18=0,"",Faturas!E18) | F17: =IF(Faturas!F18=$E$3,Faturas!E18,"0") -> 0 | H17: =IF(Faturas!F18=$G$3,Faturas!E18,"0") -> 0 | J17: =IF(Faturas!F18=$I$3,Faturas!E18,"0") -> 0 | L17: =IF(Faturas!F18=$K$3,Faturas!E18,"0") -> 0
... A21: 16 | B21: =IF(Faturas!C22=0,"",Faturas!C22) | C21: Não | D21: =IF(Faturas!E22=0,"",Faturas!E22) | F21: =IF(Faturas!F22=$E$3,Faturas!E22,"0") -> 0 | H21: =IF(Faturas!F22=$G$3,Faturas!E22,"0") -> 0 | J21: =IF(Faturas!F22=$I$3,Faturas!E22,"0") -> 0 | L21: =IF(Faturas!F22=$K$3,Faturas!E22,"0") -> 0
B22: SUBTOTAL | D22: =SUM(D6:D21) -> 0 | E22: =SUM(E6:E21) -> 0 | F22: =SUM(F6:F21) -> 0 | G22: =SUM(G6:G21) -> 0 | H22: =SUM(H6:H21) -> 0 | I22: =SUM(I6:I21) -> 0 | J22: =SUM(J6:J21) -> 0 | K22: =SUM(K6:K21) -> 0 | ... X22: =SUM(X6:X21) -> 0
B23: EQUIPAMENTO
A24: 1 | B24: =IF(Faturas!C26=0,"",Faturas!C26) -> Ativos 2020 | C24: Sim | D24: =IF(Faturas!E26=0,"",Faturas!E26) | F24: =IF(Faturas!F26=$E$3,Faturas!E26,"0") -> 0 | H24: =IF(Faturas!F26=$G$3,Faturas!E26,"0") -> 0 | J24: =IF(Faturas!F26=$I$3,Faturas!E26,"0") -> 0 | L24: =IF(Faturas!F26=$K$3,Faturas!E26,"0") -> 0
A25: 2 | B25: =IF(Faturas!C27=0,"",Faturas!C27) -> Ativos 2021 | C25: Sim | D25: =IF(Faturas!E27=0,"",Faturas!E27) -> 40000 | F25: =IF(Faturas!F27=$E$3,Faturas!E27,"0") -> 0 | H25: =IF(Faturas!F27=$G$3,Faturas!E27,"0") -> 40000 | J25: =IF(Faturas!F27=$I$3,Faturas!E27,"0") -> 0 | L25: =IF(Faturas!F27=$K$3,Faturas!E27,"0") -> 0
A26: 3 | B26: =IF(Faturas!C28=0,"",Faturas!C28) -> Ativos 2022 | C26: Sim | D26: =IF(Faturas!E28=0,"",Faturas!E28) | F26: =IF(Faturas!F28=$E$3,Faturas!E28,"0") -> 0 | H26: =IF(Faturas!F28=$G$3,Faturas!E28,"0") -> 0 | J26: =IF(Faturas!F28=$I$3,Faturas!E28,"0") -> 0 | L26: =IF(Faturas!F28=$K$3,Faturas!E28,"0") -> 0
A27: 4 | B27: =IF(Faturas!C29=0,"",Faturas!C29) | C27: Sim | D27: =IF(Faturas!E29=0,"",Faturas!E29) | F27: =IF(Faturas!F29=$E$3,Faturas!E29,"0") -> 0 | H27: =IF(Faturas!F29=$G$3,Faturas!E29,"0") -> 0 | J27: =IF(Faturas!F29=$I$3,Faturas!E29,"0") -> 0 | L27: =IF(Faturas!F29=$K$3,Faturas!E29,"0") -> 0
A28: 5 | B28: =IF(Faturas!C30=0,"",Faturas!C30) | C28: Sim | D28: =IF(Faturas!E30=0,"",Faturas!E30) | F28: =IF(Faturas!F30=$E$3,Faturas!E30,"0") -> 0 | H28: =IF(Faturas!F30=$G$3,Faturas!E30,"0") -> 0 | J28: =IF(Faturas!F30=$I$3,Faturas!E30,"0") -> 0 | L28: =IF(Faturas!F30=$K$3,Faturas!E30,"0") -> 0
A29: 6 | B29: =IF(Faturas!C31=0,"",Faturas!C31) | C29: Sim | D29: =IF(Faturas!E31=0,"",Faturas!E31) | F29: =IF(Faturas!F31=$E$3,Faturas!E31,"0") -> 0 | H29: =IF(Faturas!F31=$G$3,Faturas!E31,"0") -> 0 | J29: =IF(Faturas!F31=$I$3,Faturas!E31,"0") -> 0 | L29: =IF(Faturas!F31=$K$3,Faturas!E31,"0") -> 0
A30: 7 | B30: =IF(Faturas!C32=0,"",Faturas!C32) | C30: Sim | D30: =IF(Faturas!E32=0,"",Faturas!E32) | F30: =IF(Faturas!F32=$E$3,Faturas!E32,"0") -> 0 | H30: =IF(Faturas!F32=$G$3,Faturas!E32,"0") -> 0 | J30: =IF(Faturas!F32=$I$3,Faturas!E32,"0") -> 0 | L30: =IF(Faturas!F32=$K$3,Faturas!E32,"0") -> 0
A31: 8 | B31: =IF(Faturas!C33=0,"",Faturas!C33) | C31: Sim | D31: =IF(Faturas!E33=0,"",Faturas!E33) | F31: =IF(Faturas!F33=$E$3,Faturas!E33,"0") -> 0 | H31: =IF(Faturas!F33=$G$3,Faturas!E33,"0") -> 0 | J31: =IF(Faturas!F33=$I$3,Faturas!E33,"0") -> 0 | L31: =IF(Faturas!F33=$K$3,Faturas!E33,"0") -> 0
A32: 9 | B32: =IF(Faturas!C34=0,"",Faturas!C34) | C32: Sim | D32: =IF(Faturas!E34=0,"",Faturas!E34) | F32: =IF(Faturas!F34=$E$3,Faturas!E34,"0") -> 0 | H32: =IF(Faturas!F34=$G$3,Faturas!E34,"0") -> 0 | J32: =IF(Faturas!F34=$I$3,Faturas!E34,"0") -> 0 | L32: =IF(Faturas!F34=$K$3,Faturas!E34,"0") -> 0
A33: 10 | B33: =IF(Faturas!C35=0,"",Faturas!C35) | C33: Sim | D33: =IF(Faturas!E35=0,"",Faturas!E35) | F33: =IF(Faturas!F35=$E$3,Faturas!E35,"0") -> 0 | H33: =IF(Faturas!F35=$G$3,Faturas!E35,"0") -> 0 | J33: =IF(Faturas!F35=$I$3,Faturas!E35,"0") -> 0 | L33: =IF(Faturas!F35=$K$3,Faturas!E35,"0") -> 0
A34: 11 | B34: =IF(Faturas!C36=0,"",Faturas!C36) | C34: Sim | D34: =IF(Faturas!E36=0,"",Faturas!E36) | F34: =IF(Faturas!F36=$E$3,Faturas!E36,"0") -> 0 | H34: =IF(Faturas!F36=$G$3,Faturas!E36,"0") -> 0 | J34: =IF(Faturas!F36=$I$3,Faturas!E36,"0") -> 0 | L34: =IF(Faturas!F36=$K$3,Faturas!E36,"0") -> 0
A35: 12 | B35: =IF(Faturas!C37=0,"",Faturas!C37) | C35: Sim | D35: =IF(Faturas!E37=0,"",Faturas!E37) | F35: =IF(Faturas!F37=$E$3,Faturas!E37,"0") -> 0 | H35: =IF(Faturas!F37=$G$3,Faturas!E37,"0") -> 0 | J35: =IF(Faturas!F37=$I$3,Faturas!E37,"0") -> 0 | L35: =IF(Faturas!F37=$K$3,Faturas!E37,"0") -> 0
... A58: 35 | B58: =IF(Faturas!C60=0,"",Faturas!C60) | C58: Sim | D58: =IF(Faturas!E60=0,"",Faturas!E60) | F58: =IF(Faturas!F60=$E$3,Faturas!E60,"0") -> 0 | H58: =IF(Faturas!F60=$G$3,Faturas!E60,"0") -> 0 | J58: =IF(Faturas!F60=$I$3,Faturas!E60,"0") -> 0 | L58: =IF(Faturas!F60=$K$3,Faturas!E60,"0") -> 0
B59: SUB-TOTAL | D59: =SUM(D24:D58) -> 40000 | E59: =SUM(E24:E58) -> 0 | F59: =SUM(F24:F58) -> 0 | G59: =SUM(G24:G58) -> 0 | H59: =SUM(H24:H58) -> 40000 | I59: =SUM(I24:I58) -> 0 | J59: =SUM(J24:J58) -> 0 | K59: =SUM(K24:K58) -> 0 | ... X59: =SUM(X24:X58) -> 0
B60: INTANGÍVEL
A61: 1 | B61: =IF(Faturas!C64=0,"",Faturas!C64) | C61: Sim | D61: =IF(Faturas!E64=0,"",Faturas!E64) | F61: =IF(Faturas!F64=$E$3,Faturas!E64,"0") -> 0 | H61: =IF(Faturas!F64=$G$3,Faturas!E64,"0") -> 0 | J61: =IF(Faturas!F64=$I$3,Faturas!E64,"0") -> 0 | L61: =IF(Faturas!F64=$K$3,Faturas!E64,"0") -> 0
A62: 2 | B62: =IF(Faturas!C65=0,"",Faturas!C65) | C62: Sim | D62: =IF(Faturas!E65=0,"",Faturas!E65) | F62: =IF(Faturas!F65=$E$3,Faturas!E65,"0") -> 0 | H62: =IF(Faturas!F65=$G$3,Faturas!E65,"0") -> 0 | J62: =IF(Faturas!F65=$I$3,Faturas!E65,"0") -> 0 | L62: =IF(Faturas!F65=$K$3,Faturas!E65,"0") -> 0
A63: 3 | B63: =IF(Faturas!C66=0,"",Faturas!C66) | C63: Sim | D63: =IF(Faturas!E66=0,"",Faturas!E66) | F63: =IF(Faturas!F66=$E$3,Faturas!E66,"0") -> 0 | H63: =IF(Faturas!F66=$G$3,Faturas!E66,"0") -> 0 | J63: =IF(Faturas!F66=$I$3,Faturas!E66,"0") -> 0 | L63: =IF(Faturas!F66=$K$3,Faturas!E66,"0") -> 0
A64: 4 | B64: =IF(Faturas!C67=0,"",Faturas!C67) | C64: Sim | D64: =IF(Faturas!E67=0,"",Faturas!E67) | F64: =IF(Faturas!F67=$E$3,Faturas!E67,"0") -> 0 | H64: =IF(Faturas!F67=$G$3,Faturas!E67,"0") -> 0 | J64: =IF(Faturas!F67=$I$3,Faturas!E67,"0") -> 0 | L64: =IF(Faturas!F67=$K$3,Faturas!E67,"0") -> 0
A65: 5 | B65: =IF(Faturas!C68=0,"",Faturas!C68) | C65: Sim | D65: =IF(Faturas!E68=0,"",Faturas!E68) | F65: =IF(Faturas!F68=$E$3,Faturas!E68,"0") -> 0 | H65: =IF(Faturas!F68=$G$3,Faturas!E68,"0") -> 0 | J65: =IF(Faturas!F68=$I$3,Faturas!E68,"0") -> 0 | L65: =IF(Faturas!F68=$K$3,Faturas!E68,"0") -> 0
A66: 6 | B66: =IF(Faturas!C69=0,"",Faturas!C69) | C66: Sim | D66: =IF(Faturas!E69=0,"",Faturas!E69) | F66: =IF(Faturas!F69=$E$3,Faturas!E69,"0") -> 0 | H66: =IF(Faturas!F69=$G$3,Faturas!E69,"0") -> 0 | J66: =IF(Faturas!F69=$I$3,Faturas!E69,"0") -> 0 | L66: =IF(Faturas!F69=$K$3,Faturas!E69,"0") -> 0
A67: 7 | B67: =IF(Faturas!C70=0,"",Faturas!C70) | C67: Sim | D67: =IF(Faturas!E70=0,"",Faturas!E70) | F67: =IF(Faturas!F70=$E$3,Faturas!E70,"0") -> 0 | H67: =IF(Faturas!F70=$G$3,Faturas!E70,"0") -> 0 | J67: =IF(Faturas!F70=$I$3,Faturas!E70,"0") -> 0 | L67: =IF(Faturas!F70=$K$3,Faturas!E70,"0") -> 0
A68: 8 | B68: =IF(Faturas!C71=0,"",Faturas!C71) | C68: Sim | D68: =IF(Faturas!E71=0,"",Faturas!E71) | F68: =IF(Faturas!F71=$E$3,Faturas!E71,"0") -> 0 | H68: =IF(Faturas!F71=$G$3,Faturas!E71,"0") -> 0 | J68: =IF(Faturas!F71=$I$3,Faturas!E71,"0") -> 0 | L68: =IF(Faturas!F71=$K$3,Faturas!E71,"0") -> 0
A69: 9 | B69: =IF(Faturas!C72=0,"",Faturas!C72) | C69: Sim | D69: =IF(Faturas!E72=0,"",Faturas!E72) | F69: =IF(Faturas!F72=$E$3,Faturas!E72,"0") -> 0 | H69: =IF(Faturas!F72=$G$3,Faturas!E72,"0") -> 0 | J69: =IF(Faturas!F72=$I$3,Faturas!E72,"0") -> 0 | L69: =IF(Faturas!F72=$K$3,Faturas!E72,"0") -> 0
A70: 10 | B70: =IF(Faturas!C73=0,"",Faturas!C73) | C70: Sim | D70: =IF(Faturas!E73=0,"",Faturas!E73) | F70: =IF(Faturas!F73=$E$3,Faturas!E73,"0") -> 0 | H70: =IF(Faturas!F73=$G$3,Faturas!E73,"0") -> 0 | J70: =IF(Faturas!F73=$I$3,Faturas!E73,"0") -> 0 | L70: =IF(Faturas!F73=$K$3,Faturas!E73,"0") -> 0
A71: 11 | B71: =IF(Faturas!C74=0,"",Faturas!C74) | C71: Sim | D71: =IF(Faturas!E74=0,"",Faturas!E74) | F71: =IF(Faturas!F74=$E$3,Faturas!E74,"0") -> 0 | H71: =IF(Faturas!F74=$G$3,Faturas!E74,"0") -> 0 | J71: =IF(Faturas!F74=$I$3,Faturas!E74,"0") -> 0 | L71: =IF(Faturas!F74=$K$3,Faturas!E74,"0") -> 0
A72: 12 | B72: =IF(Faturas!C75=0,"",Faturas!C75) | C72: Sim | D72: =IF(Faturas!E75=0,"",Faturas!E75) | F72: =IF(Faturas!F75=$E$3,Faturas!E75,"0") -> 0 | H72: =IF(Faturas!F75=$G$3,Faturas!E75,"0") -> 0 | J72: =IF(Faturas!F75=$I$3,Faturas!E75,"0") -> 0 | L72: =IF(Faturas!F75=$K$3,Faturas!E75,"0") -> 0
... A76: 16 | B76: =IF(Faturas!C79=0,"",Faturas!C79) | C76: Sim | D76: =IF(Faturas!E79=0,"",Faturas!E79) | F76: =IF(Faturas!F79=$E$3,Faturas!E79,"0") -> 0 | H76: =IF(Faturas!F79=$G$3,Faturas!E79,"0") -> 0 | J76: =IF(Faturas!F79=$I$3,Faturas!E79,"0") -> 0 | L76: =IF(Faturas!F79=$K$3,Faturas!E79,"0") -> 0
B77: SUB-TOTAL | D77: =SUM(D61:D76) -> 0 | E77: =SUM(E61:E76) -> 0 | F77: =SUM(F61:F76) -> 0 | G77: =SUM(G61:G76) -> 0 | H77: =SUM(H61:H76) -> 0 | I77: =SUM(I61:I76) -> 0 | J77: =SUM(J61:J76) -> 0 | K77: =SUM(K61:K76) -> 0 | ... X77: =SUM(X61:X76) -> 0
B78: OUTROS ATIVOS FINANCEIROS | D78: =Faturas!E93 -> 0
B79: FUNDO MANEIO | D79: =SUM(E79:L79) -> 356124.16 | F79: =IF(FM!H18<0,0,FM!H18) -> 247467.67 | H79: =IF(FM!I18<0,0,FM!I18) -> 32679.35 | J79: =IF(FM!J18<0,0,FM!J18) -> 37892.748 | L79: =IF(FM!K18<0,0,FM!K18) -> 38084.394 | N79: =IF(FM!L18<0,0,FM!L18) -> 14004.335 | P79: =IF(FM!M18<0,0,FM!M18) -> 12982.347 | R79: =IF(FM!N18<0,0,FM!N18) -> 14800.077 | T79: =IF(FM!O18<0,0,FM!O18) -> 15097.43 | V79: =IF(FM!P18<0,0,FM!P18) -> 12829.409 | X79: =IF(FM!Q18<0,0,FM!Q18) -> 15710.178
B80: TOTAL | D80: =D22+D59+D77+D78+D79 -> 396124.16 | E80: =E22+E59+E77+E78+E79 -> 0 | F80: =F22+F59+F77+F78+F79 -> 247467.67 | G80: =G22+G59+G77+G78+G79 -> 0 | H80: =H22+H59+H77+H78+H79 -> 72679.35 | I80: =I22+I59+I77+I78+I79 -> 0 | J80: =J22+J59+J77+J78+J79 -> 37892.748 | K80: =K22+K59+K77+K78+K79 -> 0 | ... X80: =X22+X59+X77+X78+X79 -> 15710.178
B82: Inv | C82: =D80-D79 -> 40000 | D82: Ano | E82: =Pressupostos!C11 -> 2020 | F82: =E82 -> 2020 | G82: =E82+1 -> 2021 | H82: =G82 -> 2021 | I82: =G82+1 -> 2022 | J82: =I82 -> 2022 | K82: =I82+1 -> 2023 | L82: =K82 -> 2023 | M82: =K82+1 -> 2024 | N82: =M82 -> 2024 | O82: =M82+1 -> 2025 | P82: =O82 -> 2025 | Q82: =O82+1 -> 2026 | R82: =Q82 -> 2026 | S82: =Q82+1 -> 2027 | T82: =S82 -> 2027 | U82: =S82+1 -> 2028 | V82: =U82 -> 2028 | W82: =U82+1 -> 2029 | X82: =W82 -> 2029
B83: Facturas | C83: =Faturas!E23+Faturas!E61+Faturas!E80+Faturas!E93 -> 40000 | D83: Semestre | E83: I | F83: II | G83: I | H83: II | I83: I | J83: II | K83: I | L83: II | M83: I | N83: II | O83: I | P83: II | Q83: I | R83: II | S83: I | T83: II | U83: I | V83: II | W83: I | X83: II
B84: Dif | C84: =C82-C83 -> 0 | D84: Inv. Tangível | E84: =SUM(E6:E21)+SUMIF(Faturas!$G$26:$G$60,"Não",E24:E58) -> 0 | F84: =SUM(F6:F21)+SUMIF(Faturas!$G$26:$G$60,"Não",F24:F58) -> 0 | G84: =SUM(G6:G21)+SUMIF(Faturas!$G$26:$G$60,"Não",G24:G58) -> 0 | H84: =SUM(H6:H21)+SUMIF(Faturas!$G$26:$G$60,"Não",H24:H58) -> 40000 | I84: =SUM(I6:I21)+SUMIF(Faturas!$G$26:$G$60,"Não",I24:I58) -> 0 | J84: =SUM(J6:J21)+SUMIF(Faturas!$G$26:$G$60,"Não",J24:J58) -> 0 | K84: =SUM(K6:K21)+SUMIF(Faturas!$G$26:$G$60,"Não",K24:K58) -> 0 | L84: =SUM(L6:L21)+SUMIF(Faturas!$G$26:$G$60,"Não",L24:L58) -> 0 | ... X84: =SUM(X6:X21)+SUMIF(Faturas!$G$26:$G$60,"Não",X24:X58) -> 0
D85: Inv. Tangível Bio | E85: =SUM(E6:E21)+SUMIF(Faturas!$G$26:$G$60,"Sim",E24:E58) -> 0 | F85: =SUM(F6:F21)+SUMIF(Faturas!$G$26:$G$60,"Sim",F24:F58) -> 0 | G85: =SUM(G6:G21)+SUMIF(Faturas!$G$26:$G$60,"Sim",G24:G58) -> 0 | H85: =SUM(H6:H21)+SUMIF(Faturas!$G$26:$G$60,"Sim",H24:H58) -> 0 | I85: =SUM(I6:I21)+SUMIF(Faturas!$G$26:$G$60,"Sim",I24:I58) -> 0 | J85: =SUM(J6:J21)+SUMIF(Faturas!$G$26:$G$60,"Sim",J24:J58) -> 0 | K85: =SUM(K6:K21)+SUMIF(Faturas!$G$26:$G$60,"Sim",K24:K58) -> 0 | L85: =SUM(L6:L21)+SUMIF(Faturas!$G$26:$G$60,"Sim",L24:L58) -> 0 | ... X85: =SUM(X6:X21)+SUMIF(Faturas!$G$26:$G$60,"Sim",X24:X58) -> 0
D86: Inv. Intangível | E86: =SUM(E61:E76) -> 0 | F86: =SUM(F61:F76) -> 0 | G86: =SUM(G61:G76) -> 0 | H86: =SUM(H61:H76) -> 0 | I86: =SUM(I61:I76) -> 0 | J86: =SUM(J61:J76) -> 0 | K86: =SUM(K61:K76) -> 0 | L86: =SUM(L61:L76) -> 0 | ... X86: =SUM(X61:X76) -> 0
D87: Tot. Inv. Imob. | E87: =SUM(E84:E86) -> 0 | F87: =SUM(F84:F86) -> 0 | G87: =SUM(G84:G86) -> 0 | H87: =SUM(H84:H86) -> 40000 | I87: =SUM(I84:I86) -> 0 | J87: =SUM(J84:J86) -> 0 | K87: =SUM(K84:K86) -> 0 | L87: =SUM(L84:L86) -> 0 | ... X87: =SUM(X84:X86) -> 0
D88: Part. Financ. | E88: =E78 -> 0 | F88: =F78 -> 0 | G88: =G78 -> 0 | H88: =H78 -> 0 | I88: =I78 -> 0 | J88: =J78 -> 0 | K88: =K78 -> 0 | L88: =L78 -> 0 | ... X88: =X78 -> 0
D89: IVA | E89: =(SUMIF($C$6:$C$21,"Sim",E6:E21)+SUMIF($C$24:$C$58,"Sim",E24:E58)+SUMIF($C$61:$C$76,"Sim",E61:E76))*SUMIF(Pressupostos!$C$16:$L$16,E$82,Pressupostos!$C$27:$L$27) -> 0 | F89: =(SUMIF($C$6:$C$21,"Sim",F6:F21)+SUMIF($C$24:$C$58,"Sim",F24:F58)+SUMIF($C$61:$C$76,"Sim",F61:F76))*SUMIF(Pressupostos!$C$16:$L$16,F$82,Pressupostos!$C$27:$L$27) -> 0 | G89: =(SUMIF($C$6:$C$21,"Sim",G6:G21)+SUMIF($C$24:$C$58,"Sim",G24:G58)+SUMIF($C$61:$C$76,"Sim",G61:G76))*SUMIF(Pressupostos!$C$16:$L$16,G$82,Pressupostos!$C$27:$L$27) -> 0 | H89: =(SUMIF($C$6:$C$21,"Sim",H6:H21)+SUMIF($C$24:$C$58,"Sim",H24:H58)+SUMIF($C$61:$C$76,"Sim",H61:H76))*SUMIF(Pressupostos!$C$16:$L$16,H$82,Pressupostos!$C$27:$L$27) -> 9200 | I89: =(SUMIF($C$6:$C$21,"Sim",I6:I21)+SUMIF($C$24:$C$58,"Sim",I24:I58)+SUMIF($C$61:$C$76,"Sim",I61:I76))*SUMIF(Pressupostos!$C$16:$L$16,I$82,Pressupostos!$C$27:$L$27) -> 0 | J89: =(SUMIF($C$6:$C$21,"Sim",J6:J21)+SUMIF($C$24:$C$58,"Sim",J24:J58)+SUMIF($C$61:$C$76,"Sim",J61:J76))*SUMIF(Pressupostos!$C$16:$L$16,J$82,Pressupostos!$C$27:$L$27) -> 0 | K89: =(SUMIF($C$6:$C$21,"Sim",K6:K21)+SUMIF($C$24:$C$58,"Sim",K24:K58)+SUMIF($C$61:$C$76,"Sim",K61:K76))*SUMIF(Pressupostos!$C$16:$L$16,K$82,Pressupostos!$C$27:$L$27) -> 0 | L89: =(SUMIF($C$6:$C$21,"Sim",L6:L21)+SUMIF($C$24:$C$58,"Sim",L24:L58)+SUMIF($C$61:$C$76,"Sim",L61:L76))*SUMIF(Pressupostos!$C$16:$L$16,L$82,Pressupostos!$C$27:$L$27) -> 0 | ... X89: =(SUMIF($C$6:$C$21,"Sim",X6:X21)+SUMIF($C$24:$C$58,"Sim",X24:X58)+SUMIF($C$61:$C$76,"Sim",X61:X76))*SUMIF(Pressupostos!$C$16:$L$16,X$82,Pressupostos!$C$27:$L$27) -> 0
C92: =E3 -> 2020 | D92: =C92+1 -> 2021 | E92: =D92+1 -> 2022 | F92: =E92+1 -> 2023 | G92: =F92+1 -> 2024 | H92: =G92+1 -> 2025 | I92: =H92+1 -> 2026 | J92: =I92+1 -> 2027 | K92: =J92+1 -> 2028 | L92: =K92+1 -> 2029
B93: Determinação do IVA dedutível | C93: =SUMIF($E$82:$X$82,C$92,$E$89:$X$89) -> 0 | D93: =SUMIF($E$82:$X$82,D$92,$E$89:$X$89) -> 9200 | E93: =SUMIF($E$82:$X$82,E$92,$E$89:$X$89) -> 0 | F93: =SUMIF($E$82:$X$82,F$92,$E$89:$X$89) -> 0 | G93: =SUMIF($E$82:$X$82,G$92,$E$89:$X$89) -> 0 | H93: =SUMIF($E$82:$X$82,H$92,$E$89:$X$89) -> 0 | I93: =SUMIF($E$82:$X$82,I$92,$E$89:$X$89) -> 0 | J93: =SUMIF($E$82:$X$82,J$92,$E$89:$X$89) -> 0 | ... L93: =SUMIF($E$82:$X$82,L$92,$E$89:$X$89) -> 0
B95: Total de Investimento por ano
B96: Imobilizado Tangível | C96: =SUMIF($E$82:$X$82,C$92,$E84:$X84) -> 0 | D96: =SUMIF($E$82:$X$82,D$92,$E84:$X84) -> 40000 | E96: =SUMIF($E$82:$X$82,E$92,$E84:$X84) -> 0 | F96: =SUMIF($E$82:$X$82,F$92,$E84:$X84) -> 0 | G96: =SUMIF($E$82:$X$82,G$92,$E84:$X84) -> 0 | H96: =SUMIF($E$82:$X$82,H$92,$E84:$X84) -> 0 | I96: =SUMIF($E$82:$X$82,I$92,$E84:$X84) -> 0 | J96: =SUMIF($E$82:$X$82,J$92,$E84:$X84) -> 0 | ... L96: =SUMIF($E$82:$X$82,L$92,$E84:$X84) -> 0
B97: Imobilizado Tangível - Biológico | C97: =SUMIF($E$82:$X$82,C$92,$E85:$X85) -> 0 | D97: =SUMIF($E$82:$X$82,D$92,$E85:$X85) -> 0 | E97: =SUMIF($E$82:$X$82,E$92,$E85:$X85) -> 0 | F97: =SUMIF($E$82:$X$82,F$92,$E85:$X85) -> 0 | G97: =SUMIF($E$82:$X$82,G$92,$E85:$X85) -> 0 | H97: =SUMIF($E$82:$X$82,H$92,$E85:$X85) -> 0 | I97: =SUMIF($E$82:$X$82,I$92,$E85:$X85) -> 0 | J97: =SUMIF($E$82:$X$82,J$92,$E85:$X85) -> 0 | ... L97: =SUMIF($E$82:$X$82,L$92,$E85:$X85) -> 0
B98: Imobilizado Intangível | C98: =SUMIF($E$82:$X$82,C$92,$E86:$X86) -> 0 | D98: =SUMIF($E$82:$X$82,D$92,$E86:$X86) -> 0 | E98: =SUMIF($E$82:$X$82,E$92,$E86:$X86) -> 0 | F98: =SUMIF($E$82:$X$82,F$92,$E86:$X86) -> 0 | G98: =SUMIF($E$82:$X$82,G$92,$E86:$X86) -> 0 | H98: =SUMIF($E$82:$X$82,H$92,$E86:$X86) -> 0 | I98: =SUMIF($E$82:$X$82,I$92,$E86:$X86) -> 0 | J98: =SUMIF($E$82:$X$82,J$92,$E86:$X86) -> 0 | ... L98: =SUMIF($E$82:$X$82,L$92,$E86:$X86) -> 0
B99: Outros Ativos Financeiros | C99: =SUMIF($E$82:$X$82,C$92,$E88:$X88) -> 0 | D99: =SUMIF($E$82:$X$82,D$92,$E88:$X88) -> 0 | E99: =SUMIF($E$82:$X$82,E$92,$E88:$X88) -> 0 | F99: =SUMIF($E$82:$X$82,F$92,$E88:$X88) -> 0 | G99: =SUMIF($E$82:$X$82,G$92,$E88:$X88) -> 0 | H99: =SUMIF($E$82:$X$82,H$92,$E88:$X88) -> 0 | I99: =SUMIF($E$82:$X$82,I$92,$E88:$X88) -> 0 | J99: =SUMIF($E$82:$X$82,J$92,$E88:$X88) -> 0 | ... L99: =SUMIF($E$82:$X$82,L$92,$E88:$X88) -> 0
B100: Total de Investimento por ano | C100: =SUM(C96:C99) -> 0 | D100: =SUM(D96:D99) -> 40000 | E100: =SUM(E96:E99) -> 0 | F100: =SUM(F96:F99) -> 0 | G100: =SUM(G96:G99) -> 0 | H100: =SUM(H96:H99) -> 0 | I100: =SUM(I96:I99) -> 0 | J100: =SUM(J96:J99) -> 0 | ... L100: =SUM(L96:L99) -> 0

Sheet Amortização
B2: PLANO DE AMORTIZAÇÃO | K2: UNIDADE: EUROS
B3: RUBRICAS DO INVESTIMENTO | C3: TAXA | D3: VALOR | E3: =Pressupostos!C11 -> 2020 | F3: =E3+1 -> 2021 | G3: =F3+1 -> 2022 | H3: =G3+1 -> 2023 | I3: =H3+1 -> 2024 | J3: =I3+1 -> 2025 | K3: =J3+1 -> 2026 | L3: =K3+1 -> 2027 | M3: =L3+1 -> 2028 | N3: =M3+1 -> 2029 | O3: VALOR RESIDUAL
B5: OBRAS
A6: 1 | B6: =IF(Faturas!C7=0,"",Faturas!C7) | C6: 0 | D6: =IF(Faturas!E7=0,"",Faturas!E7) | K6: =IF($B6="","",IF($C6=0,0,IF(K$3-$E$3<1/$C6,$D6*$C6,0))) | L6: =IF($B6="","",IF($C6=0,0,IF(L$3-$E$3<1/$C6,$D6*$C6,0))) | M6: =IF($B6="","",IF($C6=0,0,IF(M$3-$E$3<1/$C6,$D6*$C6,0))) | N6: =IF($B6="","",IF($C6=0,0,IF(N$3-$E$3<1/$C6,$D6*$C6,0))) | O6: =IF($B6="","",D6-SUM(E6:N6))
A7: 2 | B7: =IF(Faturas!C8=0,"",Faturas!C8) | C7: 0 | D7: =IF(Faturas!E8=0,"",Faturas!E8) | K7: =IF($B7="","",IF($C7=0,0,IF(K$3-$E$3<1/$C7,$D7*$C7,0))) | L7: =IF($B7="","",IF($C7=0,0,IF(L$3-$E$3<1/$C7,$D7*$C7,0))) | M7: =IF($B7="","",IF($C7=0,0,IF(M$3-$E$3<1/$C7,$D7*$C7,0))) | N7: =IF($B7="","",IF($C7=0,0,IF(N$3-$E$3<1/$C7,$D7*$C7,0))) | O7: =IF($B7="","",D7-SUM(E7:N7))
A8: 3 | B8: =IF(Faturas!C9=0,"",Faturas!C9) | C8: 0 | D8: =IF(Faturas!E9=0,"",Faturas!E9) | K8: =IF($B8="","",IF($C8=0,0,IF(K$3-$E$3<1/$C8,$D8*$C8,0))) | L8: =IF($B8="","",IF($C8=0,0,IF(L$3-$E$3<1/$C8,$D8*$C8,0))) | M8: =IF($B8="","",IF($C8=0,0,IF(M$3-$E$3<1/$C8,$D8*$C8,0))) | N8: =IF($B8="","",IF($C8=0,0,IF(N$3-$E$3<1/$C8,$D8*$C8,0))) | O8: =IF($B8="","",D8-SUM(E8:N8))
A9: 4 | B9: =IF(Faturas!C10=0,"",Faturas!C10) | C9: 0 | D9: =IF(Faturas!E10=0,"",Faturas!E10) | K9: =IF($B9="","",IF($C9=0,0,IF(K$3-$E$3<1/$C9,$D9*$C9,0))) | L9: =IF($B9="","",IF($C9=0,0,IF(L$3-$E$3<1/$C9,$D9*$C9,0))) | M9: =IF($B9="","",IF($C9=0,0,IF(M$3-$E$3<1/$C9,$D9*$C9,0))) | N9: =IF($B9="","",IF($C9=0,0,IF(N$3-$E$3<1/$C9,$D9*$C9,0))) | O9: =IF($B9="","",D9-SUM(E9:N9))
A10: 5 | B10: =IF(Faturas!C11=0,"",Faturas!C11) | C10: 0 | D10: =IF(Faturas!E11=0,"",Faturas!E11) | K10: =IF($B10="","",IF($C10=0,0,IF(K$3-$E$3<1/$C10,$D10*$C10,0))) | L10: =IF($B10="","",IF($C10=0,0,IF(L$3-$E$3<1/$C10,$D10*$C10,0))) | M10: =IF($B10="","",IF($C10=0,0,IF(M$3-$E$3<1/$C10,$D10*$C10,0))) | N10: =IF($B10="","",IF($C10=0,0,IF(N$3-$E$3<1/$C10,$D10*$C10,0))) | O10: =IF($B10="","",D10-SUM(E10:N10))
A11: 6 | B11: =IF(Faturas!C12=0,"",Faturas!C12) | C11: 0 | D11: =IF(Faturas!E12=0,"",Faturas!E12) | K11: =IF($B11="","",IF($C11=0,0,IF(K$3-$E$3<1/$C11,$D11*$C11,0))) | L11: =IF($B11="","",IF($C11=0,0,IF(L$3-$E$3<1/$C11,$D11*$C11,0))) | M11: =IF($B11="","",IF($C11=0,0,IF(M$3-$E$3<1/$C11,$D11*$C11,0))) | N11: =IF($B11="","",IF($C11=0,0,IF(N$3-$E$3<1/$C11,$D11*$C11,0))) | O11: =IF($B11="","",D11-SUM(E11:N11))
A12: 7 | B12: =IF(Faturas!C13=0,"",Faturas!C13) | C12: 0 | D12: =IF(Faturas!E13=0,"",Faturas!E13) | K12: =IF($B12="","",IF($C12=0,0,IF(K$3-$E$3<1/$C12,$D12*$C12,0))) | L12: =IF($B12="","",IF($C12=0,0,IF(L$3-$E$3<1/$C12,$D12*$C12,0))) | M12: =IF($B12="","",IF($C12=0,0,IF(M$3-$E$3<1/$C12,$D12*$C12,0))) | N12: =IF($B12="","",IF($C12=0,0,IF(N$3-$E$3<1/$C12,$D12*$C12,0))) | O12: =IF($B12="","",D12-SUM(E12:N12))
A13: 8 | B13: =IF(Faturas!C14=0,"",Faturas!C14) | C13: 0 | D13: =IF(Faturas!E14=0,"",Faturas!E14) | K13: =IF($B13="","",IF($C13=0,0,IF(K$3-$E$3<1/$C13,$D13*$C13,0))) | L13: =IF($B13="","",IF($C13=0,0,IF(L$3-$E$3<1/$C13,$D13*$C13,0))) | M13: =IF($B13="","",IF($C13=0,0,IF(M$3-$E$3<1/$C13,$D13*$C13,0))) | N13: =IF($B13="","",IF($C13=0,0,IF(N$3-$E$3<1/$C13,$D13*$C13,0))) | O13: =IF($B13="","",D13-SUM(E13:N13))
A14: 9 | B14: =IF(Faturas!C15=0,"",Faturas!C15) | C14: 0 | D14: =IF(Faturas!E15=0,"",Faturas!E15) | K14: =IF($B14="","",IF($C14=0,0,IF(K$3-$E$3<1/$C14,$D14*$C14,0))) | L14: =IF($B14="","",IF($C14=0,0,IF(L$3-$E$3<1/$C14,$D14*$C14,0))) | M14: =IF($B14="","",IF($C14=0,0,IF(M$3-$E$3<1/$C14,$D14*$C14,0))) | N14: =IF($B14="","",IF($C14=0,0,IF(N$3-$E$3<1/$C14,$D14*$C14,0))) | O14: =IF($B14="","",D14-SUM(E14:N14))
A15: 10 | B15: =IF(Faturas!C16=0,"",Faturas!C16) | C15: 0 | D15: =IF(Faturas!E16=0,"",Faturas!E16) | K15: =IF($B15="","",IF($C15=0,0,IF(K$3-$E$3<1/$C15,$D15*$C15,0))) | L15: =IF($B15="","",IF($C15=0,0,IF(L$3-$E$3<1/$C15,$D15*$C15,0))) | M15: =IF($B15="","",IF($C15=0,0,IF(M$3-$E$3<1/$C15,$D15*$C15,0))) | N15: =IF($B15="","",IF($C15=0,0,IF(N$3-$E$3<1/$C15,$D15*$C15,0))) | O15: =IF($B15="","",D15-SUM(E15:N15))
A16: 11 | B16: =IF(Faturas!C17=0,"",Faturas!C17) | C16: 0 | D16: =IF(Faturas!E17=0,"",Faturas!E17) | K16: =IF($B16="","",IF($C16=0,0,IF(K$3-$E$3<1/$C16,$D16*$C16,0))) | L16: =IF($B16="","",IF($C16=0,0,IF(L$3-$E$3<1/$C16,$D16*$C16,0))) | M16: =IF($B16="","",IF($C16=0,0,IF(M$3-$E$3<1/$C16,$D16*$C16,0))) | N16: =IF($B16="","",IF($C16=0,0,IF(N$3-$E$3<1/$C16,$D16*$C16,0))) | O16: =IF($B16="","",D16-SUM(E16:N16))
A17: 12 | B17: =IF(Faturas!C18=0,"",Faturas!C18) | C17: 0 | D17: =IF(Faturas!E18=0,"",Faturas!E18) | K17: =IF($B17="","",IF($C17=0,0,IF(K$3-$E$3<1/$C17,$D17*$C17,0))) | L17: =IF($B17="","",IF($C17=0,0,IF(L$3-$E$3<1/$C17,$D17*$C17,0))) | M17: =IF($B17="","",IF($C17=0,0,IF(M$3-$E$3<1/$C17,$D17*$C17,0))) | N17: =IF($B17="","",IF($C17=0,0,IF(N$3-$E$3<1/$C17,$D17*$C17,0))) | O17: =IF($B17="","",D17-SUM(E17:N17))
... A21: 16 | B21: =IF(Faturas!C22=0,"",Faturas!C22) | C21: 0 | D21: =IF(Faturas!E22=0,"",Faturas!E22) | K21: =IF($B21="","",IF($C21=0,0,IF(K$3-$E$3<1/$C21,$D21*$C21,0))) | L21: =IF($B21="","",IF($C21=0,0,IF(L$3-$E$3<1/$C21,$D21*$C21,0))) | M21: =IF($B21="","",IF($C21=0,0,IF(M$3-$E$3<1/$C21,$D21*$C21,0))) | N21: =IF($B21="","",IF($C21=0,0,IF(N$3-$E$3<1/$C21,$D21*$C21,0))) | O21: =IF($B21="","",D21-SUM(E21:N21))
B22: Total Obras | D22: =SUM(D6:D21) -> 0 | E22: =SUM(E6:E21) -> 0 | F22: =SUM(F6:F21) -> 0 | G22: =SUM(G6:G21) -> 0 | H22: =SUM(H6:H21) -> 0 | I22: =SUM(I6:I21) -> 0 | J22: =SUM(J6:J21) -> 0 | K22: =SUM(K6:K21) -> 0 | ... O22: =SUM(O6:O21) -> 0
B24: EQUIPAMENTO
A25: 1 | B25: =IF(Faturas!C26=0,"",Faturas!C26) -> Ativos 2020 | C25: 0.25 | D25: =IF(Faturas!E26=0,"",Faturas!E26) | K25: =IF($B25="","",IF($C25=0,0,IF(K$3-$E$3<1/$C25,$D25*$C25,0))) -> 0 | L25: =IF($B25="","",IF($C25=0,0,IF(L$3-$E$3<1/$C25,$D25*$C25,0))) -> 0 | M25: =IF($B25="","",IF($C25=0,0,IF(M$3-$E$3<1/$C25,$D25*$C25,0))) -> 0 | N25: =IF($B25="","",IF($C25=0,0,IF(N$3-$E$3<1/$C25,$D25*$C25,0))) -> 0 | O25: =IF($B25="","",D25-SUM(E25:N25)) -> #VALUE!
A26: 2 | B26: =IF(Faturas!C27=0,"",Faturas!C27) -> Ativos 2021 | C26: 0.25 | D26: =IF(Faturas!E27=0,"",Faturas!E27) -> 40000 | F26: =$D$26*$C$26 -> 10000 | G26: =$D$26*$C$26 -> 10000 | H26: =$D$26*$C$26 -> 10000 | I26: =$D$26*$C$26 -> 10000 | K26: =IF($B26="","",IF($C26=0,0,IF(K$3-$E$3<1/$C26,$D26*$C26,0))) -> 0 | L26: =IF($B26="","",IF($C26=0,0,IF(L$3-$E$3<1/$C26,$D26*$C26,0))) -> 0 | M26: =IF($B26="","",IF($C26=0,0,IF(M$3-$E$3<1/$C26,$D26*$C26,0))) -> 0 | N26: =IF($B26="","",IF($C26=0,0,IF(N$3-$E$3<1/$C26,$D26*$C26,0))) -> 0 | O26: =IF($B26="","",D26-SUM(E26:N26)) -> 0
A27: 3 | B27: =IF(Faturas!C28=0,"",Faturas!C28) -> Ativos 2022 | C27: 0.25 | D27: =IF(Faturas!E28=0,"",Faturas!E28) | K27: =IF($B27="","",IF($C27=0,0,IF(K$3-$E$3<1/$C27,$D27*$C27,0))) -> 0 | L27: =IF($B27="","",IF($C27=0,0,IF(L$3-$E$3<1/$C27,$D27*$C27,0))) -> 0 | M27: =IF($B27="","",IF($C27=0,0,IF(M$3-$E$3<1/$C27,$D27*$C27,0))) -> 0 | N27: =IF($B27="","",IF($C27=0,0,IF(N$3-$E$3<1/$C27,$D27*$C27,0))) -> 0 | O27: =IF($B27="","",D27-SUM(E27:N27)) -> #VALUE!
A28: 4 | B28: =IF(Faturas!C29=0,"",Faturas!C29) | C28: 0 | D28: =IF(Faturas!E29=0,"",Faturas!E29) | K28: =IF($B28="","",IF($C28=0,0,IF(K$3-$E$3<1/$C28,$D28*$C28,0))) | L28: =IF($B28="","",IF($C28=0,0,IF(L$3-$E$3<1/$C28,$D28*$C28,0))) | M28: =IF($B28="","",IF($C28=0,0,IF(M$3-$E$3<1/$C28,$D28*$C28,0))) | N28: =IF($B28="","",IF($C28=0,0,IF(N$3-$E$3<1/$C28,$D28*$C28,0))) | O28: =IF($B28="","",D28-SUM(E28:N28))
A29: 5 | B29: =IF(Faturas!C30=0,"",Faturas!C30) | C29: 0 | D29: =IF(Faturas!E30=0,"",Faturas!E30) | K29: =IF($B29="","",IF($C29=0,0,IF(K$3-$E$3<1/$C29,$D29*$C29,0))) | L29: =IF($B29="","",IF($C29=0,0,IF(L$3-$E$3<1/$C29,$D29*$C29,0))) | M29: =IF($B29="","",IF($C29=0,0,IF(M$3-$E$3<1/$C29,$D29*$C29,0))) | N29: =IF($B29="","",IF($C29=0,0,IF(N$3-$E$3<1/$C29,$D29*$C29,0))) | O29: =IF($B29="","",D29-SUM(E29:N29))
A30: 6 | B30: =IF(Faturas!C31=0,"",Faturas!C31) | C30: 0 | D30: =IF(Faturas!E31=0,"",Faturas!E31) | K30: =IF($B30="","",IF($C30=0,0,IF(K$3-$E$3<1/$C30,$D30*$C30,0))) | L30: =IF($B30="","",IF($C30=0,0,IF(L$3-$E$3<1/$C30,$D30*$C30,0))) | M30: =IF($B30="","",IF($C30=0,0,IF(M$3-$E$3<1/$C30,$D30*$C30,0))) | N30: =IF($B30="","",IF($C30=0,0,IF(N$3-$E$3<1/$C30,$D30*$C30,0))) | O30: =IF($B30="","",D30-SUM(E30:N30))
A31: 7 | B31: =IF(Faturas!C32=0,"",Faturas!C32) | C31: 0 | D31: =IF(Faturas!E32=0,"",Faturas!E32) | K31: =IF($B31="","",IF($C31=0,0,IF(K$3-$E$3<1/$C31,$D31*$C31,0))) | L31: =IF($B31="","",IF($C31=0,0,IF(L$3-$E$3<1/$C31,$D31*$C31,0))) | M31: =IF($B31="","",IF($C31=0,0,IF(M$3-$E$3<1/$C31,$D31*$C31,0))) | N31: =IF($B31="","",IF($C31=0,0,IF(N$3-$E$3<1/$C31,$D31*$C31,0))) | O31: =IF($B31="","",D31-SUM(E31:N31))
A32: 8 | B32: =IF(Faturas!C33=0,"",Faturas!C33) | C32: 0 | D32: =IF(Faturas!E33=0,"",Faturas!E33) | K32: =IF($B32="","",IF($C32=0,0,IF(K$3-$E$3<1/$C32,$D32*$C32,0))) | L32: =IF($B32="","",IF($C32=0,0,IF(L$3-$E$3<1/$C32,$D32*$C32,0))) | M32: =IF($B32="","",IF($C32=0,0,IF(M$3-$E$3<1/$C32,$D32*$C32,0))) | N32: =IF($B32="","",IF($C32=0,0,IF(N$3-$E$3<1/$C32,$D32*$C32,0))) | O32: =IF($B32="","",D32-SUM(E32:N32))
A33: 9 | B33: =IF(Faturas!C34=0,"",Faturas!C34) | C33: 0 | D33: =IF(Faturas!E34=0,"",Faturas!E34) | K33: =IF($B33="","",IF($C33=0,0,IF(K$3-$E$3<1/$C33,$D33*$C33,0))) | L33: =IF($B33="","",IF($C33=0,0,IF(L$3-$E$3<1/$C33,$D33*$C33,0))) | M33: =IF($B33="","",IF($C33=0,0,IF(M$3-$E$3<1/$C33,$D33*$C33,0))) | N33: =IF($B33="","",IF($C33=0,0,IF(N$3-$E$3<1/$C33,$D33*$C33,0))) | O33: =IF($B33="","",D33-SUM(E33:N33))
A34: 10 | B34: =IF(Faturas!C35=0,"",Faturas!C35) | C34: 0 | D34: =IF(Faturas!E35=0,"",Faturas!E35) | K34: =IF($B34="","",IF($C34=0,0,IF(K$3-$E$3<1/$C34,$D34*$C34,0))) | L34: =IF($B34="","",IF($C34=0,0,IF(L$3-$E$3<1/$C34,$D34*$C34,0))) | M34: =IF($B34="","",IF($C34=0,0,IF(M$3-$E$3<1/$C34,$D34*$C34,0))) | N34: =IF($B34="","",IF($C34=0,0,IF(N$3-$E$3<1/$C34,$D34*$C34,0))) | O34: =IF($B34="","",D34-SUM(E34:N34))
A35: 11 | B35: =IF(Faturas!C36=0,"",Faturas!C36) | C35: 0 | D35: =IF(Faturas!E36=0,"",Faturas!E36) | K35: =IF($B35="","",IF($C35=0,0,IF(K$3-$E$3<1/$C35,$D35*$C35,0))) | L35: =IF($B35="","",IF($C35=0,0,IF(L$3-$E$3<1/$C35,$D35*$C35,0))) | M35: =IF($B35="","",IF($C35=0,0,IF(M$3-$E$3<1/$C35,$D35*$C35,0))) | N35: =IF($B35="","",IF($C35=0,0,IF(N$3-$E$3<1/$C35,$D35*$C35,0))) | O35: =IF($B35="","",D35-SUM(E35:N35))
A36: 12 | B36: =IF(Faturas!C37=0,"",Faturas!C37) | C36: 0 | D36: =IF(Faturas!E37=0,"",Faturas!E37) | K36: =IF($B36="","",IF($C36=0,0,IF(K$3-$E$3<1/$C36,$D36*$C36,0))) | L36: =IF($B36="","",IF($C36=0,0,IF(L$3-$E$3<1/$C36,$D36*$C36,0))) | M36: =IF($B36="","",IF($C36=0,0,IF(M$3-$E$3<1/$C36,$D36*$C36,0))) | N36: =IF($B36="","",IF($C36=0,0,IF(N$3-$E$3<1/$C36,$D36*$C36,0))) | O36: =IF($B36="","",D36-SUM(E36:N36))
A37: 13 | B37: =IF(Faturas!C38=0,"",Faturas!C38) | C37: 0 | D37: =IF(Faturas!E38=0,"",Faturas!E38) | K37: =IF($B37="","",IF($C37=0,0,IF(K$3-$E$3<1/$C37,$D37*$C37,0))) | L37: =IF($B37="","",IF($C37=0,0,IF(L$3-$E$3<1/$C37,$D37*$C37,0))) | M37: =IF($B37="","",IF($C37=0,0,IF(M$3-$E$3<1/$C37,$D37*$C37,0))) | N37: =IF($B37="","",IF($C37=0,0,IF(N$3-$E$3<1/$C37,$D37*$C37,0))) | O37: =IF($B37="","",D37-SUM(E37:N37))
A38: 14 | B38: =IF(Faturas!C39=0,"",Faturas!C39) | C38: 0 | D38: =IF(Faturas!E39=0,"",Faturas!E39) | K38: =IF($B38="","",IF($C38=0,0,IF(K$3-$E$3<1/$C38,$D38*$C38,0))) | L38: =IF($B38="","",IF($C38=0,0,IF(L$3-$E$3<1/$C38,$D38*$C38,0))) | M38: =IF($B38="","",IF($C38=0,0,IF(M$3-$E$3<1/$C38,$D38*$C38,0))) | N38: =IF($B38="","",IF($C38=0,0,IF(N$3-$E$3<1/$C38,$D38*$C38,0))) | O38: =IF($B38="","",D38-SUM(E38:N38))
... A59: 35 | B59: =IF(Faturas!C60=0,"",Faturas!C60) | C59: 0 | D59: =IF(Faturas!E60=0,"",Faturas!E60) | K59: =IF($B59="","",IF($C59=0,0,IF(K$3-$E$3<1/$C59,$D59*$C59,0))) | L59: =IF($B59="","",IF($C59=0,0,IF(L$3-$E$3<1/$C59,$D59*$C59,0))) | M59: =IF($B59="","",IF($C59=0,0,IF(M$3-$E$3<1/$C59,$D59*$C59,0))) | N59: =IF($B59="","",IF($C59=0,0,IF(N$3-$E$3<1/$C59,$D59*$C59,0))) | O59: =IF($B59="","",D59-SUM(E59:N59))
B60: Total Equipamento | D60: =SUM(D25:D59) -> 40000 | E60: =SUM(E25:E59) -> 0 | F60: =SUM(F25:F59) -> 10000 | G60: =SUM(G25:G59) -> 10000 | H60: =SUM(H25:H59) -> 10000 | I60: =SUM(I25:I59) -> 10000 | J60: =SUM(J25:J59) -> 0 | K60: =SUM(K25:K59) -> 0 | ... O60: =SUM(O25:O59) -> #VALUE!
B62: INTANGÍVEL
A63: 1 | B63: =IF(Faturas!C64=0,"",Faturas!C64) | C63: 0.3333333 | D63: =IF(Faturas!E64=0,"",Faturas!E64) | K63: =IF($B63="","",IF($C63=0,0,IF(K$3-$E$3<1/$C63,$D63*$C63,0))) | L63: =IF($B63="","",IF($C63=0,0,IF(L$3-$E$3<1/$C63,$D63*$C63,0))) | M63: =IF($B63="","",IF($C63=0,0,IF(M$3-$E$3<1/$C63,$D63*$C63,0))) | N63: =IF($B63="","",IF($C63=0,0,IF(N$3-$E$3<1/$C63,$D63*$C63,0))) | O63: =IF($B63="","",D63-SUM(E63:N63))
A64: 2 | B64: =IF(Faturas!C65=0,"",Faturas!C65) | C64: 0 | D64: =IF(Faturas!E65=0,"",Faturas!E65) | K64: =IF($B64="","",IF($C64=0,0,IF(K$3-$E$3<1/$C64,$D64*$C64,0))) | L64: =IF($B64="","",IF($C64=0,0,IF(L$3-$E$3<1/$C64,$D64*$C64,0))) | M64: =IF($B64="","",IF($C64=0,0,IF(M$3-$E$3<1/$C64,$D64*$C64,0))) | N64: =IF($B64="","",IF($C64=0,0,IF(N$3-$E$3<1/$C64,$D64*$C64,0))) | O64: =IF($B64="","",D64-SUM(E64:N64))
A65: 3 | B65: =IF(Faturas!C66=0,"",Faturas!C66) | C65: 0 | D65: =IF(Faturas!E66=0,"",Faturas!E66) | K65: =IF($B65="","",IF($C65=0,0,IF(K$3-$E$3<1/$C65,$D65*$C65,0))) | L65: =IF($B65="","",IF($C65=0,0,IF(L$3-$E$3<1/$C65,$D65*$C65,0))) | M65: =IF($B65="","",IF($C65=0,0,IF(M$3-$E$3<1/$C65,$D65*$C65,0))) | N65: =IF($B65="","",IF($C65=0,0,IF(N$3-$E$3<1/$C65,$D65*$C65,0))) | O65: =IF($B65="","",D65-SUM(E65:N65))
A66: 4 | B66: =IF(Faturas!C67=0,"",Faturas!C67) | C66: 0 | D66: =IF(Faturas!E67=0,"",Faturas!E67) | K66: =IF($B66="","",IF($C66=0,0,IF(K$3-$E$3<1/$C66,$D66*$C66,0))) | L66: =IF($B66="","",IF($C66=0,0,IF(L$3-$E$3<1/$C66,$D66*$C66,0))) | M66: =IF($B66="","",IF($C66=0,0,IF(M$3-$E$3<1/$C66,$D66*$C66,0))) | N66: =IF($B66="","",IF($C66=0,0,IF(N$3-$E$3<1/$C66,$D66*$C66,0))) | O66: =IF($B66="","",D66-SUM(E66:N66))
A67: 5 | B67: =IF(Faturas!C68=0,"",Faturas!C68) | C67: 0 | D67: =IF(Faturas!E68=0,"",Faturas!E68) | K67: =IF($B67="","",IF($C67=0,0,IF(K$3-$E$3<1/$C67,$D67*$C67,0))) | L67: =IF($B67="","",IF($C67=0,0,IF(L$3-$E$3<1/$C67,$D67*$C67,0))) | M67: =IF($B67="","",IF($C67=0,0,IF(M$3-$E$3<1/$C67,$D67*$C67,0))) | N67: =IF($B67="","",IF($C67=0,0,IF(N$3-$E$3<1/$C67,$D67*$C67,0))) | O67: =IF($B67="","",D67-SUM(E67:N67))
A68: 6 | B68: =IF(Faturas!C69=0,"",Faturas!C69) | C68: 0 | D68: =IF(Faturas!E69=0,"",Faturas!E69) | K68: =IF($B68="","",IF($C68=0,0,IF(K$3-$E$3<1/$C68,$D68*$C68,0))) | L68: =IF($B68="","",IF($C68=0,0,IF(L$3-$E$3<1/$C68,$D68*$C68,0))) | M68: =IF($B68="","",IF($C68=0,0,IF(M$3-$E$3<1/$C68,$D68*$C68,0))) | N68: =IF($B68="","",IF($C68=0,0,IF(N$3-$E$3<1/$C68,$D68*$C68,0))) | O68: =IF($B68="","",D68-SUM(E68:N68))
A69: 7 | B69: =IF(Faturas!C70=0,"",Faturas!C70) | C69: 0 | D69: =IF(Faturas!E70=0,"",Faturas!E70) | K69: =IF($B69="","",IF($C69=0,0,IF(K$3-$E$3<1/$C69,$D69*$C69,0))) | L69: =IF($B69="","",IF($C69=0,0,IF(L$3-$E$3<1/$C69,$D69*$C69,0))) | M69: =IF($B69="","",IF($C69=0,0,IF(M$3-$E$3<1/$C69,$D69*$C69,0))) | N69: =IF($B69="","",IF($C69=0,0,IF(N$3-$E$3<1/$C69,$D69*$C69,0))) | O69: =IF($B69="","",D69-SUM(E69:N69))
A70: 8 | B70: =IF(Faturas!C71=0,"",Faturas!C71) | C70: 0 | D70: =IF(Faturas!E71=0,"",Faturas!E71) | K70: =IF($B70="","",IF($C70=0,0,IF(K$3-$E$3<1/$C70,$D70*$C70,0))) | L70: =IF($B70="","",IF($C70=0,0,IF(L$3-$E$3<1/$C70,$D70*$C70,0))) | M70: =IF($B70="","",IF($C70=0,0,IF(M$3-$E$3<1/$C70,$D70*$C70,0))) | N70: =IF($B70="","",IF($C70=0,0,IF(N$3-$E$3<1/$C70,$D70*$C70,0))) | O70: =IF($B70="","",D70-SUM(E70:N70))
A71: 9 | B71: =IF(Faturas!C72=0,"",Faturas!C72) | C71: 0 | D71: =IF(Faturas!E72=0,"",Faturas!E72) | K71: =IF($B71="","",IF($C71=0,0,IF(K$3-$E$3<1/$C71,$D71*$C71,0))) | L71: =IF($B71="","",IF($C71=0,0,IF(L$3-$E$3<1/$C71,$D71*$C71,0))) | M71: =IF($B71="","",IF($C71=0,0,IF(M$3-$E$3<1/$C71,$D71*$C71,0))) | N71: =IF($B71="","",IF($C71=0,0,IF(N$3-$E$3<1/$C71,$D71*$C71,0))) | O71: =IF($B71="","",D71-SUM(E71:N71))
A72: 10 | B72: =IF(Faturas!C73=0,"",Faturas!C73) | C72: 0 | D72: =IF(Faturas!E73=0,"",Faturas!E73) | K72: =IF($B72="","",IF($C72=0,0,IF(K$3-$E$3<1/$C72,$D72*$C72,0))) | L72: =IF($B72="","",IF($C72=0,0,IF(L$3-$E$3<1/$C72,$D72*$C72,0))) | M72: =IF($B72="","",IF($C72=0,0,IF(M$3-$E$3<1/$C72,$D72*$C72,0))) | N72: =IF($B72="","",IF($C72=0,0,IF(N$3-$E$3<1/$C72,$D72*$C72,0))) | O72: =IF($B72="","",D72-SUM(E72:N72))
A73: 11 | B73: =IF(Faturas!C74=0,"",Faturas!C74) | C73: 0 | D73: =IF(Faturas!E74=0,"",Faturas!E74) | K73: =IF($B73="","",IF($C73=0,0,IF(K$3-$E$3<1/$C73,$D73*$C73,0))) | L73: =IF($B73="","",IF($C73=0,0,IF(L$3-$E$3<1/$C73,$D73*$C73,0))) | M73: =IF($B73="","",IF($C73=0,0,IF(M$3-$E$3<1/$C73,$D73*$C73,0))) | N73: =IF($B73="","",IF($C73=0,0,IF(N$3-$E$3<1/$C73,$D73*$C73,0))) | O73: =IF($B73="","",D73-SUM(E73:N73))
A74: 12 | B74: =IF(Faturas!C75=0,"",Faturas!C75) | C74: 0 | D74: =IF(Faturas!E75=0,"",Faturas!E75) | K74: =IF($B74="","",IF($C74=0,0,IF(K$3-$E$3<1/$C74,$D74*$C74,0))) | L74: =IF($B74="","",IF($C74=0,0,IF(L$3-$E$3<1/$C74,$D74*$C74,0))) | M74: =IF($B74="","",IF($C74=0,0,IF(M$3-$E$3<1/$C74,$D74*$C74,0))) | N74: =IF($B74="","",IF($C74=0,0,IF(N$3-$E$3<1/$C74,$D74*$C74,0))) | O74: =IF($B74="","",D74-SUM(E74:N74))
... A78: 16 | B78: =IF(Faturas!C79=0,"",Faturas!C79) | C78: 0 | D78: =IF(Faturas!E79=0,"",Faturas!E79) | K78: =IF($B78="","",IF($C78=0,0,IF(K$3-$E$3<1/$C78,$D78*$C78,0))) | L78: =IF($B78="","",IF($C78=0,0,IF(L$3-$E$3<1/$C78,$D78*$C78,0))) | M78: =IF($B78="","",IF($C78=0,0,IF(M$3-$E$3<1/$C78,$D78*$C78,0))) | N78: =IF($B78="","",IF($C78=0,0,IF(N$3-$E$3<1/$C78,$D78*$C78,0))) | O78: =IF($B78="","",D78-SUM(E78:N78))
B79: Total Intangível | E79: =SUM(E63:E78) -> 0 | F79: =SUM(F63:F78) -> 0 | G79: =SUM(G63:G78) -> 0 | H79: =SUM(H63:H78) -> 0 | I79: =SUM(I63:I78) -> 0 | J79: =SUM(J63:J78) -> 0 | K79: =SUM(K63:K78) -> 0 | L79: =SUM(L63:L78) -> 0 | ... O79: =SUM(O63:O78) -> 0
B81: TABELA DE AMORTIZAÇÕES | E81: =E3 -> 2020 | F81: =F3 -> 2021 | G81: =G3 -> 2022 | H81: =H3 -> 2023 | I81: =I3 -> 2024 | J81: =J3 -> 2025 | K81: =K3 -> 2026 | L81: =L3 -> 2027 | ... N81: =N3 -> 2029
B83: IMOBILIZADO BRUTO SEM PROJETO | D83: =SUM(D84:D86) -> 84625.24 | E83: =SUM(E84:E86) -> 0 | F83: =SUM(F84:F86) -> 0 | G83: =SUM(G84:G86) -> 0 | H83: =SUM(H84:H86) -> 0 | I83: =SUM(I84:I86) -> 0 | J83: =SUM(J84:J86) -> 0 | K83: =SUM(K84:K86) -> 0 | ... O83: =SUM(O84:O86) -> 84625.24
B84: Imobilizado Tangível | D84: =Balanço!E79 -> 84625.24 | O84: =IF($B84="","",D84-SUM(E84:N84)) -> 84625.24
B85: Imobilizado Tangível - Biológico | D85: =Balanço!E80 -> 0 | O85: =IF($B85="","",D85-SUM(E85:N85)) -> 0
B86: Imobilizado Intangível | D86: =Balanço!E81 -> 0 | O86: =IF($B86="","",D86-SUM(E86:N86)) -> 0
B88: AMORTIZAÇÕES IMOB. SEM PROJETO | E88: =SUM(E89:E91) -> 8462.524 | F88: =SUM(F89:F91) -> 8462.524 | G88: =SUM(G89:G91) -> 8462.524 | H88: =SUM(H89:H91) -> 8462.524 | I88: =SUM(I89:I91) -> 8462.524 | J88: =SUM(J89:J91) -> 8462.524 | K88: =SUM(K89:K91) -> 8462.524 | L88: =SUM(L89:L91) -> 8462.524 | ... O88: =SUM(O89:O91) -> -84625.24
B89: Imobilizado Tangível | C89: 0.1 | E89: =IF(E$81-$E$81<1/$C89,($D84-$D94)*$C89,0) -> 8462.524 | F89: =IF(F$81-$E$81<1/$C89,($D84-$D94)*$C89,0) -> 8462.524 | G89: =IF(G$81-$E$81<1/$C89,($D84-$D94)*$C89,0) -> 8462.524 | H89: =IF(H$81-$E$81<1/$C89,($D84-$D94)*$C89,0) -> 8462.524 | I89: =IF(I$81-$E$81<1/$C89,($D84-$D94)*$C89,0) -> 8462.524 | J89: =IF(J$81-$E$81<1/$C89,($D84-$D94)*$C89,0) -> 8462.524 | K89: =IF(K$81-$E$81<1/$C89,($D84-$D94)*$C89,0) -> 8462.524 | L89: =IF(L$81-$E$81<1/$C89,($D84-$D94)*$C89,0) -> 8462.524 | ... N89: =IF(N$81-$E$81<1/$C89,($D84-$D94)*$C89,0) -> 8462.524 | O89: =IF($B89="","",D89-SUM(E89:N89)) -> -84625.24
B90: Imobilizado Tangível - Biológico | C90: 0.1 | E90: =IF(E$81-$E$81<1/$C90,($D85-$D95)*$C90,0) -> 0 | F90: =IF(F$81-$E$81<1/$C90,($D85-$D95)*$C90,0) -> 0 | G90: =IF(G$81-$E$81<1/$C90,($D85-$D95)*$C90,0) -> 0 | H90: =IF(H$81-$E$81<1/$C90,($D85-$D95)*$C90,0) -> 0 | I90: =IF(I$81-$E$81<1/$C90,($D85-$D95)*$C90,0) -> 0 | J90: =IF(J$81-$E$81<1/$C90,($D85-$D95)*$C90,0) -> 0 | K90: =IF(K$81-$E$81<1/$C90,($D85-$D95)*$C90,0) -> 0 | L90: =IF(L$81-$E$81<1/$C90,($D85-$D95)*$C90,0) -> 0 | ... N90: =IF(N$81-$E$81<1/$C90,($D85-$D95)*$C90,0) -> 0 | O90: =IF($B90="","",D90-SUM(E90:N90)) -> 0
B91: Imobilizado Intangível | C91: 0.1 | E91: =IF(E$81-$E$81<1/$C91,($D86-$D96)*$C91,0) -> 0 | F91: =IF(F$81-$E$81<1/$C91,($D86-$D96)*$C91,0) -> 0 | G91: =IF(G$81-$E$81<1/$C91,($D86-$D96)*$C91,0) -> 0 | H91: =IF(H$81-$E$81<1/$C91,($D86-$D96)*$C91,0) -> 0 | I91: =IF(I$81-$E$81<1/$C91,($D86-$D96)*$C91,0) -> 0 | J91: =IF(J$81-$E$81<1/$C91,($D86-$D96)*$C91,0) -> 0 | K91: =IF(K$81-$E$81<1/$C91,($D86-$D96)*$C91,0) -> 0 | L91: =IF(L$81-$E$81<1/$C91,($D86-$D96)*$C91,0) -> 0 | ... N91: =IF(N$81-$E$81<1/$C91,($D86-$D96)*$C91,0) -> 0 | O91: =IF($B91="","",D91-SUM(E91:N91)) -> 0
B93: AMORTIZAÇÕES ACUMULADAS IMOB. SEM PROJETO | D93: =SUM(D94:D96) -> 0 | E93: =SUM(E94:E96) -> 8462.524 | F93: =SUM(F94:F96) -> 16925.048 | G93: =SUM(G94:G96) -> 25387.572 | H93: =SUM(H94:H96) -> 33850.096 | I93: =SUM(I94:I96) -> 42312.62 | J93: =SUM(J94:J96) -> 50775.144 | K93: =SUM(K94:K96) -> 59237.668 | ... O93: =SUM(O94:O96) -> -465438.82
B94: Imobilizado Tangível | D94: =Balanço!E84 -> 0 | E94: =D94+E89 -> 8462.524 | F94: =E94+F89 -> 16925.048 | G94: =F94+G89 -> 25387.572 | H94: =G94+H89 -> 33850.096 | I94: =H94+I89 -> 42312.62 | J94: =I94+J89 -> 50775.144 | K94: =J94+K89 -> 59237.668 | L94: =K94+L89 -> 67700.192 | ... N94: =M94+N89 -> 84625.24 | O94: =IF($B94="","",D94-SUM(E94:N94)) -> -465438.82
B95: Imobilizado Tangível - Biológico | D95: =Balanço!E85 -> 0 | E95: =D95+E90 -> 0 | F95: =E95+F90 -> 0 | G95: =F95+G90 -> 0 | H95: =G95+H90 -> 0 | I95: =H95+I90 -> 0 | J95: =I95+J90 -> 0 | K95: =J95+K90 -> 0 | L95: =K95+L90 -> 0 | ... N95: =M95+N90 -> 0 | O95: =IF($B95="","",D95-SUM(E95:N95)) -> 0
B96: Imobilizado Intangível | D96: =Balanço!E86 -> 0 | E96: =D96+E91 -> 0 | F96: =E96+F91 -> 0 | G96: =F96+G91 -> 0 | H96: =G96+H91 -> 0 | I96: =H96+I91 -> 0 | J96: =I96+J91 -> 0 | K96: =J96+K91 -> 0 | L96: =K96+L91 -> 0 | ... N96: =M96+N91 -> 0 | O96: =IF($B96="","",D96-SUM(E96:N96)) -> 0
B98: AMORTIZAÇÕES IMOB. DO PROJETO | E98: =SUM(E99:E101) -> 0 | F98: =SUM(F99:F101) -> 10000 | G98: =SUM(G99:G101) -> 10000 | H98: =SUM(H99:H101) -> 10000 | I98: =SUM(I99:I101) -> 10000 | J98: =SUM(J99:J101) -> 0 | K98: =SUM(K99:K101) -> 0 | L98: =SUM(L99:L101) -> 0 | ... O98: =SUM(O99:O101) -> -40000
B99: Imobilizado Tangível | E99: =SUM(E6:E21)+SUMIF(Faturas!$G$26:$G$60,"Não",E25:E59) -> 0 | F99: =SUM(F6:F21)+SUMIF(Faturas!$G$26:$G$60,"Não",F25:F59) -> 10000 | G99: =SUM(G6:G21)+SUMIF(Faturas!$G$26:$G$60,"Não",G25:G59) -> 10000 | H99: =SUM(H6:H21)+SUMIF(Faturas!$G$26:$G$60,"Não",H25:H59) -> 10000 | I99: =SUM(I6:I21)+SUMIF(Faturas!$G$26:$G$60,"Não",I25:I59) -> 10000 | J99: =SUM(J6:J21)+SUMIF(Faturas!$G$26:$G$60,"Não",J25:J59) -> 0 | K99: =SUM(K6:K21)+SUMIF(Faturas!$G$26:$G$60,"Não",K25:K59) -> 0 | L99: =SUM(L6:L21)+SUMIF(Faturas!$G$26:$G$60,"Não",L25:L59) -> 0 | ... N99: =SUM(N6:N21)+SUMIF(Faturas!$G$26:$G$60,"Não",N25:N59) -> 0 | O99: =IF($B99="","",D99-SUM(E99:N99)) -> -40000
B100: Imobilizado Tangível - Biológico | E100: =SUMIF(Faturas!$G$26:$G$60,"Sim",E25:E59) -> 0 | F100: =SUMIF(Faturas!$G$26:$G$60,"Sim",F25:F59) -> 0 | G100: =SUMIF(Faturas!$G$26:$G$60,"Sim",G25:G59) -> 0 | H100: =SUMIF(Faturas!$G$26:$G$60,"Sim",H25:H59) -> 0 | I100: =SUMIF(Faturas!$G$26:$G$60,"Sim",I25:I59) -> 0 | J100: =SUMIF(Faturas!$G$26:$G$60,"Sim",J25:J59) -> 0 | K100: =SUMIF(Faturas!$G$26:$G$60,"Sim",K25:K59) -> 0 | L100: =SUMIF(Faturas!$G$26:$G$60,"Sim",L25:L59) -> 0 | ... N100: =SUMIF(Faturas!$G$26:$G$60,"Sim",N25:N59) -> 0 | O100: =IF($B100="","",D100-SUM(E100:N100)) -> 0
B101: Imobilizado Intangível | E101: =SUM(E63:E78) -> 0 | F101: =SUM(F63:F78) -> 0 | G101: =SUM(G63:G78) -> 0 | H101: =SUM(H63:H78) -> 0 | I101: =SUM(I63:I78) -> 0 | J101: =SUM(J63:J78) -> 0 | K101: =SUM(K63:K78) -> 0 | L101: =SUM(L63:L78) -> 0 | ... N101: =SUM(N63:N78) -> 0 | O101: =IF($B101="","",D101-SUM(E101:N101)) -> 0
B103: AMORTIZAÇÕES ACUMULADAS IMOB. DO PROJETO | E103: =SUM(E104:E106) -> 0 | F103: =SUM(F104:F106) -> 10000 | G103: =SUM(G104:G106) -> 20000 | H103: =SUM(H104:H106) -> 30000 | I103: =SUM(I104:I106) -> 40000 | J103: =SUM(J104:J106) -> 40000 | K103: =SUM(K104:K106) -> 40000 | L103: =SUM(L104:L106) -> 40000 | ... O103: =SUM(O104:O106) -> -300000
B104: Imobilizado Tangível | E104: =D104+E99 -> 0 | F104: =E104+F99 -> 10000 | G104: =F104+G99 -> 20000 | H104: =G104+H99 -> 30000 | I104: =H104+I99 -> 40000 | J104: =I104+J99 -> 40000 | K104: =J104+K99 -> 40000 | L104: =K104+L99 -> 40000 | ... N104: =M104+N99 -> 40000 | O104: =IF($B104="","",D104-SUM(E104:N104)) -> -300000
B105: Imobilizado Tangível - Biológico | E105: =D105+E100 -> 0 | F105: =E105+F100 -> 0 | G105: =F105+G100 -> 0 | H105: =G105+H100 -> 0 | I105: =H105+I100 -> 0 | J105: =I105+J100 -> 0 | K105: =J105+K100 -> 0 | L105: =K105+L100 -> 0 | ... N105: =M105+N100 -> 0 | O105: =IF($B105="","",D105-SUM(E105:N105)) -> 0
B106: Imobilizado Intangível | E106: =D106+E101 -> 0 | F106: =E106+F101 -> 0 | G106: =F106+G101 -> 0 | H106: =G106+H101 -> 0 | I106: =H106+I101 -> 0 | J106: =I106+J101 -> 0 | K106: =J106+K101 -> 0 | L106: =K106+L101 -> 0 | ... N106: =M106+N101 -> 0 | O106: =IF($B106="","",D106-SUM(E106:N106)) -> 0
B108: AMORTIZAÇÕES ACUMULADAS IMOB. COM PROJETO | D108: =SUM(D109:D111) -> 0 | E108: =SUM(E109:E111) -> 8462.524 | F108: =SUM(F109:F111) -> 26925.048 | G108: =SUM(G109:G111) -> 45387.572 | H108: =SUM(H109:H111) -> 63850.096 | I108: =SUM(I109:I111) -> 82312.62 | J108: =SUM(J109:J111) -> 90775.144 | K108: =SUM(K109:K111) -> 99237.668 | ... O108: =SUM(O109:O111) -> -765438.82
B109: Imobilizado Tangível | D109: =D94+D104 -> 0 | E109: =E94+E104 -> 8462.524 | F109: =F94+F104 -> 26925.048 | G109: =G94+G104 -> 45387.572 | H109: =H94+H104 -> 63850.096 | I109: =I94+I104 -> 82312.62 | J109: =J94+J104 -> 90775.144 | K109: =K94+K104 -> 99237.668 | ... N109: =N94+N104 -> 124625.24 | O109: =IF($B109="","",D109-SUM(E109:N109)) -> -765438.82
B110: Imobilizado Tangível - Biológico | D110: =D95+D105 -> 0 | E110: =E95+E105 -> 0 | F110: =F95+F105 -> 0 | G110: =G95+G105 -> 0 | H110: =H95+H105 -> 0 | I110: =I95+I105 -> 0 | J110: =J95+J105 -> 0 | K110: =K95+K105 -> 0 | ... N110: =N95+N105 -> 0 | O110: =IF($B110="","",D110-SUM(E110:N110)) -> 0
B111: Imobilizado Intangível | D111: =D96+D106 -> 0 | E111: =E96+E106 -> 0 | F111: =F96+F106 -> 0 | G111: =G96+G106 -> 0 | H111: =H96+H106 -> 0 | I111: =I96+I106 -> 0 | J111: =J96+J106 -> 0 | K111: =K96+K106 -> 0 | ... N111: =N96+N106 -> 0 | O111: =IF($B111="","",D111-SUM(E111:N111)) -> 0

Sheet Relatório
B2: Pré-Projeto | AB2: Vendas | AC2: Portugal
B3: Ano | C3: VN Total | D3: VN Nacional | E3: VN Internacional | F3: % IE | I3: Atividade económica por mercado (volume de negócios) | AB3: Compras | AC3: Afeganistão
B4: =Pressupostos!C10 -> 2018 | C4: =SUMIF(DR!D4:F5,Relatório!B4,DR!D6:F6) -> 0 | E4: =C4-D4 -> 0 | F4: =(C4-D4)/C4 -> #DIV/0! | AC4: África do Sul
I5: Tipo | J5: Bem / Serviço | K5: Mercado (País) | L5: Ano Pré-Projeto | N5: Ano Pós-Projeto | AB5: Transportes marítimos | AC5: Albânia
B6: Total Investimento | C6: =Faturas!E285 -> 93765.25 | L6: Quant. | M6: Valor | N6: Quant. | O6: Valor | AB6: Transportes aéreos | AC6: Alemanha
B7: VN Pós Projeto | C7: =C15 -> 4401123.4 | M7: =C18 -> 0 | O7: =G18 -> 4401123.4 | AB7: Transportes rodoviários | AC7: Andorra
B8: VN Pós Projeto (mínimo) | C8: =C4+(C6*1.1)/C10 -> #DIV/0! | M8: =C19 -> 0 | O8: =G19 -> #DIV/0! | AB8: Outros transportes | AC8: Angola
B9: Diferença | C9: =C7-C8 -> #DIV/0! | M9: =C20 -> 0 | O9: =G20 -> #DIV/0! | AB9: Fretes de mercadorias | AC9: Anguila
B10: % IE Pós-Projeto (prevista) | M10: =C21 -> 0 | O10: =G21 -> #DIV/0! | AB10: Passagens | AC10: Antárctica
B11: Pós Projeto: VN Intern. Mínimo | C11: =E4+C6 -> 93765.25 | M11: =C22 -> 0 | O11: =G22 -> #DIV/0! | AB11: Outros serviços de transporte | AC11: Antígua e Barbuda
M12: =C23 -> 0 | O12: =G23 -> #DIV/0! | AB12: Viagens e turismo | AC12: Antilhas Holandesas
B13: Pós-Projeto | M13: =C24 -> 0 | O13: =G24 -> #DIV/0! | AB13: Serviços de comunicação | AC13: Arábia Saudita
B14: Ano | C14: VN Total | D14: VN Nacional | E14: VN Internacional | F14: % IE | M14: =C25 -> 0 | O14: =G25 -> #DIV/0! | AB14: Serviços de construção | AC14: Argélia
B15: =Pressupostos!C13 -> 2023 | C15: =SUMIF('DR Empresa'!C4:L4,B15,'DR Empresa'!C5:L5) -> 4401123.4 | D15: =C15-E15 -> 4401123.4 | E15: =C15*F15 -> 0 | F15: =C10 -> 0 | AB15: Seguros | AC15: Argentina
AB16: Serviços financeiros | AC16: Arménia
B17: Países | C17: VN Pré-Projeto | D17: € Invest. | E17: % Invest. | F17: VN Pós-Projeto indicativo | G17: VN Pós-Projeto efetivo | AB17: Serviços de informação e informática | AC17: Aruba
B18: Portugal | C18: =D4 -> 0 | D18: 0 | F18: =D15 -> 4401123.4 | G18: =F18 -> 4401123.4 | AB18: Serviços de intermediação comercial | AC18: Austrália
E19: =D19/$D$31 -> #DIV/0! | F19: =$E$15*E19 -> #DIV/0! | G19: =F19 -> #DIV/0! | AB19: Serviços de aluguer sem tripulação | AC19: Áustria
E20: =D20/$D$31 -> #DIV/0! | F20: =$E$15*E20 -> #DIV/0! | G20: =F20 -> #DIV/0! | AB20: Serviços agrícolas, mineiros e industriais | AC20: Azerbaijão
E21: =D21/$D$31 -> #DIV/0! | F21: =$E$15*E21 -> #DIV/0! | G21: =F21 -> #DIV/0! | AB21: Serviços de investigação e desenvolvimento | AC21: Bahamas
E22: =D22/$D$31 -> #DIV/0! | F22: =$E$15*E22 -> #DIV/0! | G22: =F22 -> #DIV/0! | AB22: Serv. jurídicos, contab. e consult. em gestão e de relações públicas | AC22: Bangladesh
E23: =D23/$D$31 -> #DIV/0! | F23: =$E$15*E23 -> #DIV/0! | G23: =F23 -> #DIV/0! | AB23: Serviços de arquitetura, de engenharia e de consultadoria técnica | AC23: Barbados
E24: =D24/$D$31 -> #DIV/0! | F24: =$E$15*E24 -> #DIV/0! | G24: =F24 -> #DIV/0! | AB24: Serviços de publicidade, estudos de mercado e de opinião pública | AC24: Barém
E25: =D25/$D$31 -> #DIV/0! | F25: =$E$15*E25 -> #DIV/0! | G25: =F25 -> #DIV/0! | AB25: Serviços entre empresas afiliadas | AC25: Bélgica
E26: =D26/$D$31 -> #DIV/0! | F26: =$E$15*E26 -> #DIV/0! | G26: =F26 -> #DIV/0! | AB26: Outros serviços fornecidos por empresas | AC26: Belize
E27: =D27/$D$31 -> #DIV/0! | F27: =$E$15*E27 -> #DIV/0! | G27: =F27 -> #DIV/0! | AB27: Direitos de utilização | AC27: Benim
E28: =D28/$D$31 -> #DIV/0! | F28: =$E$15*E28 -> #DIV/0! | G28: =F28 -> #DIV/0! | AB28: Serviços de natureza pessoal, cultural e recreativa | AC28: Bermudas
E29: =D29/$D$31 -> #DIV/0! | F29: =$E$15*E29 -> #DIV/0! | G29: =F29 -> #DIV/0! | AB29: Operações governamentais | AC29: Bielorrússia
E30: =D30/$D$31 -> #DIV/0! | F30: =$E$15*E30 -> #DIV/0! | G30: =F30 -> #DIV/0! | AB30: 01 - Animais vivos | AC30: Bolívia, Estado Plurinacional da
C31: =SUM(C18:C30) -> 0 | D31: =SUM(D19:D30) -> 0 | E31: =SUM(E19:E30) -> #DIV/0! | F31: =SUM(F18:F30) -> #DIV/0! | G31: =SUM(G18:G30) -> #DIV/0! | AB31: 02 - Carnes e miudezas, comestíveis | AC31: Bósnia-Herzegovina
F32: =F31-G31 -> #DIV/0! | M32: =SUM(M8:M31) -> 0 | O32: =SUM(O8:O31) -> #DIV/0! | AB32: 03 - Peixes e crustáceos, moluscos e outros invertebrados aquáticos | AC32: Botswana
AB33: 04 - Leite e lacticínios; ovos de aves; mel natural; produtos comestíveis de origem animal, não especificados nem compreendidos noutros capítulos | AC33: Brasil
AB34: 05 - Outros produtos de origem animal, não especificados nem compreendidos noutros capítulos | AC34: Brunei Darussalam
AB35: 06 - Plantas vivas e produtos de floricultura | AC35: Bulgária
AB36: 07 - Produtos hortícolas, plantas, raízes e tubérculos, comestíveis | AC36: Burkina Faso
AB37: 08 - Frutas; cascas de citrinos e de melões | AC37: Burundi
AB38: 09 - Café, chá, mate e especiarias | AC38: Butão
AB39: 10 - Cereais | AC39: Cabo Verde
AB40: 11 - Produtos da indústria de moagem; malte; amidos e féculas; inulina; glúten de trigo | AC40: Camarões
AB41: 12 - Sementes e frutos oleaginosos; grãos, sementes e frutos diversos; plantas industriais ou medicinais; palhas e forragens | AC41: Camboja
AB42: 13 - Gomas, resinas e outros sucos e extratos vegetais | AC42: Canadá
AB43: 14 - Matérias para entrançar e outros produtos de origem vegetal, não especificados nem compreendidos em noutros capítulos | AC43: Catar
AB44: 15 - Gorduras e óleos animais ou vegetais; produtos da sua dissociação; gorduras alimentares elaboradas; ceras de origem animal ou vegetal | AC44: Cazaquistão
... AB126: 98 - Conjuntos industriais | AC126: Jamaica
AC127: Japão
AC128: Jersey
AC129: Jibuti
AC130: Jordânia
AC131: Kiribati
AC132: Kosovo
AC133: Kuwait
AC134: Laos (República Popular Democrática do)
AC135: Lesoto
AC136: Letónia
AC137: Líbano
AC138: Libéria
... AC248: Zimbabwe

Sheet DR_Form
A1: DR Formulário Original
B2: =C2-1 -> 2017 | C2: =D2-1 -> 2018 | D2: =E2-1 -> 2019 | E2: =Pressupostos!C11 -> 2020 | F2: =E2+1 -> 2021 | G2: =F2+1 -> 2022 | H2: =G2+1 -> 2023 | I2: =H2+1 -> 2024 | J2: =I2+1 -> 2025 | K2: =J2+1 -> 2026 | L2: =K2+1 -> 2027
A3: Vendas e serviços prestados | B3: =DR!D6 -> 0 | C3: =DR!E6 -> 0 | D3: =DR!F6 -> 3479532.1 | E3: ='DR Empresa'!C5 -> 3690043.8 | F3: ='DR Empresa'!D5 -> 3913291.5 | G3: ='DR Empresa'!E5 -> 4150045.6 | H3: ='DR Empresa'!F5 -> 4401123.4 | I3: ='DR Empresa'!G5 -> 4489586 | J3: ='DR Empresa'!H5 -> 4579826.6 | K3: ='DR Empresa'!I5 -> 4671881.2 | L3: ='DR Empresa'!J5 -> 4765786
A4: Subsídios à exploração | B4: =DR!D7 -> 0 | C4: =DR!E7 -> 0 | D4: =DR!F7 -> 49.26 | E4: ='DR Empresa'!C6 -> 9281.3625 | F4: ='DR Empresa'!D6 -> 26253 | G4: ='DR Empresa'!E6 -> 6660 | H4: ='DR Empresa'!F6 -> 0 | I4: ='DR Empresa'!G6 -> 0 | J4: ='DR Empresa'!H6 -> 0 | K4: ='DR Empresa'!I6 -> 0 | L4: ='DR Empresa'!J6 -> 0
A5: Ganhos/perdas imputados de subsidiárias, associadas a empreendimentos conjuntos | B5: =DR!D8 -> 0 | C5: =DR!E8 -> 0 | D5: =DR!F8 -> 0 | E5: ='DR Empresa'!C7 -> 0 | F5: ='DR Empresa'!D7 -> 0 | G5: ='DR Empresa'!E7 -> 0 | H5: ='DR Empresa'!F7 -> 0 | I5: ='DR Empresa'!G7 -> 0 | J5: ='DR Empresa'!H7 -> 0 | K5: ='DR Empresa'!I7 -> 0 | L5: ='DR Empresa'!J7 -> 0
A6: Variação nos inventários da produção | B6: =DR!D9 -> 0 | C6: =DR!E9 -> 0 | D6: =DR!F9 -> 0 | E6: ='DR Empresa'!C8 -> 0 | F6: ='DR Empresa'!D8 -> 0 | G6: ='DR Empresa'!E8 -> 0 | H6: ='DR Empresa'!F8 -> 0 | I6: ='DR Empresa'!G8 -> 0 | J6: ='DR Empresa'!H8 -> 0 | K6: ='DR Empresa'!I8 -> 0 | L6: ='DR Empresa'!J8 -> 0
A7: Trabalhos para a própria entidade | B7: =DR!D10 -> 0 | C7: =DR!E10 -> 0 | D7: =DR!F10 -> 0 | E7: ='DR Empresa'!C9 -> 0 | F7: ='DR Empresa'!D9 -> 0 | G7: ='DR Empresa'!E9 -> 0 | H7: ='DR Empresa'!F9 -> 0 | I7: ='DR Empresa'!G9 -> 0 | J7: ='DR Empresa'!H9 -> 0 | K7: ='DR Empresa'!I9 -> 0 | L7: ='DR Empresa'!J9 -> 0
A8: Custo das mercadorias vendidas e das matérias consumidas | B8: =DR!D11 -> 0 | C8: =DR!E11 -> 0 | D8: =DR!F11 -> 2780591.1 | E8: ='DR Empresa'!C10 -> 2896684.4 | F8: ='DR Empresa'!D10 -> 3071933.8 | G8: ='DR Empresa'!E10 -> 3237035.6 | H8: ='DR Empresa'!F10 -> 3432876.2 | I8: ='DR Empresa'!G10 -> 3501877 | J8: ='DR Empresa'!H10 -> 3572264.8 | K8: ='DR Empresa'!I10 -> 3644067.3 | L8: ='DR Empresa'!J10 -> 3717313.1
A9: Fornecimentos e serviços externos | B9: =DR!D12 -> 0 | C9: =DR!E12 -> 0 | D9: =DR!F12 -> 506782.86 | E9: ='DR Empresa'!C11 -> 532475.94 | F9: ='DR Empresa'!D11 -> 546634.35 | G9: ='DR Empresa'!E11 -> 575056.16 | H9: ='DR Empresa'!F11 -> 594151.66 | I9: ='DR Empresa'!G11 -> 606094.1 | J9: ='DR Empresa'!H11 -> 618276.6 | K9: ='DR Empresa'!I11 -> 630703.96 | L9: ='DR Empresa'!J11 -> 643381.11
A10: Gastos com o pessoal | B10: =DR!D13 -> 0 | C10: =DR!E13 -> 0 | D10: =DR!F13 -> 169363.3 | E10: ='DR Empresa'!C12 -> 218097.59 | F10: ='DR Empresa'!D12 -> 254274.54 | G10: ='DR Empresa'!E12 -> 269965.03 | H10: ='DR Empresa'!F12 -> 275364.33 | I10: ='DR Empresa'!G12 -> 280871.62 | J10: ='DR Empresa'!H12 -> 286489.05 | K10: ='DR Empresa'!I12 -> 292218.83 | L10: ='DR Empresa'!J12 -> 298063.21
A11: Imparidade de inventários (perdas/reversões) | B11: =DR!D14 -> 0 | C11: =DR!E14 -> 0 | D11: =DR!F14 -> 0 | E11: ='DR Empresa'!C13 -> 0 | F11: ='DR Empresa'!D13 -> 0 | G11: ='DR Empresa'!E13 -> 0 | H11: ='DR Empresa'!F13 -> 0 | I11: ='DR Empresa'!G13 -> 0 | J11: ='DR Empresa'!H13 -> 0 | K11: ='DR Empresa'!I13 -> 0 | L11: ='DR Empresa'!J13 -> 0
A12: Imparidade de dívidas a receber (perdas/reversões) | B12: =DR!D15 -> 0 | C12: =DR!E15 -> 0 | D12: =DR!F15 -> 40.26 | E12: ='DR Empresa'!C14 -> 0 | F12: ='DR Empresa'!D14 -> 0 | G12: ='DR Empresa'!E14 -> 0 | H12: ='DR Empresa'!F14 -> 0 | I12: ='DR Empresa'!G14 -> 0 | J12: ='DR Empresa'!H14 -> 0 | K12: ='DR Empresa'!I14 -> 0 | L12: ='DR Empresa'!J14 -> 0
A13: Provisões (aumentos/reduções) | B13: =DR!D16 -> 0 | C13: =DR!E16 -> 0 | D13: =DR!F16 -> 0 | E13: ='DR Empresa'!C15 -> 0 | F13: ='DR Empresa'!D15 -> 0 | G13: ='DR Empresa'!E15 -> 0 | H13: ='DR Empresa'!F15 -> 0 | I13: ='DR Empresa'!G15 -> 0 | J13: ='DR Empresa'!H15 -> 0 | K13: ='DR Empresa'!I15 -> 0 | L13: ='DR Empresa'!J15 -> 0
A14: Imparidade de investimentos não depreciáveis/amortizáveis (perdas/reversões) | B14: =DR!D17 -> 0 | C14: =DR!E17 -> 0 | D14: =DR!F17 -> 0 | E14: ='DR Empresa'!C16 -> 0 | F14: ='DR Empresa'!D16 -> 0 | G14: ='DR Empresa'!E16 -> 0 | H14: ='DR Empresa'!F16 -> 0 | I14: ='DR Empresa'!G16 -> 0 | J14: ='DR Empresa'!H16 -> 0 | K14: ='DR Empresa'!I16 -> 0 | L14: ='DR Empresa'!J16 -> 0
... A16: Aumentos/reduções de justo valor | B16: =DR!D19 -> 0 | C16: =DR!E19 -> 0 | D16: =DR!F19 -> 0 | E16: ='DR Empresa'!C18 -> 0 | F16: ='DR Empresa'!D18 -> 0 | G16: ='DR Empresa'!E18 -> 0 | H16: ='DR Empresa'!F18 -> 0 | I16: ='DR Empresa'!G18 -> 0 | J16: ='DR Empresa'!H18 -> 0 | K16: ='DR Empresa'!I18 -> 0 | L16: ='DR Empresa'!J18 -> 0
A17: Outros rendimentos e ganhos
A18: Rendimentos suplementares
A19: Outros | B19: =DR!D20 -> 0 | C19: =DR!E20 -> 0 | D19: =DR!F20 -> 73417.34 | E19: ='DR Empresa'!C19 -> 0 | F19: ='DR Empresa'!D19 -> 27195.75 | G19: ='DR Empresa'!E19 -> 12616.875 | H19: ='DR Empresa'!F19 -> 3262.5 | I19: ='DR Empresa'!G19 -> 3262.5 | J19: ='DR Empresa'!H19 -> 0 | K19: ='DR Empresa'!I19 -> 0 | L19: ='DR Empresa'!J19 -> 0
A20: Outros gastos e perdas
A21: Impostos indiretos
A22: Outros | B22: =DR!D21 -> 0 | C22: =DR!E21 -> 0 | D22: =DR!F21 -> 37622.48 | E22: ='DR Empresa'!C20 -> 0 | F22: ='DR Empresa'!D20 -> 0 | G22: ='DR Empresa'!E20 -> 0 | H22: ='DR Empresa'!F20 -> 0 | I22: ='DR Empresa'!G20 -> 0 | J22: ='DR Empresa'!H20 -> 0 | K22: ='DR Empresa'!I20 -> 0 | L22: ='DR Empresa'!J20 -> 0
A23: Resultado antes de depreciações, gastos de financiamento e impostos
A24: Gastos/reversões de depreciação e de amortização | B24: =DR!D23 -> 0 | C24: =DR!E23 -> 0 | D24: =DR!F23 -> 15247.25 | E24: ='DR Empresa'!C22 -> 8462.524 | F24: ='DR Empresa'!D22 -> 18462.524 | G24: ='DR Empresa'!E22 -> 18462.524 | H24: ='DR Empresa'!F22 -> 18462.524 | I24: ='DR Empresa'!G22 -> 18462.524 | J24: ='DR Empresa'!H22 -> 8462.524 | K24: ='DR Empresa'!I22 -> 8462.524 | L24: ='DR Empresa'!J22 -> 8462.524
A25: Imparidade de Investimentos depreciáveis/amortizáveis (perdas/reversões) | B25: =DR!D24 -> 0 | C25: =DR!E24 -> 0 | D25: =DR!F24 -> 0 | E25: ='DR Empresa'!C23 -> 0 | F25: ='DR Empresa'!D23 -> 0 | G25: ='DR Empresa'!E23 -> 0 | H25: ='DR Empresa'!F23 -> 0 | I25: ='DR Empresa'!G23 -> 0 | J25: ='DR Empresa'!H23 -> 0 | K25: ='DR Empresa'!I23 -> 0 | L25: ='DR Empresa'!J23 -> 0
A26: Resultado operacional (antes de gastos de financiamento e impostos)
A27: Juros e rendimentos similares obtidos | B27: =DR!D26 -> 0 | C27: =DR!E26 -> 0 | D27: =DR!F26 -> 0 | E27: ='DR Empresa'!C25 -> 0 | F27: ='DR Empresa'!D25 -> 0 | G27: ='DR Empresa'!E25 -> 0 | H27: ='DR Empresa'!F25 -> 0 | I27: ='DR Empresa'!G25 -> 0 | J27: ='DR Empresa'!H25 -> 0 | K27: ='DR Empresa'!I25 -> 0 | L27: ='DR Empresa'!J25 -> 0
A28: Juros e gastos similares suportados | B28: =DR!D27 -> 0 | C28: =DR!E27 -> 0 | D28: =DR!F27 -> 1053 | E28: ='DR Empresa'!C26 -> 11672.263 | F28: ='DR Empresa'!D26 -> 11657.01 | G28: ='DR Empresa'!E26 -> 11595.996 | H28: ='DR Empresa'!F26 -> 11534.983 | I28: ='DR Empresa'!G26 -> 11473.97 | J28: ='DR Empresa'!H26 -> 11428.21 | K28: ='DR Empresa'!I26 -> 11428.21 | L28: ='DR Empresa'!J26 -> 11428.21
A29: Resultado antes de impostos
A30: Imposto sobre o rendimento do período | B30: =DR!D29 -> 0 | C30: =DR!E29 -> 0 | D30: =DR!F29 -> 10443.87 | E30: ='DR Empresa'!C28 -> 7184.8061 | F30: ='DR Empresa'!D28 -> 14350.049 | G30: ='DR Empresa'!E28 -> 12871.62 | H30: ='DR Empresa'!F28 -> 16199.133 | I30: ='DR Empresa'!G28 -> 16665.569 | J30: ='DR Empresa'!H28 -> 18653.733 | K30: ='DR Empresa'!I28 -> 19125.075 | L30: ='DR Empresa'!J28 -> 19606.019
A31: Resultado líquido do período
A32: Resultado das atividades descontinuadas (líquido de impostos) incluído no resultado líquido do período
A34: Resultados Líquidos DR Form | B34: =B3+B4+B5+B6+B7-B8-B9-B10-B11-B12-B13-B14-B15+B16+B18+B19-B21-B22-B24-B25+B27-B28-B30 -> 0 | C34: =C3+C4+C5+C6+C7-C8-C9-C10-C11-C12-C13-C14-C15+C16+C18+C19-C21-C22-C24-C25+C27-C28-C30 -> 0 | D34: =D3+D4+D5+D6+D7-D8-D9-D10-D11-D12-D13-D14-D15+D16+D18+D19-D21-D22-D24-D25+D27-D28-D30 -> 31854.57 | E34: =E3+E4+E5+E6+E7-E8-E9-E10-E11-E12-E13-E14-E15+E16+E18+E19-E21-E22-E24-E25+E27-E28-E30 -> 24747.666 | F34: =F3+F4+F5+F6+F7-F8-F9-F10-F11-F12-F13-F14-F15+F16+F18+F19-F21-F22-F24-F25+F27-F28-F30 -> 49427.945 | G34: =G3+G4+G5+G6+G7-G8-G9-G10-G11-G12-G13-G14-G15+G16+G18+G19-G21-G22-G24-G25+G27-G28-G30 -> 44335.58 | H34: =H3+H4+H5+H6+H7-H8-H9-H10-H11-H12-H13-H14-H15+H16+H18+H19-H21-H22-H24-H25+H27-H28-H30 -> 55797.014 | I34: =I3+I4+I5+I6+I7-I8-I9-I10-I11-I12-I13-I14-I15+I16+I18+I19-I21-I22-I24-I25+I27-I28-I30 -> 57403.625 | ... L34: =L3+L4+L5+L6+L7-L8-L9-L10-L11-L12-L13-L14-L15+L16+L18+L19-L21-L22-L24-L25+L27-L28-L30 -> 67531.844
A35: Resultados Líquidos DR Empresa | B35: =DR!D30 -> 0 | C35: =DR!E30 -> 0 | D35: =DR!F30 -> 31854.57 | E35: ='DR Empresa'!C29 -> 24747.666 | F35: ='DR Empresa'!D29 -> 49427.945 | G35: ='DR Empresa'!E29 -> 44335.58 | H35: ='DR Empresa'!F29 -> 55797.014 | I35: ='DR Empresa'!G29 -> 57403.625 | J35: ='DR Empresa'!H29 -> 64251.746 | K35: ='DR Empresa'!I29 -> 65875.257 | L35: ='DR Empresa'!J29 -> 67531.844
A36: Diferença | B36: =B34-B35 -> 0 | C36: =C34-C35 -> 0 | D36: =D34-D35 -> 0 | E36: =E34-E35 -> 0 | F36: =F34-F35 -> 0 | G36: =G34-G35 -> 0 | H36: =H34-H35 -> 0 | I36: =I34-I35 -> 0 | ... L36: =L34-L35 -> 0
A39: DR Formulário com Arredondamentos
B40: =B2 -> 2017 | C40: =C2 -> 2018 | D40: =D2 -> 2019 | E40: =E2 -> 2020 | F40: =F2 -> 2021 | G40: =G2 -> 2022 | H40: =H2 -> 2023 | I40: =I2 -> 2024 | ... L40: =L2 -> 2027
A41: Vendas e serviços prestados | B41: =ROUND(B3,2) -> 0 | C41: =ROUND(C3,2) -> 0 | D41: =ROUND(D3,2) -> 3479532.1 | E41: =ROUND(E3,2) -> 3690043.8 | F41: =ROUND(F3,2) -> 3913291.5 | G41: =ROUND(G3,2) -> 4150045.6 | H41: =ROUND(H3,2) -> 4401123.4 | I41: =ROUND(I3,2) -> 4489586 | ... L41: =ROUND(L3,2) -> 4765786
A42: Subsídios à exploração | B42: =ROUND(B4,2) -> 0 | C42: =ROUND(C4,2) -> 0 | D42: =ROUND(D4,2) -> 49.26 | E42: =ROUND(E4,2) -> 9281.36 | F42: =ROUND(F4,2) -> 26253 | G42: =ROUND(G4,2) -> 6660 | H42: =ROUND(H4,2) -> 0 | I42: =ROUND(I4,2) -> 0 | ... L42: =ROUND(L4,2) -> 0
A43: Ganhos/perdas imputados de subsidiárias, associadas a empreendimentos conjuntos | B43: =ROUND(B5,2) -> 0 | C43: =ROUND(C5,2) -> 0 | D43: =ROUND(D5,2) -> 0 | E43: =ROUND(E5,2) -> 0 | F43: =ROUND(F5,2) -> 0 | G43: =ROUND(G5,2) -> 0 | H43: =ROUND(H5,2) -> 0 | I43: =ROUND(I5,2) -> 0 | ... L43: =ROUND(L5,2) -> 0
A44: Variação nos inventários da produção | B44: =ROUND(B6,2) -> 0 | C44: =ROUND(C6,2) -> 0 | D44: =ROUND(D6,2) -> 0 | E44: =ROUND(E6,2) -> 0 | F44: =ROUND(F6,2) -> 0 | G44: =ROUND(G6,2) -> 0 | H44: =ROUND(H6,2) -> 0 | I44: =ROUND(I6,2) -> 0 | ... L44: =ROUND(L6,2) -> 0
A45: Trabalhos para a própria entidade | B45: =ROUND(B7,2) -> 0 | C45: =ROUND(C7,2) -> 0 | D45: =ROUND(D7,2) -> 0 | E45: =ROUND(E7,2) -> 0 | F45: =ROUND(F7,2) -> 0 | G45: =ROUND(G7,2) -> 0 | H45: =ROUND(H7,2) -> 0 | I45: =ROUND(I7,2) -> 0 | ... L45: =ROUND(L7,2) -> 0
A46: Custo das mercadorias vendidas e das matérias consumidas | B46: =ROUND(B8,2) -> 0 | C46: =ROUND(C8,2) -> 0 | D46: =ROUND(D8,2) -> 2780591.1 | E46: =ROUND(E8,2) -> 2896684.4 | F46: =ROUND(F8,2) -> 3071933.8 | G46: =ROUND(G8,2) -> 3237035.6 | H46: =ROUND(H8,2) -> 3432876.2 | I46: =ROUND(I8,2) -> 3501877 | ... L46: =ROUND(L8,2) -> 3717313
A47: Fornecimentos e serviços externos | B47: =ROUND(B9,2) -> 0 | C47: =ROUND(C9,2) -> 0 | D47: =ROUND(D9,2) -> 506782.86 | E47: =ROUND(E9,2) -> 532475.94 | F47: =ROUND(F9,2) -> 546634.35 | G47: =ROUND(G9,2) -> 575056.16 | H47: =ROUND(H9,2) -> 594151.66 | I47: =ROUND(I9,2) -> 606094.1 | ... L47: =ROUND(L9,2) -> 643381.11
A48: Gastos com o pessoal | B48: =ROUND(B10,2) -> 0 | C48: =ROUND(C10,2) -> 0 | D48: =ROUND(D10,2) -> 169363.3 | E48: =ROUND(E10,2) -> 218097.59 | F48: =ROUND(F10,2) -> 254274.54 | G48: =ROUND(G10,2) -> 269965.03 | H48: =ROUND(H10,2) -> 275364.33 | I48: =ROUND(I10,2) -> 280871.62 | ... L48: =ROUND(L10,2) -> 298063.21
A49: Imparidade de inventários (perdas/reversões) | B49: =ROUND(B11,2) -> 0 | C49: =ROUND(C11,2) -> 0 | D49: =ROUND(D11,2) -> 0 | E49: =ROUND(E11,2) -> 0 | F49: =ROUND(F11,2) -> 0 | G49: =ROUND(G11,2) -> 0 | H49: =ROUND(H11,2) -> 0 | I49: =ROUND(I11,2) -> 0 | ... L49: =ROUND(L11,2) -> 0
A50: Imparidade de dívidas a receber (perdas/reversões) | B50: =ROUND(B12,2) -> 0 | C50: =ROUND(C12,2) -> 0 | D50: =ROUND(D12,2) -> 40.26 | E50: =ROUND(E12,2) -> 0 | F50: =ROUND(F12,2) -> 0 | G50: =ROUND(G12,2) -> 0 | H50: =ROUND(H12,2) -> 0 | I50: =ROUND(I12,2) -> 0 | ... L50: =ROUND(L12,2) -> 0
A51: Provisões (aumentos/reduções) | B51: =ROUND(B13,2) -> 0 | C51: =ROUND(C13,2) -> 0 | D51: =ROUND(D13,2) -> 0 | E51: =ROUND(E13,2) -> 0 | F51: =ROUND(F13,2) -> 0 | G51: =ROUND(G13,2) -> 0 | H51: =ROUND(H13,2) -> 0 | I51: =ROUND(I13,2) -> 0 | ... L51: =ROUND(L13,2) -> 0
A52: Imparidade de investimentos não depreciáveis/amortizáveis (perdas/reversões) | B52: =ROUND(B14,2) -> 0 | C52: =ROUND(C14,2) -> 0 | D52: =ROUND(D14,2) -> 0 | E52: =ROUND(E14,2) -> 0 | F52: =ROUND(F14,2) -> 0 | G52: =ROUND(G14,2) -> 0 | H52: =ROUND(H14,2) -> 0 | I52: =ROUND(I14,2) -> 0 | ... L52: =ROUND(L14,2) -> 0
... A54: Aumentos/reduções de justo valor | B54: =ROUND(B16,2) -> 0 | C54: =ROUND(C16,2) -> 0 | D54: =ROUND(D16,2) -> 0 | E54: =ROUND(E16,2) -> 0 | F54: =ROUND(F16,2) -> 0 | G54: =ROUND(G16,2) -> 0 | H54: =ROUND(H16,2) -> 0 | I54: =ROUND(I16,2) -> 0 | ... L54: =ROUND(L16,2) -> 0
A55: Outros rendimentos e ganhos
A56: Rendimentos suplementares | B56: =ROUND(B18,2) -> 0 | C56: =ROUND(C18,2) -> 0 | D56: =ROUND(D18,2) -> 0 | E56: =ROUND(E18,2) -> 0 | F56: =ROUND(F18,2) -> 0 | G56: =ROUND(G18,2) -> 0 | H56: =ROUND(H18,2) -> 0 | I56: =ROUND(I18,2) -> 0 | ... L56: =ROUND(L18,2) -> 0
A57: Outros | B57: =ROUND(B19,2) -> 0 | C57: =ROUND(C19,2) -> 0 | D57: =ROUND(D19,2) -> 73417.34 | E57: =ROUND(E19,2) -> 0 | F57: =ROUND(F19,2) -> 27195.75 | G57: =ROUND(G19,2) -> 12616.88 | H57: =ROUND(H19,2) -> 3262.5 | I57: =ROUND(I19,2) -> 3262.5 | ... L57: =ROUND(L19,2) -> 0
A58: Outros gastos e perdas
A59: Impostos indiretos | B59: =ROUND(B21,2) -> 0 | C59: =ROUND(C21,2) -> 0 | D59: =ROUND(D21,2) -> 0 | E59: =ROUND(E21,2) -> 0 | F59: =ROUND(F21,2) -> 0 | G59: =ROUND(G21,2) -> 0 | H59: =ROUND(H21,2) -> 0 | I59: =ROUND(I21,2) -> 0 | ... L59: =ROUND(L21,2) -> 0
A60: Outros | B60: =ROUND(B22,2) -> 0 | C60: =ROUND(C22,2) -> 0 | D60: =ROUND(D22,2) -> 37622.48 | E60: =ROUND(E22,2) -> 0 | F60: =ROUND(F22,2) -> 0 | G60: =ROUND(G22,2) -> 0 | H60: =ROUND(H22,2) -> 0 | I60: =ROUND(I22,2) -> 0 | ... L60: =ROUND(L22,2) -> 0
A61: Resultado antes de depreciações, gastos de financiamento e impostos
A62: Gastos/reversões de depreciação e de amortização | B62: =ROUND(B24,2) -> 0 | C62: =ROUND(C24,2) -> 0 | D62: =ROUND(D24,2) -> 15247.25 | E62: =ROUND(E24,2) -> 8462.52 | F62: =ROUND(F24,2) -> 18462.52 | G62: =ROUND(G24,2) -> 18462.52 | H62: =ROUND(H24,2) -> 18462.52 | I62: =ROUND(I24,2) -> 18462.52 | ... L62: =ROUND(L24,2) -> 8462.52
A63: Imparidade de Investimentos depreciáveis/amortizáveis (perdas/reversões) | B63: =ROUND(B25,2) -> 0 | C63: =ROUND(C25,2) -> 0 | D63: =ROUND(D25,2) -> 0 | E63: =ROUND(E25,2) -> 0 | F63: =ROUND(F25,2) -> 0 | G63: =ROUND(G25,2) -> 0 | H63: =ROUND(H25,2) -> 0 | I63: =ROUND(I25,2) -> 0 | ... L63: =ROUND(L25,2) -> 0
A64: Resultado operacional (antes de gastos de financiamento e impostos)
A65: Juros e rendimentos similares obtidos | B65: =ROUND(B27,2) -> 0 | C65: =ROUND(C27,2) -> 0 | D65: =ROUND(D27,2) -> 0 | E65: =ROUND(E27,2) -> 0 | F65: =ROUND(F27,2) -> 0 | G65: =ROUND(G27,2) -> 0 | H65: =ROUND(H27,2) -> 0 | I65: =ROUND(I27,2) -> 0 | ... L65: =ROUND(L27,2) -> 0
A66: Juros e gastos similares suportados | B66: =ROUND(B28,2) -> 0 | C66: =ROUND(C28,2) -> 0 | D66: =ROUND(D28,2) -> 1053 | E66: =ROUND(E28,2) -> 11672.26 | F66: =ROUND(F28,2) -> 11657.01 | G66: =ROUND(G28,2) -> 11596 | H66: =ROUND(H28,2) -> 11534.98 | I66: =ROUND(I28,2) -> 11473.97 | ... L66: =ROUND(L28,2) -> 11428.21
A67: Resultado antes de impostos
A68: Imposto sobre o rendimento do período | B68: =ROUND(B30,2) -> 0 | C68: =ROUND(C30,2) -> 0 | D68: =ROUND(D30,2) -> 10443.87 | E68: =ROUND(E30,2) -> 7184.81 | F68: =ROUND(F30,2) -> 14350.05 | G68: =ROUND(G30,2) -> 12871.62 | H68: =ROUND(H30,2) -> 16199.13 | I68: =ROUND(I30,2) -> 16665.57 | ... L68: =ROUND(L30,2) -> 19606.02
A69: Resultado líquido do período
A70: Resultado das atividades descontinuadas (líquido de impostos) incluído no resultado líquido do período
A72: Resultados Líquidos DR Form | B72: =ROUND(B41+B42+B43+B44+B45-B46-B47-B48-B49-B50-B51-B52-B53+B54+B56+B57-B59-B60-B62-B63+B65-B66-B68,2) -> 0 | C72: =ROUND(C41+C42+C43+C44+C45-C46-C47-C48-C49-C50-C51-C52-C53+C54+C56+C57-C59-C60-C62-C63+C65-C66-C68,2) -> 0 | D72: =ROUND(D41+D42+D43+D44+D45-D46-D47-D48-D49-D50-D51-D52-D53+D54+D56+D57-D59-D60-D62-D63+D65-D66-D68,2) -> 31854.57 | E72: =ROUND(E41+E42+E43+E44+E45-E46-E47-E48-E49-E50-E51-E52-E53+E54+E56+E57-E59-E60-E62-E63+E65-E66-E68,2) -> 24747.66 | F72: =ROUND(F41+F42+F43+F44+F45-F46-F47-F48-F49-F50-F51-F52-F53+F54+F56+F57-F59-F60-F62-F63+F65-F66-F68,2) -> 49427.95 | G72: =ROUND(G41+G42+G43+G44+G45-G46-G47-G48-G49-G50-G51-G52-G53+G54+G56+G57-G59-G60-G62-G63+G65-G66-G68,2) -> 44335.59 | H72: =ROUND(H41+H42+H43+H44+H45-H46-H47-H48-H49-H50-H51-H52-H53+H54+H56+H57-H59-H60-H62-H63+H65-H66-H68,2) -> 55797.02 | I72: =ROUND(I41+I42+I43+I44+I45-I46-I47-I48-I49-I50-I51-I52-I53+I54+I56+I57-I59-I60-I62-I63+I65-I66-I68,2) -> 57403.63 | ... L72: =ROUND(L41+L42+L43+L44+L45-L46-L47-L48-L49-L50-L51-L52-L53+L54+L56+L57-L59-L60-L62-L63+L65-L66-L68,2) -> 67531.85
A73: Resultados Líquidos DR Empresa | B73: =ROUND(B35,2) -> 0 | C73: =ROUND(C35,2) -> 0 | D73: =ROUND(D35,2) -> 31854.57 | E73: =ROUND(E35,2) -> 24747.67 | F73: =ROUND(F35,2) -> 49427.95 | G73: =ROUND(G35,2) -> 44335.58 | H73: =ROUND(H35,2) -> 55797.01 | I73: =ROUND(I35,2) -> 57403.62 | ... L73: =ROUND(L35,2) -> 67531.84
A74: Diferença | B74: =B72-B73 -> 0 | C74: =C72-C73 -> 0 | D74: =D72-D73 -> 0 | E74: =E72-E73 -> -0.01 | F74: =F72-F73 -> 0 | G74: =G72-G73 -> 0.01 | H74: =H72-H73 -> 0.01 | I74: =I72-I73 -> 0.01 | ... L74: =L72-L73 -> 0.01
A77: DR Formulário a Exportar
B78: =B2 -> 2017 | C78: =C2 -> 2018 | D78: =D2 -> 2019 | E78: =E2 -> 2020 | F78: =F2 -> 2021 | G78: =G2 -> 2022 | H78: =H2 -> 2023 | I78: =I2 -> 2024 | ... L78: =L2 -> 2027
A79: Vendas e serviços prestados | B79: =B41 -> 0 | C79: =C41 -> 0 | D79: =D41 -> 3479532.1 | E79: =E41 -> 3690043.8 | F79: =F41 -> 3913291.5 | G79: =G41 -> 4150045.6 | H79: =H41 -> 4401123.4 | I79: =I41 -> 4489586 | ... L79: =L41 -> 4765786
A80: Subsídios à exploração | B80: =B42 -> 0 | C80: =C42 -> 0 | D80: =D42 -> 49.26 | E80: =E42 -> 9281.36 | F80: =F42 -> 26253 | G80: =G42 -> 6660 | H80: =H42 -> 0 | I80: =I42 -> 0 | ... L80: =L42 -> 0
A81: Ganhos/perdas imputados de subsidiárias, associadas a empreendimentos conjuntos | B81: =B43 -> 0 | C81: =C43 -> 0 | D81: =D43 -> 0 | E81: =E43 -> 0 | F81: =F43 -> 0 | G81: =G43 -> 0 | H81: =H43 -> 0 | I81: =I43 -> 0 | ... L81: =L43 -> 0
A82: Variação nos inventários da produção | B82: =B44 -> 0 | C82: =C44 -> 0 | D82: =D44 -> 0 | E82: =E44 -> 0 | F82: =F44 -> 0 | G82: =G44 -> 0 | H82: =H44 -> 0 | I82: =I44 -> 0 | ... L82: =L44 -> 0
A83: Trabalhos para a própria entidade | B83: =B45 -> 0 | C83: =C45 -> 0 | D83: =D45 -> 0 | E83: =E45 -> 0 | F83: =F45 -> 0 | G83: =G45 -> 0 | H83: =H45 -> 0 | I83: =I45 -> 0 | ... L83: =L45 -> 0
A84: Custo das mercadorias vendidas e das matérias consumidas | B84: =B46 -> 0 | C84: =C46 -> 0 | D84: =D46 -> 2780591.1 | E84: =E46 -> 2896684.4 | F84: =F46 -> 3071933.8 | G84: =G46 -> 3237035.6 | H84: =H46 -> 3432876.2 | I84: =I46 -> 3501877 | ... L84: =L46 -> 3717313
A85: Fornecimentos e serviços externos | B85: =B47 -> 0 | C85: =C47 -> 0 | D85: =D47 -> 506782.86 | E85: =E47 -> 532475.94 | F85: =F47 -> 546634.35 | G85: =G47 -> 575056.16 | H85: =H47 -> 594151.66 | I85: =I47 -> 606094.1 | ... L85: =L47 -> 643381.11
A86: Gastos com o pessoal | B86: =B48 -> 0 | C86: =C48 -> 0 | D86: =D48 -> 169363.3 | E86: =E48 -> 218097.59 | F86: =F48 -> 254274.54 | G86: =G48 -> 269965.03 | H86: =H48 -> 275364.33 | I86: =I48 -> 280871.62 | ... L86: =L48 -> 298063.21
A87: Imparidade de inventários (perdas/reversões) | B87: =B49 -> 0 | C87: =C49 -> 0 | D87: =D49 -> 0 | E87: =E49 -> 0 | F87: =F49 -> 0 | G87: =G49 -> 0 | H87: =H49 -> 0 | I87: =I49 -> 0 | ... L87: =L49 -> 0
A88: Imparidade de dívidas a receber (perdas/reversões) | B88: =B50 -> 0 | C88: =C50 -> 0 | D88: =D50 -> 40.26 | E88: =E50 -> 0 | F88: =F50 -> 0 | G88: =G50 -> 0 | H88: =H50 -> 0 | I88: =I50 -> 0 | ... L88: =L50 -> 0
A89: Provisões (aumentos/reduções) | B89: =B51 -> 0 | C89: =C51 -> 0 | D89: =D51 -> 0 | E89: =E51 -> 0 | F89: =F51 -> 0 | G89: =G51 -> 0 | H89: =H51 -> 0 | I89: =I51 -> 0 | ... L89: =L51 -> 0
A90: Imparidade de investimentos não depreciáveis/amortizáveis (perdas/reversões) | B90: =B52 -> 0 | C90: =C52 -> 0 | D90: =D52 -> 0 | E90: =E52 -> 0 | F90: =F52 -> 0 | G90: =G52 -> 0 | H90: =H52 -> 0 | I90: =I52 -> 0 | ... L90: =L52 -> 0
... A92: Aumentos/reduções de justo valor | B92: =B54 -> 0 | C92: =C54 -> 0 | D92: =D54 -> 0 | E92: =E54 -> 0 | F92: =F54 -> 0 | G92: =G54 -> 0 | H92: =H54 -> 0 | I92: =I54 -> 0 | ... L92: =L54 -> 0
A93: Outros rendimentos e ganhos | B93: =B94+B95 -> 0 | C93: =C94+C95 -> 0 | D93: =D94+D95 -> 73417.34 | E93: =E94+E95 -> 0 | F93: =F94+F95 -> 27195.75 | G93: =G94+G95 -> 12616.88 | H93: =H94+H95 -> 3262.5 | I93: =I94+I95 -> 3262.5 | ... L93: =L94+L95 -> 0
A94: Rendimentos suplementares | B94: =B56 -> 0 | C94: =C56 -> 0 | D94: =D56 -> 0 | E94: =E56 -> 0 | F94: =F56 -> 0 | G94: =G56 -> 0 | H94: =H56 -> 0 | I94: =I56 -> 0 | ... L94: =L56 -> 0
A95: Outros | B95: =B57 -> 0 | C95: =C57 -> 0 | D95: =D57 -> 73417.34 | E95: =E57 -> 0 | F95: =F57 -> 27195.75 | G95: =G57 -> 12616.88 | H95: =H57 -> 3262.5 | I95: =I57 -> 3262.5 | ... L95: =L57 -> 0
A96: Outros gastos e perdas | B96: =B97+B98 -> 0 | C96: =C97+C98 -> 0 | D96: =D97+D98 -> 37622.48 | E96: =E97+E98 -> 0 | F96: =F97+F98 -> 0 | G96: =G97+G98 -> 0 | H96: =H97+H98 -> 0 | I96: =I97+I98 -> 0 | ... L96: =L97+L98 -> 0
A97: Impostos indiretos | B97: =B59 -> 0 | C97: =C59 -> 0 | D97: =D59 -> 0 | E97: =E59 -> 0 | F97: =F59 -> 0 | G97: =G59 -> 0 | H97: =H59 -> 0 | I97: =I59 -> 0 | ... L97: =L59 -> 0
A98: Outros | B98: =B60 -> 0 | C98: =C60 -> 0 | D98: =D60 -> 37622.48 | E98: =E60 -> 0 | F98: =F60 -> 0 | G98: =G60 -> 0 | H98: =H60 -> 0 | I98: =I60 -> 0 | ... L98: =L60 -> 0
A99: Resultado antes de depreciações, gastos de financiamento e impostos | B99: =B79+B80+B81+B82+B83-B84-B85-B86-B87-B88-B89-B90-B91+B92+B93-B96 -> 0 | C99: =C79+C80+C81+C82+C83-C84-C85-C86-C87-C88-C89-C90-C91+C92+C93-C96 -> 0 | D99: =D79+D80+D81+D82+D83-D84-D85-D86-D87-D88-D89-D90-D91+D92+D93-D96 -> 58598.69 | E99: =E79+E80+E81+E82+E83-E84-E85-E86-E87-E88-E89-E90-E91+E92+E93-E96 -> 52067.25 | F99: =F79+F80+F81+F82+F83-F84-F85-F86-F87-F88-F89-F90-F91+F92+F93-F96 -> 93897.53 | G99: =G79+G80+G81+G82+G83-G84-G85-G86-G87-G88-G89-G90-G91+G92+G93-G96 -> 87265.73 | H99: =H79+H80+H81+H82+H83-H84-H85-H86-H87-H88-H89-H90-H91+H92+H93-H96 -> 101993.65 | I99: =I79+I80+I81+I82+I83-I84-I85-I86-I87-I88-I89-I90-I91+I92+I93-I96 -> 104005.69 | ... L99: =L79+L80+L81+L82+L83-L84-L85-L86-L87-L88-L89-L90-L91+L92+L93-L96 -> 107028.6
A100: Gastos/reversões de depreciação e de amortização | B100: =B62 -> 0 | C100: =C62 -> 0 | D100: =D62 -> 15247.25 | E100: =E62 -> 8462.52 | F100: =F62 -> 18462.52 | G100: =G62 -> 18462.52 | H100: =H62 -> 18462.52 | I100: =I62 -> 18462.52 | ... L100: =L62 -> 8462.52
A101: Imparidade de Investimentos depreciáveis/amortizáveis (perdas/reversões) | B101: =B63 -> 0 | C101: =C63 -> 0 | D101: =D63 -> 0 | E101: =E63 -> 0 | F101: =F63 -> 0 | G101: =G63 -> 0 | H101: =H63 -> 0 | I101: =I63 -> 0 | ... L101: =L63 -> 0
A102: Resultado operacional (antes de gastos de financiamento e impostos) | B102: =B99-B100-B101 -> 0 | C102: =C99-C100-C101 -> 0 | D102: =D99-D100-D101 -> 43351.44 | E102: =E99-E100-E101 -> 43604.73 | F102: =F99-F100-F101 -> 75435.01 | G102: =G99-G100-G101 -> 68803.21 | H102: =H99-H100-H101 -> 83531.13 | I102: =I99-I100-I101 -> 85543.17 | ... L102: =L99-L100-L101 -> 98566.08
A103: Juros e rendimentos similares obtidos | B103: =B65 -> 0 | C103: =C65 -> 0 | D103: =D65 -> 0 | E103: =E65 -> 0 | F103: =F65 -> 0 | G103: =G65 -> 0 | H103: =H65 -> 0 | I103: =I65 -> 0 | ... L103: =L65 -> 0
A104: Juros e gastos similares suportados | B104: =B66 -> 0 | C104: =C66 -> 0 | D104: =D66 -> 1053 | E104: =E66 -> 11672.26 | F104: =F66 -> 11657.01 | G104: =G66 -> 11596 | H104: =H66 -> 11534.98 | I104: =I66 -> 11473.97 | ... L104: =L66 -> 11428.21
A105: Resultado antes de impostos | B105: =B102-B104+B103 -> 0 | C105: =C102-C104+C103 -> 0 | D105: =D102-D104+D103 -> 42298.44 | E105: =E102-E104+E103 -> 31932.47 | F105: =F102-F104+F103 -> 63778 | G105: =G102-G104+G103 -> 57207.21 | H105: =H102-H104+H103 -> 71996.15 | I105: =I102-I104+I103 -> 74069.2 | ... L105: =L102-L104+L103 -> 87137.87
A106: Imposto sobre o rendimento do período | B106: =IF(B74=0,B68,B68+B74) -> 0 | C106: =IF(C74=0,C68,C68+C74) -> 0 | D106: =IF(D74=0,D68,D68+D74) -> 10443.87 | E106: =IF(E74=0,E68,E68+E74) -> 7184.8 | F106: =IF(F74=0,F68,F68+F74) -> 14350.05 | G106: =IF(G74=0,G68,G68+G74) -> 12871.63 | H106: =IF(H74=0,H68,H68+H74) -> 16199.14 | I106: =IF(I74=0,I68,I68+I74) -> 16665.58 | ... L106: =IF(L74=0,L68,L68+L74) -> 19606.03
A107: Resultado líquido do período | B107: =B105-B106 -> 0 | C107: =C105-C106 -> 0 | D107: =D105-D106 -> 31854.57 | E107: =E105-E106 -> 24747.67 | F107: =F105-F106 -> 49427.95 | G107: =G105-G106 -> 44335.58 | H107: =H105-H106 -> 55797.01 | I107: =I105-I106 -> 57403.62 | ... L107: =L105-L106 -> 67531.84
A108: Resultado das atividades descontinuadas (líquido de impostos) incluído no resultado líquido do período
A110: Resultados Líquidos DR Form | B110: =ROUND(B79+B80+B81+B82+B83-B84-B85-B86-B87-B88-B89-B90-B91+B92+B94+B95-B97-B98-B100-B101+B103-B104-B106,2) -> 0 | C110: =ROUND(C79+C80+C81+C82+C83-C84-C85-C86-C87-C88-C89-C90-C91+C92+C94+C95-C97-C98-C100-C101+C103-C104-C106,2) -> 0 | D110: =ROUND(D79+D80+D81+D82+D83-D84-D85-D86-D87-D88-D89-D90-D91+D92+D94+D95-D97-D98-D100-D101+D103-D104-D106,2) -> 31854.57 | E110: =ROUND(E79+E80+E81+E82+E83-E84-E85-E86-E87-E88-E89-E90-E91+E92+E94+E95-E97-E98-E100-E101+E103-E104-E106,2) -> 24747.67 | F110: =ROUND(F79+F80+F81+F82+F83-F84-F85-F86-F87-F88-F89-F90-F91+F92+F94+F95-F97-F98-F100-F101+F103-F104-F106,2) -> 49427.95 | G110: =ROUND(G79+G80+G81+G82+G83-G84-G85-G86-G87-G88-G89-G90-G91+G92+G94+G95-G97-G98-G100-G101+G103-G104-G106,2) -> 44335.58 | H110: =ROUND(H79+H80+H81+H82+H83-H84-H85-H86-H87-H88-H89-H90-H91+H92+H94+H95-H97-H98-H100-H101+H103-H104-H106,2) -> 55797.01 | I110: =ROUND(I79+I80+I81+I82+I83-I84-I85-I86-I87-I88-I89-I90-I91+I92+I94+I95-I97-I98-I100-I101+I103-I104-I106,2) -> 57403.62 | ... L110: =ROUND(L79+L80+L81+L82+L83-L84-L85-L86-L87-L88-L89-L90-L91+L92+L94+L95-L97-L98-L100-L101+L103-L104-L106,2) -> 67531.84
...

Sheet Balanço_Form
A1: Balanço Formulário Original
A2: ATIVO | B2: =C2-1 -> 2017 | C2: =D2-1 -> 2018 | D2: =E2-1 -> 2019 | E2: =Pressupostos!C11 -> 2020 | F2: =E2+1 -> 2021 | G2: =F2+1 -> 2022 | H2: =G2+1 -> 2023 | I2: =H2+1 -> 2024 | J2: =I2+1 -> 2025 | K2: =J2+1 -> 2026 | L2: =K2+1 -> 2027
A3: Ativo não corrente
A4: Ativos fixos tangíveis | B4: =Balanço!C7 -> 0 | C4: =Balanço!D7 -> 0 | D4: =Balanço!E7 -> 84625.24 | E4: ='Balanço Futuro'!C8 -> 76162.716 | F4: ='Balanço Futuro'!D8 -> 97700.192 | G4: ='Balanço Futuro'!E8 -> 79237.668 | H4: ='Balanço Futuro'!F8 -> 60775.144 | I4: ='Balanço Futuro'!G8 -> 42312.62 | J4: ='Balanço Futuro'!H8 -> 33850.096 | K4: ='Balanço Futuro'!I8 -> 25387.572 | L4: ='Balanço Futuro'!J8 -> 16925.048
A5: Propriedades de investimento | B5: =Balanço!C8 -> 0 | C5: =Balanço!D8 -> 0 | D5: =Balanço!E8 -> 102152.86 | E5: ='Balanço Futuro'!C9 -> 102152.86 | F5: ='Balanço Futuro'!D9 -> 102152.86 | G5: ='Balanço Futuro'!E9 -> 102152.86 | H5: ='Balanço Futuro'!F9 -> 102152.86 | I5: ='Balanço Futuro'!G9 -> 102152.86 | J5: ='Balanço Futuro'!H9 -> 102152.86 | K5: ='Balanço Futuro'!I9 -> 102152.86 | L5: ='Balanço Futuro'!J9 -> 102152.86
A6: Goodwill | B6: =Balanço!C9 -> 0 | C6: =Balanço!D9 -> 0 | D6: =Balanço!E9 -> 0 | E6: ='Balanço Futuro'!C10 -> 0 | F6: ='Balanço Futuro'!D10 -> 0 | G6: ='Balanço Futuro'!E10 -> 0 | H6: ='Balanço Futuro'!F10 -> 0 | I6: ='Balanço Futuro'!G10 -> 0 | J6: ='Balanço Futuro'!H10 -> 0 | K6: ='Balanço Futuro'!I10 -> 0 | L6: ='Balanço Futuro'!J10 -> 0
A7: Ativos intangíveis | B7: =Balanço!C10 -> 0 | C7: =Balanço!D10 -> 0 | D7: =Balanço!E10 -> 0 | E7: ='Balanço Futuro'!C11 -> 0 | F7: ='Balanço Futuro'!D11 -> 0 | G7: ='Balanço Futuro'!E11 -> 0 | H7: ='Balanço Futuro'!F11 -> 0 | I7: ='Balanço Futuro'!G11 -> 0 | J7: ='Balanço Futuro'!H11 -> 0 | K7: ='Balanço Futuro'!I11 -> 0 | L7: ='Balanço Futuro'!J11 -> 0
A8: Ativos biológicos | B8: =Balanço!C11 -> 0 | C8: =Balanço!D11 -> 0 | D8: =Balanço!E11 -> 0 | E8: ='Balanço Futuro'!C12 -> 0 | F8: ='Balanço Futuro'!D12 -> 0 | G8: ='Balanço Futuro'!E12 -> 0 | H8: ='Balanço Futuro'!F12 -> 0 | I8: ='Balanço Futuro'!G12 -> 0 | J8: ='Balanço Futuro'!H12 -> 0 | K8: ='Balanço Futuro'!I12 -> 0 | L8: ='Balanço Futuro'!J12 -> 0
A9: Participações financeiras - método da equivalência patrimonial | B9: =Balanço!C12 -> 0 | C9: =Balanço!D12 -> 0 | D9: =Balanço!E12 -> 0 | E9: ='Balanço Futuro'!C13 -> 0 | F9: ='Balanço Futuro'!D13 -> 0 | G9: ='Balanço Futuro'!E13 -> 0 | H9: ='Balanço Futuro'!F13 -> 0 | I9: ='Balanço Futuro'!G13 -> 0 | J9: ='Balanço Futuro'!H13 -> 0 | K9: ='Balanço Futuro'!I13 -> 0 | L9: ='Balanço Futuro'!J13 -> 0
A10: Participações financeiras - outros métodos | B10: =Balanço!C13 -> 0 | C10: =Balanço!D13 -> 0 | D10: =Balanço!E13 -> 0 | E10: ='Balanço Futuro'!C14 -> 0 | F10: ='Balanço Futuro'!D14 -> 0 | G10: ='Balanço Futuro'!E14 -> 0 | H10: ='Balanço Futuro'!F14 -> 0 | I10: ='Balanço Futuro'!G14 -> 0 | J10: ='Balanço Futuro'!H14 -> 0 | K10: ='Balanço Futuro'!I14 -> 0 | L10: ='Balanço Futuro'!J14 -> 0
A11: Acionistas/sócios | B11: =Balanço!C14 -> 0 | C11: =Balanço!D14 -> 0 | D11: =Balanço!E14 -> 0 | E11: ='Balanço Futuro'!C15 -> 0 | F11: ='Balanço Futuro'!D15 -> 0 | G11: ='Balanço Futuro'!E15 -> 0 | H11: ='Balanço Futuro'!F15 -> 0 | I11: ='Balanço Futuro'!G15 -> 0 | J11: ='Balanço Futuro'!H15 -> 0 | K11: ='Balanço Futuro'!I15 -> 0 | L11: ='Balanço Futuro'!J15 -> 0
A12: Outros ativos financeiros | B12: =Balanço!C15 -> 0 | C12: =Balanço!D15 -> 0 | D12: =Balanço!E15 -> 347.82 | E12: ='Balanço Futuro'!C16 -> 347.82 | F12: ='Balanço Futuro'!D16 -> 347.82 | G12: ='Balanço Futuro'!E16 -> 347.82 | H12: ='Balanço Futuro'!F16 -> 347.82 | I12: ='Balanço Futuro'!G16 -> 347.82 | J12: ='Balanço Futuro'!H16 -> 347.82 | K12: ='Balanço Futuro'!I16 -> 347.82 | L12: ='Balanço Futuro'!J16 -> 347.82
A13: Ativos por impostos diferidos | B13: =Balanço!C16 -> 0 | C13: =Balanço!D16 -> 0 | D13: =Balanço!E16 -> 0 | E13: ='Balanço Futuro'!C17 -> 0 | F13: ='Balanço Futuro'!D17 -> 0 | G13: ='Balanço Futuro'!E17 -> 0 | H13: ='Balanço Futuro'!F17 -> 0 | I13: ='Balanço Futuro'!G17 -> 0 | J13: ='Balanço Futuro'!H17 -> 0 | K13: ='Balanço Futuro'!I17 -> 0 | L13: ='Balanço Futuro'!J17 -> 0
A14: Investimentos financeiros (*) | B14: =Balanço!C17 -> 0 | C14: =Balanço!D17 -> 0 | D14: =Balanço!E17 -> 0 | E14: ='Balanço Futuro'!C18 -> 0 | F14: ='Balanço Futuro'!D18 -> 0 | G14: ='Balanço Futuro'!E18 -> 0 | H14: ='Balanço Futuro'!F18 -> 0 | I14: ='Balanço Futuro'!G18 -> 0 | J14: ='Balanço Futuro'!H18 -> 0 | K14: ='Balanço Futuro'!I18 -> 0 | L14: ='Balanço Futuro'!J18 -> 0
A15: Ativo corrente
A16: Inventários | B16: =Balanço!C20 -> 0 | C16: =Balanço!D20 -> 0 | D16: =Balanço!E20 -> 343630.82 | E16: ='Balanço Futuro'!C21 -> 241390.37 | F16: ='Balanço Futuro'!D21 -> 255994.48 | G16: ='Balanço Futuro'!E21 -> 269752.97 | H16: ='Balanço Futuro'!F21 -> 286073.02 | I16: ='Balanço Futuro'!G21 -> 291823.09 | J16: ='Balanço Futuro'!H21 -> 297688.73 | K16: ='Balanço Futuro'!I21 -> 303672.28 | L16: ='Balanço Futuro'!J21 -> 309776.09
A17: Ativos biológicos | B17: =Balanço!C21 -> 0 | C17: =Balanço!D21 -> 0 | D17: =Balanço!E21 -> 0 | E17: ='Balanço Futuro'!C22 -> 0 | F17: ='Balanço Futuro'!D22 -> 0 | G17: ='Balanço Futuro'!E22 -> 0 | H17: ='Balanço Futuro'!F22 -> 0 | I17: ='Balanço Futuro'!G22 -> 0 | J17: ='Balanço Futuro'!H22 -> 0 | K17: ='Balanço Futuro'!I22 -> 0 | L17: ='Balanço Futuro'!J22 -> 0
A18: Clientes | B18: =Balanço!C22 -> 0 | C18: =Balanço!D22 -> 0 | D18: =Balanço!E22 -> 758084.77 | E18: ='Balanço Futuro'!C23 -> 1134688.5 | F18: ='Balanço Futuro'!D23 -> 1203337.1 | G18: ='Balanço Futuro'!E23 -> 1276139 | H18: ='Balanço Futuro'!F23 -> 1353345.4 | I18: ='Balanço Futuro'!G23 -> 1380547.7 | J18: ='Balanço Futuro'!H23 -> 1408296.7 | K18: ='Balanço Futuro'!I23 -> 1436603.5 | L18: ='Balanço Futuro'!J23 -> 1465479.2
A19: Adiantamentos a fornecedores | B19: =Balanço!C23 -> 0 | C19: =Balanço!D23 -> 0 | D19: =Balanço!E23 -> 0 | E19: ='Balanço Futuro'!C24 -> 0 | F19: ='Balanço Futuro'!D24 -> 0 | G19: ='Balanço Futuro'!E24 -> 0 | H19: ='Balanço Futuro'!F24 -> 0 | I19: ='Balanço Futuro'!G24 -> 0 | J19: ='Balanço Futuro'!H24 -> 0 | K19: ='Balanço Futuro'!I24 -> 0 | L19: ='Balanço Futuro'!J24 -> 0
A20: Estado e outros entes públicos | B20: =Balanço!C24 -> 0 | C20: =Balanço!D24 -> 0 | D20: =Balanço!E24 -> 21003.43 | E20: ='Balanço Futuro'!C25 -> 0 | F20: ='Balanço Futuro'!D25 -> 0 | G20: ='Balanço Futuro'!E25 -> 0 | H20: ='Balanço Futuro'!F25 -> 0 | I20: ='Balanço Futuro'!G25 -> 0 | J20: ='Balanço Futuro'!H25 -> 0 | K20: ='Balanço Futuro'!I25 -> 0 | L20: ='Balanço Futuro'!J25 -> 0
A21: Acionistas/sócios | B21: =Balanço!C25 -> 0 | C21: =Balanço!D25 -> 0 | D21: =Balanço!E25 -> 0 | E21: ='Balanço Futuro'!C26 -> 0 | F21: ='Balanço Futuro'!D26 -> 0 | G21: ='Balanço Futuro'!E26 -> 0 | H21: ='Balanço Futuro'!F26 -> 0 | I21: ='Balanço Futuro'!G26 -> 0 | J21: ='Balanço Futuro'!H26 -> 0 | K21: ='Balanço Futuro'!I26 -> 0 | L21: ='Balanço Futuro'!J26 -> 0
A22: Outras contas a receber | B22: =Balanço!C26 -> 0 | C22: =Balanço!D26 -> 0 | D22: =Balanço!E26 -> 80826.21 | E22: ='Balanço Futuro'!C27 -> 80826.21 | F22: ='Balanço Futuro'!D27 -> 80826.21 | G22: ='Balanço Futuro'!E27 -> 80826.21 | H22: ='Balanço Futuro'!F27 -> 80826.21 | I22: ='Balanço Futuro'!G27 -> 80826.21 | J22: ='Balanço Futuro'!H27 -> 80826.21 | K22: ='Balanço Futuro'!I27 -> 80826.21 | L22: ='Balanço Futuro'!J27 -> 80826.21
A23: Diferimentos | B23: =Balanço!C27 -> 0 | C23: =Balanço!D27 -> 0 | D23: =Balanço!E27 -> 955.33 | E23: ='Balanço Futuro'!C28 -> 955.33 | F23: ='Balanço Futuro'!D28 -> 955.33 | G23: ='Balanço Futuro'!E28 -> 955.33 | H23: ='Balanço Futuro'!F28 -> 955.33 | I23: ='Balanço Futuro'!G28 -> 955.33 | J23: ='Balanço Futuro'!H28 -> 955.33 | K23: ='Balanço Futuro'!I28 -> 955.33 | L23: ='Balanço Futuro'!J28 -> 955.33
A24: Ativos financeiros detidos para negociação | B24: =Balanço!C28 -> 0 | C24: =Balanço!D28 -> 0 | D24: =Balanço!E28 -> 0 | E24: ='Balanço Futuro'!C29 -> 0 | F24: ='Balanço Futuro'!D29 -> 0 | G24: ='Balanço Futuro'!E29 -> 0 | H24: ='Balanço Futuro'!F29 -> 0 | I24: ='Balanço Futuro'!G29 -> 0 | J24: ='Balanço Futuro'!H29 -> 0 | K24: ='Balanço Futuro'!I29 -> 0 | L24: ='Balanço Futuro'!J29 -> 0
A25: Outros ativos financeiros | B25: =Balanço!C29 -> 0 | C25: =Balanço!D29 -> 0 | D25: =Balanço!E29 -> 0 | E25: ='Balanço Futuro'!C30 -> 0 | F25: ='Balanço Futuro'!D30 -> 0 | G25: ='Balanço Futuro'!E30 -> 0 | H25: ='Balanço Futuro'!F30 -> 0 | I25: ='Balanço Futuro'!G30 -> 0 | J25: ='Balanço Futuro'!H30 -> 0 | K25: ='Balanço Futuro'!I30 -> 0 | L25: ='Balanço Futuro'!J30 -> 0
A26: Ativos não correntes detidos para venda | B26: =Balanço!C30 -> 0 | C26: =Balanço!D30 -> 0 | D26: =Balanço!E30 -> 0 | E26: ='Balanço Futuro'!C31 -> 0 | F26: ='Balanço Futuro'!D31 -> 0 | G26: ='Balanço Futuro'!E31 -> 0 | H26: ='Balanço Futuro'!F31 -> 0 | I26: ='Balanço Futuro'!G31 -> 0 | J26: ='Balanço Futuro'!H31 -> 0 | K26: ='Balanço Futuro'!I31 -> 0 | L26: ='Balanço Futuro'!J31 -> 0
A27: Outros ativos correntes | B27: =Balanço!C31 -> 0 | C27: =Balanço!D31 -> 0 | D27: =Balanço!E31 -> 0 | E27: ='Balanço Futuro'!C32 -> 0 | F27: ='Balanço Futuro'!D32 -> 0 | G27: ='Balanço Futuro'!E32 -> 0 | H27: ='Balanço Futuro'!F32 -> 0 | I27: ='Balanço Futuro'!G32 -> 0 | J27: ='Balanço Futuro'!H32 -> 0 | K27: ='Balanço Futuro'!I32 -> 0 | L27: ='Balanço Futuro'!J32 -> 0
A28: Caixa e depósitos bancários | B28: =Balanço!C32 -> 0 | C28: =Balanço!D32 -> 0 | D28: =Balanço!E32 -> 215805.41 | E28: ='Balanço Futuro'!C33 -> 23550.443 | F28: ='Balanço Futuro'!D33 -> 85411.438 | G28: ='Balanço Futuro'!E33 -> 134863.93 | H28: ='Balanço Futuro'!F33 -> 171226.18 | I28: ='Balanço Futuro'!G33 -> 233278.84 | J28: ='Balanço Futuro'!H33 -> 293205.43 | K28: ='Balanço Futuro'!I33 -> 352941.69 | L28: ='Balanço Futuro'!J33 -> 414041.15
A29: TOTAL DO ATIVO
A30: CAPITAL PRÓPRIO E PASSIVO
A31: Capital realizado | B31: =Balanço!C37 -> 0 | C31: =Balanço!D37 -> 0 | D31: =Balanço!E37 -> 300000 | E31: ='Balanço Futuro'!C38 -> 300000 | F31: ='Balanço Futuro'!D38 -> 300000 | G31: ='Balanço Futuro'!E38 -> 300000 | H31: ='Balanço Futuro'!F38 -> 300000 | I31: ='Balanço Futuro'!G38 -> 300000 | J31: ='Balanço Futuro'!H38 -> 300000 | K31: ='Balanço Futuro'!I38 -> 300000 | L31: ='Balanço Futuro'!J38 -> 300000
A32: Ações (quotas) próprias | B32: =Balanço!C38 -> 0 | C32: =Balanço!D38 -> 0 | D32: =Balanço!E38 -> 0 | E32: ='Balanço Futuro'!C39 -> 0 | F32: ='Balanço Futuro'!D39 -> 0 | G32: ='Balanço Futuro'!E39 -> 0 | H32: ='Balanço Futuro'!F39 -> 0 | I32: ='Balanço Futuro'!G39 -> 0 | J32: ='Balanço Futuro'!H39 -> 0 | K32: ='Balanço Futuro'!I39 -> 0 | L32: ='Balanço Futuro'!J39 -> 0
A33: Outros instrumentos de capital próprio | B33: =Balanço!C39 -> 0 | C33: =Balanço!D39 -> 0 | D33: =Balanço!E39 -> 0 | E33: ='Balanço Futuro'!C40 -> 5158.8125 | F33: ='Balanço Futuro'!D40 -> 28514.605 | G33: ='Balanço Futuro'!E40 -> 37087.25 | H33: ='Balanço Futuro'!F40 -> 37087.25 | I33: ='Balanço Futuro'!G40 -> 37087.25 | J33: ='Balanço Futuro'!H40 -> 37087.25 | K33: ='Balanço Futuro'!I40 -> 37087.25 | L33: ='Balanço Futuro'!J40 -> 37087.25
A34: Prémios de emissão | B34: =Balanço!C40 -> 0 | C34: =Balanço!D40 -> 0 | D34: =Balanço!E40 -> 0 | E34: ='Balanço Futuro'!C41 -> 0 | F34: ='Balanço Futuro'!D41 -> 0 | G34: ='Balanço Futuro'!E41 -> 0 | H34: ='Balanço Futuro'!F41 -> 0 | I34: ='Balanço Futuro'!G41 -> 0 | J34: ='Balanço Futuro'!H41 -> 0 | K34: ='Balanço Futuro'!I41 -> 0 | L34: ='Balanço Futuro'!J41 -> 0
A35: Reservas legais | B35: =Balanço!C41 -> 0 | C35: =Balanço!D41 -> 0 | D35: =Balanço!E41 -> 14785.57 | E35: ='Balanço Futuro'!C42 -> 29109.658 | F35: ='Balanço Futuro'!D42 -> 43954.925 | G35: ='Balanço Futuro'!E42 -> 60000 | H35: ='Balanço Futuro'!F42 -> 60000 | I35: ='Balanço Futuro'!G42 -> 60000 | J35: ='Balanço Futuro'!H42 -> 60000 | K35: ='Balanço Futuro'!I42 -> 60000 | L35: ='Balanço Futuro'!J42 -> 60000
A36: Outras reservas | B36: =Balanço!C42 -> 0 | C36: =Balanço!D42 -> 0 | D36: =Balanço!E42 -> 0 | E36: ='Balanço Futuro'!C43 -> 0 | F36: ='Balanço Futuro'!D43 -> 0 | G36: ='Balanço Futuro'!E43 -> 0 | H36: ='Balanço Futuro'!F43 -> 0 | I36: ='Balanço Futuro'!G43 -> 0 | J36: ='Balanço Futuro'!H43 -> 0 | K36: ='Balanço Futuro'!I43 -> 0 | L36: ='Balanço Futuro'!J43 -> 0
A37: Resultados transitados | B37: =Balanço!C43 -> 0 | C37: =Balanço!D43 -> 0 | D37: =Balanço!E43 -> 254627.19 | E37: ='Balanço Futuro'!C44 -> 272157.67 | F37: ='Balanço Futuro'!D44 -> 282060.07 | G37: ='Balanço Futuro'!E44 -> 315442.94 | H37: ='Balanço Futuro'!F44 -> 359778.52 | I37: ='Balanço Futuro'!G44 -> 415575.54 | J37: ='Balanço Futuro'!H44 -> 472979.16 | K37: ='Balanço Futuro'!I44 -> 537230.91 | L37: ='Balanço Futuro'!J44 -> 603106.16
A38: Ajustamentos em ativos financeiros | B38: =Balanço!C44 -> 0 | C38: =Balanço!D44 -> 0 | D38: =Balanço!E44 -> 0 | E38: ='Balanço Futuro'!C45 -> 0 | F38: ='Balanço Futuro'!D45 -> 0 | G38: ='Balanço Futuro'!E45 -> 0 | H38: ='Balanço Futuro'!F45 -> 0 | I38: ='Balanço Futuro'!G45 -> 0 | J38: ='Balanço Futuro'!H45 -> 0 | K38: ='Balanço Futuro'!I45 -> 0 | L38: ='Balanço Futuro'!J45 -> 0
A39: Excedentes de revalorização | B39: =Balanço!C45 -> 0 | C39: =Balanço!D45 -> 0 | D39: =Balanço!E45 -> 0 | E39: ='Balanço Futuro'!C46 -> 0 | F39: ='Balanço Futuro'!D46 -> 0 | G39: ='Balanço Futuro'!E46 -> 0 | H39: ='Balanço Futuro'!F46 -> 0 | I39: ='Balanço Futuro'!G46 -> 0 | J39: ='Balanço Futuro'!H46 -> 0 | K39: ='Balanço Futuro'!I46 -> 0 | L39: ='Balanço Futuro'!J46 -> 0
A40: Outras variações no capital próprio | B40: =Balanço!C46 -> 0 | C40: =Balanço!D46 -> 0 | D40: =Balanço!E46 -> 0 | E40: ='Balanço Futuro'!C47 -> 9285.8625 | F40: ='Balanço Futuro'!D47 -> 51326.289 | G40: ='Balanço Futuro'!E47 -> 66757.05 | H40: ='Balanço Futuro'!F47 -> 66757.05 | I40: ='Balanço Futuro'!G47 -> 66757.05 | J40: ='Balanço Futuro'!H47 -> 66757.05 | K40: ='Balanço Futuro'!I47 -> 66757.05 | L40: ='Balanço Futuro'!J47 -> 66757.05
A41: Resultado líquido do período | B41: =DR_Form!B110 -> 0 | C41: =DR_Form!C110 -> 0 | D41: =DR_Form!D110 -> 31854.57 | E41: =DR_Form!E110 -> 24747.67 | F41: =DR_Form!F110 -> 49427.95 | G41: =DR_Form!G110 -> 44335.58 | H41: =DR_Form!H110 -> 55797.01 | I41: =DR_Form!I110 -> 57403.62 | ... L41: =DR_Form!L110 -> 67531.84
A42: Interesses minoritários | B42: 0 | C42: 0 | D42: 0 | E42: 0 | F42: 0 | G42: 0 | H42: 0 | I42: 0 | J42: 0 | K42: 0 | L42: 0
A43: Dividendos antecipados | B43: 0 | C43: 0 | D43: 0 | E43: 0 | F43: 0 | G43: 0 | H43: 0 | I43: 0 | J43: 0 | K43: 0 | L43: 0
A44: TOTAL DO CAPITAL PRÓPRIO
A45: PASSIVO
A46: Passivo não corrente
A47: Provisões | B47: =Balanço!C53 -> 0 | C47: =Balanço!D53 -> 0 | D47: =Balanço!E53 -> 0 | E47: ='Balanço Futuro'!C54 -> 0 | F47: ='Balanço Futuro'!D54 -> 0 | G47: ='Balanço Futuro'!E54 -> 0 | H47: ='Balanço Futuro'!F54 -> 0 | I47: ='Balanço Futuro'!G54 -> 0 | J47: ='Balanço Futuro'!H54 -> 0 | K47: ='Balanço Futuro'!I54 -> 0 | L47: ='Balanço Futuro'!J54 -> 0
A48: Financiamentos obtidos | B48: =Balanço!C54 -> 0 | C48: =Balanço!D54 -> 0 | D48: =Balanço!E54 -> 0 | E48: ='Balanço Futuro'!C55 -> 0 | F48: ='Balanço Futuro'!D55 -> 0 | G48: ='Balanço Futuro'!E55 -> 0 | H48: ='Balanço Futuro'!F55 -> 0 | I48: ='Balanço Futuro'!G55 -> 0 | J48: ='Balanço Futuro'!H55 -> 0 | K48: ='Balanço Futuro'!I55 -> 0 | L48: ='Balanço Futuro'!J55 -> 0
A49: Responsabilidades por benefícios pós-emprego | B49: =Balanço!C55 -> 0 | C49: =Balanço!D55 -> 0 | D49: =Balanço!E55 -> 0 | E49: ='Balanço Futuro'!C56 -> 0 | F49: ='Balanço Futuro'!D56 -> 0 | G49: ='Balanço Futuro'!E56 -> 0 | H49: ='Balanço Futuro'!F56 -> 0 | I49: ='Balanço Futuro'!G56 -> 0 | J49: ='Balanço Futuro'!H56 -> 0 | K49: ='Balanço Futuro'!I56 -> 0 | L49: ='Balanço Futuro'!J56 -> 0
A50: Passivos por impostos diferidos | B50: =Balanço!C56 -> 0 | C50: =Balanço!D56 -> 0 | D50: =Balanço!E56 -> 0 | E50: ='Balanço Futuro'!C57 -> 0 | F50: ='Balanço Futuro'!D57 -> 0 | G50: ='Balanço Futuro'!E57 -> 0 | H50: ='Balanço Futuro'!F57 -> 0 | I50: ='Balanço Futuro'!G57 -> 0 | J50: ='Balanço Futuro'!H57 -> 0 | K50: ='Balanço Futuro'!I57 -> 0 | L50: ='Balanço Futuro'!J57 -> 0
A51: Outras contas a pagar | B51: =Balanço!C57 -> 0 | C51: =Balanço!D57 -> 0 | D51: =Balanço!E57 -> 0 | E51: ='Balanço Futuro'!C58 -> 0 | F51: ='Balanço Futuro'!D58 -> 0 | G51: ='Balanço Futuro'!E58 -> 0 | H51: ='Balanço Futuro'!F58 -> 0 | I51: ='Balanço Futuro'!G58 -> 0 | J51: ='Balanço Futuro'!H58 -> 0 | K51: ='Balanço Futuro'!I58 -> 0 | L51: ='Balanço Futuro'!J58 -> 0
A52: Passivo corrente
A53: Fornecedores | B53: =Balanço!C60 -> 0 | C53: =Balanço!D60 -> 0 | D53: =Balanço!E60 -> 760538.01 | E53: ='Balanço Futuro'!C61 -> 756458.99 | F53: ='Balanço Futuro'!D61 -> 802224.75 | G53: ='Balanço Futuro'!E61 -> 850759.35 | H53: ='Balanço Futuro'!F61 -> 902230.29 | I53: ='Balanço Futuro'!G61 -> 920365.12 | J53: ='Balanço Futuro'!H61 -> 938864.46 | K53: ='Balanço Futuro'!I61 -> 957735.64 | L53: ='Balanço Futuro'!J61 -> 976986.12
A54: Adiantamentos de clientes | B54: =Balanço!C61 -> 0 | C54: =Balanço!D61 -> 0 | D54: =Balanço!E61 -> 0 | E54: ='Balanço Futuro'!C62 -> 0 | F54: ='Balanço Futuro'!D62 -> 0 | G54: ='Balanço Futuro'!E62 -> 0 | H54: ='Balanço Futuro'!F62 -> 0 | I54: ='Balanço Futuro'!G62 -> 0 | J54: ='Balanço Futuro'!H62 -> 0 | K54: ='Balanço Futuro'!I62 -> 0 | L54: ='Balanço Futuro'!J62 -> 0
A55: Estado e outros entes públicos | B55: =Balanço!C62 -> 0 | C55: =Balanço!D62 -> 0 | D55: =Balanço!E62 -> 4173.5 | E55: ='Balanço Futuro'!C63 -> 21702.519 | F55: ='Balanço Futuro'!D63 -> 27763.827 | G55: ='Balanço Futuro'!E63 -> 28440.589 | H55: ='Balanço Futuro'!F63 -> 32598.824 | I55: ='Balanço Futuro'!G63 -> 33602.818 | J55: ='Balanço Futuro'!H63 -> 35930.447 | K55: ='Balanço Futuro'!I63 -> 36748.058 | L55: ='Balanço Futuro'!J63 -> 37582.212
A56: Acionistas/sócios | B56: =Balanço!C63 -> 0 | C56: =Balanço!D63 -> 0 | D56: =Balanço!E63 -> 0 | E56: ='Balanço Futuro'!C64 -> 0 | F56: ='Balanço Futuro'!D64 -> 0 | G56: ='Balanço Futuro'!E64 -> 0 | H56: ='Balanço Futuro'!F64 -> 0 | I56: ='Balanço Futuro'!G64 -> 0 | J56: ='Balanço Futuro'!H64 -> 0 | K56: ='Balanço Futuro'!I64 -> 0 | L56: ='Balanço Futuro'!J64 -> 0
A57: Financiamentos obtidos | B57: =Balanço!C64 -> 0 | C57: =Balanço!D64 -> 0 | D57: =Balanço!E64 -> 0 | E57: ='Balanço Futuro'!C65 -> 0 | F57: ='Balanço Futuro'!D65 -> 0 | G57: ='Balanço Futuro'!E65 -> 0 | H57: ='Balanço Futuro'!F65 -> 0 | I57: ='Balanço Futuro'!G65 -> 0 | J57: ='Balanço Futuro'!H65 -> 0 | K57: ='Balanço Futuro'!I65 -> 0 | L57: ='Balanço Futuro'!J65 -> 0
A58: Outras contas a pagar | B58: =Balanço!C65 -> 0 | C58: =Balanço!D65 -> 0 | D58: =Balanço!E65 -> 241453.05 | E58: ='Balanço Futuro'!C66 -> 241453.05 | F58: ='Balanço Futuro'!D66 -> 241453.05 | G58: ='Balanço Futuro'!E66 -> 241453.05 | H58: ='Balanço Futuro'!F66 -> 241453.05 | I58: ='Balanço Futuro'!G66 -> 241453.05 | J58: ='Balanço Futuro'!H66 -> 241453.05 | K58: ='Balanço Futuro'!I66 -> 241453.05 | L58: ='Balanço Futuro'!J66 -> 241453.05
A59: Diferimentos | B59: =Balanço!C66 -> 0 | C59: =Balanço!D66 -> 0 | D59: =Balanço!E66 -> 0 | E59: ='Balanço Futuro'!C67 -> 0 | F59: ='Balanço Futuro'!D67 -> 0 | G59: ='Balanço Futuro'!E67 -> 0 | H59: ='Balanço Futuro'!F67 -> 0 | I59: ='Balanço Futuro'!G67 -> 0 | J59: ='Balanço Futuro'!H67 -> 0 | K59: ='Balanço Futuro'!I67 -> 0 | L59: ='Balanço Futuro'!J67 -> 0
A60: Passivos financeiros detidos para negociação | B60: =Balanço!C67 -> 0 | C60: =Balanço!D67 -> 0 | D60: =Balanço!E67 -> 0 | E60: ='Balanço Futuro'!C68 -> 0 | F60: ='Balanço Futuro'!D68 -> 0 | G60: ='Balanço Futuro'!E68 -> 0 | H60: ='Balanço Futuro'!F68 -> 0 | I60: ='Balanço Futuro'!G68 -> 0 | J60: ='Balanço Futuro'!H68 -> 0 | K60: ='Balanço Futuro'!I68 -> 0 | L60: ='Balanço Futuro'!J68 -> 0
A61: Outros passivos financeiros | B61: =Balanço!C68 -> 0 | C61: =Balanço!D68 -> 0 | D61: =Balanço!E68 -> 0 | E61: ='Balanço Futuro'!C69 -> 0 | F61: ='Balanço Futuro'!D69 -> 0 | G61: ='Balanço Futuro'!E69 -> 0 | H61: ='Balanço Futuro'!F69 -> 0 | I61: ='Balanço Futuro'!G69 -> 0 | J61: ='Balanço Futuro'!H69 -> 0 | K61: ='Balanço Futuro'!I69 -> 0 | L61: ='Balanço Futuro'!J69 -> 0
A62: Passivos não correntes detidos para venda | B62: =Balanço!C69 -> 0 | C62: =Balanço!D69 -> 0 | D62: =Balanço!E69 -> 0 | E62: ='Balanço Futuro'!C70 -> 0 | F62: ='Balanço Futuro'!D70 -> 0 | G62: ='Balanço Futuro'!E70 -> 0 | H62: ='Balanço Futuro'!F70 -> 0 | I62: ='Balanço Futuro'!G70 -> 0 | J62: ='Balanço Futuro'!H70 -> 0 | K62: ='Balanço Futuro'!I70 -> 0 | L62: ='Balanço Futuro'!J70 -> 0
A63: Outros passivos correntes | B63: =Balanço!C70 -> 0 | C63: =Balanço!D70 -> 0 | D63: =Balanço!E70 -> 0 | E63: ='Balanço Futuro'!C71 -> 0 | F63: ='Balanço Futuro'!D71 -> 0 | G63: ='Balanço Futuro'!E71 -> 0 | H63: ='Balanço Futuro'!F71 -> 0 | I63: ='Balanço Futuro'!G71 -> 0 | J63: ='Balanço Futuro'!H71 -> 0 | K63: ='Balanço Futuro'!I71 -> 0 | L63: ='Balanço Futuro'!J71 -> 0
A64: TOTAL DO PASSIVO
A65: TOTAL DO CAPITAL PRÓPRIO + PASSIVO
B67: =IF(B68=0, "OK", "VERIFICAR") -> OK | C67: =IF(C68=0, "OK", "VERIFICAR") -> OK | D67: =IF(D68=0, "OK", "VERIFICAR") -> OK | E67: =IF(E68=0, "OK", "VERIFICAR") -> VERIFICAR | F67: =IF(F68=0, "OK", "VERIFICAR") -> VERIFICAR | G67: =IF(G68=0, "OK", "VERIFICAR") -> VERIFICAR | H67: =IF(H68=0, "OK", "VERIFICAR") -> VERIFICAR | I67: =IF(I68=0, "OK", "VERIFICAR") -> VERIFICAR | ... L67: =IF(L68=0, "OK", "VERIFICAR") -> VERIFICAR
B68: =SUM(B4:B28)-SUM(B31:B63) -> 0 | C68: =SUM(C4:C28)-SUM(C31:C63) -> 0 | D68: =SUM(D4:D28)-SUM(D31:D63) -> 0 | E68: =SUM(E4:E28)-SUM(E31:E63) -> -0.004426254 | F68: =SUM(F4:F28)-SUM(F31:F63) -> -0.0047623939 | G68: =SUM(G4:G28)-SUM(G31:G63) -> 0.00020238524 | H68: =SUM(H4:H28)-SUM(H31:H63) -> 0.0043569577 | I68: =SUM(I4:I28)-SUM(I31:I63) -> 0.0049857437 | ... L68: =SUM(L4:L28)-SUM(L31:L63) -> 0.0044637853
A72: Balanço Formulário com Arredondamentos
A73: ATIVO | B73: =B2 -> 2017 | C73: =C2 -> 2018 | D73: =D2 -> 2019 | E73: =E2 -> 2020 | F73: =F2 -> 2021 | G73: =G2 -> 2022 | H73: =H2 -> 2023 | I73: =I2 -> 2024 | ... L73: =L2 -> 2027
A74: Ativo não corrente
A75: Ativos fixos tangíveis | B75: =ROUND(B4,2) -> 0 | C75: =ROUND(C4,2) -> 0 | D75: =ROUND(D4,2) -> 84625.24 | E75: =ROUND(E4,2) -> 76162.72 | F75: =ROUND(F4,2) -> 97700.19 | G75: =ROUND(G4,2) -> 79237.67 | H75: =ROUND(H4,2) -> 60775.14 | I75: =ROUND(I4,2) -> 42312.62 | ... L75: =ROUND(L4,2) -> 16925.05
A76: Propriedades de investimento | B76: =ROUND(B5,2) -> 0 | C76: =ROUND(C5,2) -> 0 | D76: =ROUND(D5,2) -> 102152.86 | E76: =ROUND(E5,2) -> 102152.86 | F76: =ROUND(F5,2) -> 102152.86 | G76: =ROUND(G5,2) -> 102152.86 | H76: =ROUND(H5,2) -> 102152.86 | I76: =ROUND(I5,2) -> 102152.86 | ... L76: =ROUND(L5,2) -> 102152.86
A77: Goodwill | B77: =ROUND(B6,2) -> 0 | C77: =ROUND(C6,2) -> 0 | D77: =ROUND(D6,2) -> 0 | E77: =ROUND(E6,2) -> 0 | F77: =ROUND(F6,2) -> 0 | G77: =ROUND(G6,2) -> 0 | H77: =ROUND(H6,2) -> 0 | I77: =ROUND(I6,2) -> 0 | ... L77: =ROUND(L6,2) -> 0
A78: Ativos intangíveis | B78: =ROUND(B7,2) -> 0 | C78: =ROUND(C7,2) -> 0 | D78: =ROUND(D7,2) -> 0 | E78: =ROUND(E7,2) -> 0 | F78: =ROUND(F7,2) -> 0 | G78: =ROUND(G7,2) -> 0 | H78: =ROUND(H7,2) -> 0 | I78: =ROUND(I7,2) -> 0 | ... L78: =ROUND(L7,2) -> 0
A79: Ativos biológicos | B79: =ROUND(B8,2) -> 0 | C79: =ROUND(C8,2) -> 0 | D79: =ROUND(D8,2) -> 0 | E79: =ROUND(E8,2) -> 0 | F79: =ROUND(F8,2) -> 0 | G79: =ROUND(G8,2) -> 0 | H79: =ROUND(H8,2) -> 0 | I79: =ROUND(I8,2) -> 0 | ... L79: =ROUND(L8,2) -> 0
A80: Participações financeiras - método da equivalência patrimonial | B80: =ROUND(B9,2) -> 0 | C80: =ROUND(C9,2) -> 0 | D80: =ROUND(D9,2) -> 0 | E80: =ROUND(E9,2) -> 0 | F80: =ROUND(F9,2) -> 0 | G80: =ROUND(G9,2) -> 0 | H80: =ROUND(H9,2) -> 0 | I80: =ROUND(I9,2) -> 0 | ... L80: =ROUND(L9,2) -> 0
A81: Participações financeiras - outros métodos | B81: =ROUND(B10,2) -> 0 | C81: =ROUND(C10,2) -> 0 | D81: =ROUND(D10,2) -> 0 | E81: =ROUND(E10,2) -> 0 | F81: =ROUND(F10,2) -> 0 | G81: =ROUND(G10,2) -> 0 | H81: =ROUND(H10,2) -> 0 | I81: =ROUND(I10,2) -> 0 | ... L81: =ROUND(L10,2) -> 0
A82: Acionistas/sócios | B82: =ROUND(B11,2) -> 0 | C82: =ROUND(C11,2) -> 0 | D82: =ROUND(D11,2) -> 0 | E82: =ROUND(E11,2) -> 0 | F82: =ROUND(F11,2) -> 0 | G82: =ROUND(G11,2) -> 0 | H82: =ROUND(H11,2) -> 0 | I82: =ROUND(I11,2) -> 0 | ... L82: =ROUND(L11,2) -> 0
A83: Outros ativos financeiros | B83: =ROUND(B12,2) -> 0 | C83: =ROUND(C12,2) -> 0 | D83: =ROUND(D12,2) -> 347.82 | E83: =ROUND(E12,2) -> 347.82 | F83: =ROUND(F12,2) -> 347.82 | G83: =ROUND(G12,2) -> 347.82 | H83: =ROUND(H12,2) -> 347.82 | I83: =ROUND(I12,2) -> 347.82 | ... L83: =ROUND(L12,2) -> 347.82
A84: Ativos por impostos diferidos | B84: =ROUND(B13,2) -> 0 | C84: =ROUND(C13,2) -> 0 | D84: =ROUND(D13,2) -> 0 | E84: =ROUND(E13,2) -> 0 | F84: =ROUND(F13,2) -> 0 | G84: =ROUND(G13,2) -> 0 | H84: =ROUND(H13,2) -> 0 | I84: =ROUND(I13,2) -> 0 | ... L84: =ROUND(L13,2) -> 0
A85: Investimentos financeiros (*) | B85: =ROUND(B14,2) -> 0 | C85: =ROUND(C14,2) -> 0 | D85: =ROUND(D14,2) -> 0 | E85: =ROUND(E14,2) -> 0 | F85: =ROUND(F14,2) -> 0 | G85: =ROUND(G14,2) -> 0 | H85: =ROUND(H14,2) -> 0 | I85: =ROUND(I14,2) -> 0 | ... L85: =ROUND(L14,2) -> 0
A86: Ativo corrente
A87: Inventários | B87: =ROUND(B16,2) -> 0 | C87: =ROUND(C16,2) -> 0 | D87: =ROUND(D16,2) -> 343630.82 | E87: =ROUND(E16,2) -> 241390.37 | F87: =ROUND(F16,2) -> 255994.48 | G87: =ROUND(G16,2) -> 269752.97 | H87: =ROUND(H16,2) -> 286073.02 | I87: =ROUND(I16,2) -> 291823.09 | ... L87: =ROUND(L16,2) -> 309776.09
A88: Ativos biológicos | B88: =ROUND(B17,2) -> 0 | C88: =ROUND(C17,2) -> 0 | D88: =ROUND(D17,2) -> 0 | E88: =ROUND(E17,2) -> 0 | F88: =ROUND(F17,2) -> 0 | G88: =ROUND(G17,2) -> 0 | H88: =ROUND(H17,2) -> 0 | I88: =ROUND(I17,2) -> 0 | ... L88: =ROUND(L17,2) -> 0
A89: Clientes | B89: =ROUND(B18,2) -> 0 | C89: =ROUND(C18,2) -> 0 | D89: =ROUND(D18,2) -> 758084.77 | E89: =ROUND(E18,2) -> 1134688.5 | F89: =ROUND(F18,2) -> 1203337.1 | G89: =ROUND(G18,2) -> 1276139 | H89: =ROUND(H18,2) -> 1353345.4 | I89: =ROUND(I18,2) -> 1380547.7 | ... L89: =ROUND(L18,2) -> 1465479.2
A90: Adiantamentos a fornecedores | B90: =ROUND(B19,2) -> 0 | C90: =ROUND(C19,2) -> 0 | D90: =ROUND(D19,2) -> 0 | E90: =ROUND(E19,2) -> 0 | F90: =ROUND(F19,2) -> 0 | G90: =ROUND(G19,2) -> 0 | H90: =ROUND(H19,2) -> 0 | I90: =ROUND(I19,2) -> 0 | ... L90: =ROUND(L19,2) -> 0
A91: Estado e outros entes públicos | B91: =ROUND(B20,2) -> 0 | C91: =ROUND(C20,2) -> 0 | D91: =ROUND(D20,2) -> 21003.43 | E91: =ROUND(E20,2) -> 0 | F91: =ROUND(F20,2) -> 0 | G91: =ROUND(G20,2) -> 0 | H91: =ROUND(H20,2) -> 0 | I91: =ROUND(I20,2) -> 0 | ... L91: =ROUND(L20,2) -> 0
A92: Acionistas/sócios | B92: =ROUND(B21,2) -> 0 | C92: =ROUND(C21,2) -> 0 | D92: =ROUND(D21,2) -> 0 | E92: =ROUND(E21,2) -> 0 | F92: =ROUND(F21,2) -> 0 | G92: =ROUND(G21,2) -> 0 | H92: =ROUND(H21,2) -> 0 | I92: =ROUND(I21,2) -> 0 | ... L92: =ROUND(L21,2) -> 0
A93: Outras contas a receber | B93: =ROUND(B22,2) -> 0 | C93: =ROUND(C22,2) -> 0 | D93: =ROUND(D22,2) -> 80826.21 | E93: =ROUND(E22,2) -> 80826.21 | F93: =ROUND(F22,2) -> 80826.21 | G93: =ROUND(G22,2) -> 80826.21 | H93: =ROUND(H22,2) -> 80826.21 | I93: =ROUND(I22,2) -> 80826.21 | ... L93: =ROUND(L22,2) -> 80826.21
A94: Diferimentos | B94: =ROUND(B23,2) -> 0 | C94: =ROUND(C23,2) -> 0 | D94: =ROUND(D23,2) -> 955.33 | E94: =ROUND(E23,2) -> 955.33 | F94: =ROUND(F23,2) -> 955.33 | G94: =ROUND(G23,2) -> 955.33 | H94: =ROUND(H23,2) -> 955.33 | I94: =ROUND(I23,2) -> 955.33 | ... L94: =ROUND(L23,2) -> 955.33
A95: Ativos financeiros detidos para negociação | B95: =ROUND(B24,2) -> 0 | C95: =ROUND(C24,2) -> 0 | D95: =ROUND(D24,2) -> 0 | E95: =ROUND(E24,2) -> 0 | F95: =ROUND(F24,2) -> 0 | G95: =ROUND(G24,2) -> 0 | H95: =ROUND(H24,2) -> 0 | I95: =ROUND(I24,2) -> 0 | ... L95: =ROUND(L24,2) -> 0
A96: Outros ativos financeiros | B96: =ROUND(B25,2) -> 0 | C96: =ROUND(C25,2) -> 0 | D96: =ROUND(D25,2) -> 0 | E96: =ROUND(E25,2) -> 0 | F96: =ROUND(F25,2) -> 0 | G96: =ROUND(G25,2) -> 0 | H96: =ROUND(H25,2) -> 0 | I96: =ROUND(I25,2) -> 0 | ... L96: =ROUND(L25,2) -> 0
A97: Ativos não correntes detidos para venda | B97: =ROUND(B26,2) -> 0 | C97: =ROUND(C26,2) -> 0 | D97: =ROUND(D26,2) -> 0 | E97: =ROUND(E26,2) -> 0 | F97: =ROUND(F26,2) -> 0 | G97: =ROUND(G26,2) -> 0 | H97: =ROUND(H26,2) -> 0 | I97: =ROUND(I26,2) -> 0 | ... L97: =ROUND(L26,2) -> 0
A98: Outros ativos correntes | B98: =ROUND(B27,2) -> 0 | C98: =ROUND(C27,2) -> 0 | D98: =ROUND(D27,2) -> 0 | E98: =ROUND(E27,2) -> 0 | F98: =ROUND(F27,2) -> 0 | G98: =ROUND(G27,2) -> 0 | H98: =ROUND(H27,2) -> 0 | I98: =ROUND(I27,2) -> 0 | ... L98: =ROUND(L27,2) -> 0
A99: Caixa e depósitos bancários | B99: =ROUND(B28,2) -> 0 | C99: =ROUND(C28,2) -> 0 | D99: =ROUND(D28,2) -> 215805.41 | E99: =ROUND(E28,2) -> 23550.44 | F99: =ROUND(F28,2) -> 85411.44 | G99: =ROUND(G28,2) -> 134863.93 | H99: =ROUND(H28,2) -> 171226.18 | I99: =ROUND(I28,2) -> 233278.84 | ... L99: =ROUND(L28,2) -> 414041.15
A100: TOTAL DO ATIVO
A101: CAPITAL PRÓPRIO E PASSIVO
A102: Capital realizado | B102: =ROUND(B31,2) -> 0 | C102: =ROUND(C31,2) -> 0 | D102: =ROUND(D31,2) -> 300000 | E102: =ROUND(E31,2) -> 300000 | F102: =ROUND(F31,2) -> 300000 | G102: =ROUND(G31,2) -> 300000 | H102: =ROUND(H31,2) -> 300000 | I102: =ROUND(I31,2) -> 300000 | ... L102: =ROUND(L31,2) -> 300000
A103: Ações (quotas) próprias | B103: =ROUND(B32,2) -> 0 | C103: =ROUND(C32,2) -> 0 | D103: =ROUND(D32,2) -> 0 | E103: =ROUND(E32,2) -> 0 | F103: =ROUND(F32,2) -> 0 | G103: =ROUND(G32,2) -> 0 | H103: =ROUND(H32,2) -> 0 | I103: =ROUND(I32,2) -> 0 | ... L103: =ROUND(L32,2) -> 0
A104: Outros instrumentos de capital próprio | B104: =ROUND(B33,2) -> 0 | C104: =ROUND(C33,2) -> 0 | D104: =ROUND(D33,2) -> 0 | E104: =ROUND(E33,2) -> 5158.81 | F104: =ROUND(F33,2) -> 28514.61 | G104: =ROUND(G33,2) -> 37087.25 | H104: =ROUND(H33,2) -> 37087.25 | I104: =ROUND(I33,2) -> 37087.25 | ... L104: =ROUND(L33,2) -> 37087.25
...

Sheet Mapa_Invest_Form
A1: N.º | C1: Actividade Inovação | D1: Designação | E1: Aquisição (aaaa-mm) | F1: Investimento | G1: Elegível | H1: Classificação das despesas | I1: Tipologia de Operação | J1: SNC | K1: Mercado | L1: Estabelecimento | M1: Concellho | N1: NUT II | Q1: 43.1 - Terrenos e recursos naturais
Q2: 43.2 - Edifícios e outras construções
A3: 1 | B3: 1 | C3: Feira IDTECHEX - Alemanha | D3: Feira IDTECHEX - Alemanha - Aluguer de espaços | E3: 2020-04 | F3: 7200 | G3: 7200 | H3: Feiras e exposições - Aluguer de espaço | J3: 62.2 - Serviços especializados | K3: Alemanha | Q3: 43.3 - Equipamento básico
A4: 2 | B4: 1 | C4: Feira IDTECHEX - Alemanha | D4: Feira IDTECHEX - Alemanha - Concepção, decoração e montagem de stand | E4: 2020-04 | F4: 3500 | G4: 3500 | H4: Feiras e exposições - Construção Stand | J4: 62.2 - Serviços especializados | K4: Alemanha | Q4: 43.4 - Equipamento de transporte
A5: 3 | B5: 1 | C5: Feira IDTECHEX - Alemanha | D5: Feira IDTECHEX - Alemanha - Transporte de materiais, mostruários e outros suportes promocionais | E5: 2020-04 | F5: 750 | G5: 750 | H5: Feiras e exposições - Outros serviços - Construção Stand | J5: 62.5 - Deslocações, estadas, e transportes | K5: Alemanha | Q5: 43.5 - Equipamento administrativo
A6: 4 | B6: 1 | C6: Feira IDTECHEX - Alemanha | D6: Feira IDTECHEX - Alemanha - Assistência Local e apoio logístico | E6: 2020-04 | F6: 2500 | G6: 2500 | H6: Feiras e exposições - Custos de funcionamento | J6: 62.2 - Serviços especializados | K6: Alemanha | Q6: 43.6 - Equipamentos biológicos
A7: 5 | B7: 1 | C7: Feira IDTECHEX - Alemanha | D7: Feira IDTECHEX - Alemanha - Tradutor/interprete | E7: 2020-04 | F7: 1500 | G7: 1500 | H7: Feiras e exposições - Custos de funcionamento | J7: 62.2 - Serviços especializados | K7: Alemanha | Q7: 43.7 - Outros ativos fixos tangíveis
A8: 6 | B8: 1 | C8: Feira IDTECHEX - Alemanha | D8: Feira IDTECHEX - Alemanha - Material Promocional | E8: 2020-04 | F8: 2500 | G8: 2500 | H8: Feiras e exposições - Outros serviços - Construção Stand | J8: 62.2 - Serviços especializados | K8: Alemanha | Q8: 44.1 - Goodwill
A9: 7 | B9: 1 | C9: Feira IDTECHEX - Alemanha | D9: Feira IDTECHEX - Alemanha - Promoção e divulgação do local do stand e Assessoria de Imprensa | E9: 2020-04 | F9: 3000 | G9: 3000 | H9: Feiras e exposições - Custos de funcionamento | J9: 62.5 - Deslocações, estadas, e transportes | K9: Alemanha | Q9: 44.2 - Projetos de desenvolvimento
A10: 8 | B10: 1 | C10: Feira IDTECHEX - Alemanha | D10: Feira IDTECHEX - Alemanha - Viagem e estadia | E10: 2020-04 | F10: 1450 | G10: 1450 | H10: Feiras e exposições - Deslocações e alojamento | J10: 62.5 - Deslocações, estadas, e transportes | K10: Alemanha | Q10: 43.3 - Equipamento básico
A11: 9 | B11: 2 | C11: Feira IDTECHEX - USA - California | D11: Feira IDTECHEX - USA - California - Santa Clara Convention Centers - Aluguer de espaços | E11: 2019-11 | F11: 6900 | G11: 6900 | H11: Feiras e exposições - Aluguer de espaço | J11: 62.2 - Serviços especializados | K11: Estados Unidos | Q11: 43.4 - Equipamento de transporte
A12: 10 | B12: 2 | C12: Feira IDTECHEX - USA - California | D12: Feira IDTECHEX - USA - California - Santa Clara Convention Centers - Concepção, decoração e montagem de stand | E12: 2019-11 | F12: 3500 | G12: 3500 | H12: Feiras e exposições - Construção Stand | J12: 62.2 - Serviços especializados | K12: Estados Unidos | Q12: 43.5 - Equipamento administrativo
A13: 11 | B13: 2 | C13: Feira IDTECHEX - USA - California | D13: Feira IDTECHEX - USA - California - Santa Clara Convention Centers - Transporte de materiais, mostruários e outros suportes promocionais | E13: 2019-11 | F13: 1500 | G13: 1500 | H13: Feiras e exposições - Outros serviços - Construção Stand | J13: 62.5 - Deslocações, estadas, e transportes | K13: Estados Unidos | Q13: 43.6 - Equipamentos biológicos
A14: 12 | B14: 2 | C14: Feira IDTECHEX - USA - California | D14: Feira IDTECHEX - USA - California - Santa Clara Convention Centers - Assistência Local e apoio logístico | E14: 2019-11 | F14: 2500 | G14: 2500 | H14: Feiras e exposições - Custos de funcionamento | J14: 62.2 - Serviços especializados | K14: Estados Unidos | Q14: 43.7 - Outros ativos fixos tangíveis
... A29: 27 | B29: 4 | C29: Feira Wearable Technology Show - Reino Unido | D29: Feira Wearable Technology Show - Reino Unido - Material Promocional | E29: 2020-03 | F29: 2500 | G29: 2500 | H29: Feiras e exposições - Outros serviços - Construção Stand | J29: 62.2 - Serviços especializados | K29: Reino Unido | Q29: Fundo de Maneio
A30: 28 | B30: 4 | C30: Feira Wearable Technology Show - Reino Unido | D30: Feira Wearable Technology Show - Reino Unido - Promoção e divulgação do local do stand e Assessoria de Imprensa | E30: 2020-03 | F30: 3000 | G30: 3000 | H30: Feiras e exposições - Custos de funcionamento | J30: 62.5 - Deslocações, estadas, e transportes | K30: Reino Unido
A31: 29 | B31: 4 | C31: Feira Wearable Technology Show - Reino Unido | D31: Feira Wearable Technology Show - Reino Unido - Viagem e estadia | E31: 2020-03 | F31: 1450 | G31: 1450 | H31: Feiras e exposições - Deslocações e alojamento | J31: 62.5 - Deslocações, estadas, e transportes | K31: Reino Unido
A32: 30 | B32: 5 | C32: Feira Wearable Technology Show - Reino Unido | D32: Feira Wearable Technology Show - Reino Unido- Aluguer de espaços | E32: 2021-03 | F32: 8100 | G32: 8100 | H32: Feiras e exposições - Aluguer de espaço | J32: 62.2 - Serviços especializados | K32: Reino Unido | Q32: Equipamentos
A33: 31 | B33: 5 | C33: Feira Wearable Technology Show - Reino Unido | D33: Feira Wearable Technology Show - Reino Unido - Concepção, decoração e montagem de stand | E33: 2021-03 | F33: 3500 | G33: 3500 | H33: Feiras e exposições - Construção Stand | J33: 62.2 - Serviços especializados | K33: Reino Unido | Q33: Software
A34: 32 | B34: 5 | C34: Feira Wearable Technology Show - Reino Unido | D34: Feira Wearable Technology Show - Reino Unido - Transporte de materiais, mostruários e outros suportes promocionais | E34: 2021-03 | F34: 1000 | G34: 1000 | H34: Feiras e exposições - Outros serviços - Construção Stand | J34: 62.5 - Deslocações, estadas, e transportes | K34: Reino Unido | Q34: Custo com contratação técnicos
A35: 33 | B35: 5 | C35: Feira Wearable Technology Show - Reino Unido | D35: Feira Wearable Technology Show - Reino Unido - Assistência Local e apoio logístico | E35: 2021-03 | F35: 2500 | G35: 2500 | H35: Feiras e exposições - Custos de funcionamento | J35: 62.2 - Serviços especializados | K35: Reino Unido | Q35: Feiras e exposições - Aluguer de espaço
A36: 34 | B36: 5 | C36: Feira Wearable Technology Show - Reino Unido | D36: Feira Wearable Technology Show - Reino Unido - Material Promocional | E36: 2021-03 | F36: 2500 | G36: 2500 | H36: Feiras e exposições - Outros serviços - Construção Stand | J36: 62.2 - Serviços especializados | K36: Reino Unido | Q36: Feiras e exposições - Outros serviços - Aluguer de espaço
A37: 35 | B37: 5 | C37: Feira Wearable Technology Show - Reino Unido | D37: Feira Wearable Technology Show - Reino Unido - Promoção e divulgação do local do stand e Assessoria de Imprensa | E37: 2021-03 | F37: 3000 | G37: 3000 | H37: Feiras e exposições - Custos de funcionamento | J37: 62.5 - Deslocações, estadas, e transportes | K37: Reino Unido | Q37: Feiras e exposições - Construção Stand
A38: 36 | B38: 5 | C38: Feira Wearable Technology Show - Reino Unido | D38: Feira Wearable Technology Show - Reino Unido - Viagem e estadia | E38: 2021-03 | F38: 1450 | G38: 1450 | H38: Feiras e exposições - Deslocações e alojamento | J38: 62.5 - Deslocações, estadas, e transportes | K38: Reino Unido | Q38: Feiras e exposições - Outros serviços - Construção Stand
A39: 37 | B39: 6 | C39: Feira Medica-Trade Fair - Alemanha | D39: Feira Medica-Trade Fair - Alemanha - Aluguer de espaços | E39: 2020-05 | F39: 7400 | G39: 7400 | H39: Feiras e exposições - Aluguer de espaço | J39: 62.2 - Serviços especializados | K39: Alemanha | Q39: Feiras e exposições - Custos de funcionamento
A40: 38 | B40: 6 | C40: Feira Medica-Trade Fair - Alemanha | D40: Feira Medica-Trade Fair - Alemanha - Concepção, decoração e montagem de stand | E40: 2020-05 | F40: 3500 | G40: 3500 | H40: Feiras e exposições - Construção Stand | J40: 62.2 - Serviços especializados | K40: Alemanha | Q40: Feiras e exposições - Deslocações e alojamento
A41: 39 | B41: 6 | C41: Feira Medica-Trade Fair - Alemanha | D41: Feira Medica-Trade Fair - Alemanha - Transporte de materiais, mostruários e outros suportes promocionais | E41: 2020-05 | F41: 750 | G41: 750 | H41: Feiras e exposições - Outros serviços - Construção Stand | J41: 62.5 - Deslocações, estadas, e transportes | K41: Alemanha | Q41: Prospeção - Contratação de serviços específicos
A42: 40 | B42: 6 | C42: Feira Medica-Trade Fair - Alemanha | D42: Feira Medica-Trade Fair - Alemanha - Assistência Local e apoio logístico | E42: 2020-05 | F42: 2500 | G42: 2500 | H42: Feiras e exposições - Custos de funcionamento | J42: 62.2 - Serviços especializados | K42: Alemanha | Q42: Prospeção - Estudos e aquisição de informação
A43: 41 | B43: 6 | C43: Feira Medica-Trade Fair - Alemanha | D43: Feira Medica-Trade Fair - Alemanha - Tradutor/interprete | E43: 2020-05 | F43: 1500 | G43: 1500 | H43: Feiras e exposições - Custos de funcionamento | J43: 62.2 - Serviços especializados | K43: Alemanha | Q43: Prospeção - Deslocações e alojamento
... A64: 62 | B64: 9 | C64: Feira CES Las vegas em USA | D64: Feira CES Las vegas em USA - Transporte de materiais, mostruários e outros suportes promocionais | E64: 2021-01 | F64: 1500 | G64: 1500 | H64: Feiras e exposições - Outros serviços - Construção Stand | J64: 62.5 - Deslocações, estadas, e transportes | K64: Estados Unidos | Q64: Despesas não elegíveis
A65: 63 | B65: 9 | C65: Feira CES Las vegas em USA | D65: Feira CES Las vegas em USA - Assistência Local e apoio logístico | E65: 2021-01 | F65: 2500 | G65: 2500 | H65: Feiras e exposições - Custos de funcionamento | J65: 62.2 - Serviços especializados | K65: Estados Unidos
A66: 64 | B66: 9 | C66: Feira CES Las vegas em USA | D66: Feira CES Las vegas em USA - Material Promocional | E66: 2021-01 | F66: 2500 | G66: 2500 | H66: Feiras e exposições - Outros serviços - Construção Stand | J66: 62.2 - Serviços especializados | K66: Estados Unidos
A67: 65 | B67: 9 | C67: Feira CES Las vegas em USA | D67: Feira CES Las vegas em USA - Promoção e divulgação do local do stand e Assessoria de Imprensa | E67: 2021-01 | F67: 3000 | G67: 3000 | H67: Feiras e exposições - Custos de funcionamento | J67: 62.5 - Deslocações, estadas, e transportes | K67: Estados Unidos
A68: 66 | B68: 9 | C68: Feira CES Las vegas em USA | D68: Feira CES Las vegas em USA - Viagem e estadia | E68: 2021-01 | F68: 2850 | G68: 2850 | H68: Feiras e exposições - Deslocações e alojamento | J68: 62.5 - Deslocações, estadas, e transportes | K68: Estados Unidos
A69: 67 | B69: 10 | C69: Feira BONUS Hospitalar S. Paulo em Brasil | D69: Feira BONUS Hospitalar S. Paulo em Brasil - Aluguer de espaços - 2020 | E69: 2020-05 | F69: 7100 | G69: 7100 | H69: Feiras e exposições - Aluguer de espaço | J69: 62.2 - Serviços especializados | K69: Brasil
A70: 68 | B70: 10 | C70: Feira BONUS Hospitalar S. Paulo em Brasil | D70: Feira BONUS Hospitalar S. Paulo em Brasil - Concepção, decoração e montagem de stand | E70: 2020-05 | F70: 3500 | G70: 3500 | H70: Feiras e exposições - Construção Stand | J70: 62.2 - Serviços especializados | K70: Brasil
A71: 69 | B71: 10 | C71: Feira BONUS Hospitalar S. Paulo em Brasil | D71: Feira BONUS Hospitalar S. Paulo em Brasil - Transporte de materiais, mostruários e outros suportes promocionais | E71: 2020-05 | F71: 1500 | G71: 1500 | H71: Feiras e exposições - Outros serviços - Construção Stand | J71: 62.5 - Deslocações, estadas, e transportes | K71: Brasil
A72: 70 | B72: 10 | C72: Feira BONUS Hospitalar S. Paulo em Brasil | D72: Feira BONUS Hospitalar S. Paulo em Brasil - Assistência Local e apoio logístico | E72: 2020-05 | F72: 2500 | G72: 2500 | H72: Feiras e exposições - Custos de funcionamento | J72: 62.2 - Serviços especializados | K72: Brasil
A73: 71 | B73: 10 | C73: Feira BONUS Hospitalar S. Paulo em Brasil | D73: Feira BONUS Hospitalar S. Paulo em Brasil - Material Promocional | E73: 2020-05 | F73: 2500 | G73: 2500 | H73: Feiras e exposições - Outros serviços - Construção Stand | J73: 62.2 - Serviços especializados | K73: Brasil
A74: 72 | B74: 10 | C74: Feira BONUS Hospitalar S. Paulo em Brasil | D74: Feira BONUS Hospitalar S. Paulo em Brasil - Promoção e divulgação do local do stand e Assessoria de Imprensa | E74: 2020-05 | F74: 3000 | G74: 3000 | H74: Feiras e exposições - Custos de funcionamento | J74: 62.5 - Deslocações, estadas, e transportes | K74: Brasil
A75: 73 | B75: 10 | C75: Feira BONUS Hospitalar S. Paulo em Brasil | D75: Feira BONUS Hospitalar S. Paulo em Brasil - Viagem e estadia | E75: 2020-05 | F75: 2850 | G75: 2850 | H75: Feiras e exposições - Deslocações e alojamento | J75: 62.5 - Deslocações, estadas, e transportes | K75: Brasil
A76: 74 | B76: 11 | C76: Feira BONUS Hospitalar S. Paulo em Brasil | D76: Feira BONUS Hospitalar S. Paulo em Brasil - Aluguer de espaços - 2021 | E76: 2021-05 | F76: 7100 | G76: 7100 | H76: Feiras e exposições - Aluguer de espaço | J76: 62.2 - Serviços especializados | K76: Brasil
... A111: 109 | B111: 20 | C111: Showroom em USA Silicon valley 2027 | D111: Showroom em USA Silicon valley 2021 - Viagem e alojamento | E111: 2021-04 | F111: 2850 | G111: 2850 | H111: Promoção - Deslocações e alojamento | J111: 62.5 - Deslocações, estadas, e transportes | K111: Estados Unidos
A112: 110 | B112: 21 | C112: Showroom em Alemanha 2020 | D112: Showroom em Alemanha 2020 - Organização e gestão do evento | E112: 43983 | F112: 3500 | G112: 3500 | H112: Promoção - Contratação de serviços específicos | J112: 62.2 - Serviços especializados | K112: Alemanha
A113: 111 | B113: 21 | C113: Showroom em Alemanha 2021 | D113: Showroom em Alemanha 2020 - Aluguer de espaço | E113: 43983 | F113: 3000 | G113: 3000 | H113: Promoção - Contratação de serviços específicos | J113: 62.2 - Serviços especializados | K113: Alemanha
A114: 112 | B114: 21 | C114: Showroom em Alemanha 2022 | D114: Showroom em Alemanha 2020 - Implementação de showroom (incluindo design, concepção, preparação, decoração, materiais e equipamentos, obras, instalações diversas, etc) | E114: 43983 | F114: 5000 | G114: 5000 | H114: Promoção - Contratação de serviços específicos | J114: 62.2 - Serviços especializados | K114: Alemanha
A115: 113 | B115: 21 | C115: Showroom em Alemanha 2023 | D115: Showroom em Alemanha 2020 - Divulgação do evento e assessoria de imprensa | E115: 43983 | F115: 4500 | G115: 4500 | H115: Promoção - Assessoria de imprensa e relações públicas | J115: 62.2 - Serviços especializados | K115: Alemanha
A116: 114 | B116: 21 | C116: Showroom em Alemanha 2024 | D116: Showroom em Alemanha 2020 - Material Promocional para o evento | E116: 43983 | F116: 2000 | G116: 2000 | H116: Promoção - Contratação de serviços específicos | J116: 62.2 - Serviços especializados | K116: Alemanha
A117: 115 | B117: 21 | C117: Showroom em Alemanha 2025 | D117: Showroom em Alemanha 2020 - Assistência local e apoio logístico e tradutores/interpretes | E117: 43983 | F117: 2500 | G117: 2500 | H117: Promoção - Contratação de serviços específicos | J117: 62.2 - Serviços especializados | K117: Alemanha
A118: 116 | B118: 21 | C118: Showroom em Alemanha 2026 | D118: Showroom em Alemanha 2020 - Viagem e alojamento | E118: 43983 | F118: 1450 | G118: 1450 | H118: Promoção - Deslocações e alojamento | J118: 62.5 - Deslocações, estadas, e transportes | K118: Alemanha
A119: 117 | B119: 22 | C119: Showroom em Alemanha 2021 | D119: Showroom em Alemanha 2021 - Organização e gestão do evento | E119: 2020-06 | F119: 3500 | G119: 3500 | H119: Promoção - Contratação de serviços específicos | J119: 62.2 - Serviços especializados | K119: Alemanha
A120: 118 | B120: 22 | C120: Showroom em Alemanha 2022 | D120: Showroom em Alemanha 2021 - Aluguer de espaço | E120: 2020-06 | F120: 3000 | G120: 3000 | H120: Promoção - Contratação de serviços específicos | J120: 62.2 - Serviços especializados | K120: Alemanha
A121: 119 | B121: 22 | C121: Showroom em Alemanha 2023 | D121: Showroom em Alemanha 2021 - Implementação de showroom (incluindo design, concepção, preparação, decoração, materiais e equipamentos, obras, instalações diversas, etc) | E121: 2020-06 | F121: 5000 | G121: 5000 | H121: Promoção - Contratação de serviços específicos | J121: 62.2 - Serviços especializados | K121: Alemanha
A122: 120 | B122: 22 | C122: Showroom em Alemanha 2024 | D122: Showroom em Alemanha 2021 - Divulgação do evento e assessoria de imprensa | E122: 2020-06 | F122: 4500 | G122: 4500 | H122: Promoção - Assessoria de imprensa e relações públicas | J122: 62.2 - Serviços especializados | K122: Alemanha
A123: 121 | B123: 22 | C123: Showroom em Alemanha 2025 | D123: Showroom em Alemanha 2021 - Material Promocional para o evento | E123: 2020-06 | F123: 2000 | G123: 2000 | H123: Promoção - Contratação de serviços específicos | J123: 62.2 - Serviços especializados | K123: Alemanha
A124: 122 | B124: 22 | C124: Showroom em Alemanha 2026 | D124: Showroom em Alemanha 2021 - Assistência local e apoio logístico e tradutores/interpretes | E124: 2020-06 | F124: 2500 | G124: 2500 | H124: Promoção - Contratação de serviços específicos | J124: 62.2 - Serviços especializados | K124: Alemanha
A125: 123 | B125: 22 | C125: Showroom em Alemanha 2027 | D125: Showroom em Alemanha 2021 - Viagem e alojamento | E125: 2020-06 | F125: 1450 | G125: 1450 | H125: Promoção - Deslocações e alojamento | J125: 62.5 - Deslocações, estadas, e transportes | K125: Alemanha
A126: 124 | B126: 23 | C126: Showroom em Espanha 2019 | D126: Showroom em Espanha 2019 - Organização e gestão do evento | E126: 2019-12 | F126: 3500 | G126: 3500 | H126: Promoção - Contratação de serviços específicos | J126: 62.2 - Serviços especializados | K126: Espanha
A127: 125 | B127: 23 | C127: Showroom em Espanha 2020 | D127: Showroom em Espanha 2019 - Aluguer de espaço | E127: 2019-12 | F127: 3000 | G127: 3000 | H127: Promoção - Contratação de serviços específicos | J127: 62.2 - Serviços especializados | K127: Espanha
A128: 126 | B128: 23 | C128: Showroom em Espanha 2021 | D128: Showroom em Espanha 2019 - Implementação de showroom (incluindo design, concepção, preparação, decoração, materiais e equipamentos, obras, instalações diversas, etc) | E128: 2019-12 | F128: 5000 | G128: 5000 | H128: Promoção - Contratação de serviços específicos | J128: 62.2 - Serviços especializados | K128: Espanha
A129: 127 | B129: 23 | C129: Showroom em Espanha 2022 | D129: Showroom em Espanha 2019 - Divulgação do evento e assessoria de imprensa | E129: 2019-12 | F129: 4500 | G129: 4500 | H129: Promoção - Assessoria de imprensa e relações públicas | J129: 62.2 - Serviços especializados | K129: Espanha
A130: 128 | B130: 23 | C130: Showroom em Espanha 2023 | D130: Showroom em Espanha 2019 - Material Promocional para o evento | E130: 2019-12 | F130: 2000 | G130: 2000 | H130: Promoção - Contratação de serviços específicos | J130: 62.2 - Serviços especializados | K130: Espanha
... A180: 178 | B180: 31 | C180: CRM | D180: CRM | E180: 2020-02 | F180: 10000 | G180: 10000 | H180: Software | J180: 44.3 - Programas de computador | K180: Portugal

Sheet TIR&VAL_Empresa
B2: FLUXOS FINANCEIROS DA EMPRESA (Histórico + Projeto)
B4: EXISTE PERPETUIDADE? | C4: Sim
B6: RUBRICAS | C6: =Pressupostos!C11 -> 2020 | D6: =C6+1 -> 2021 | E6: =D6+1 -> 2022 | F6: =E6+1 -> 2023 | G6: =F6+1 -> 2024 | H6: =G6+1 -> 2025 | I6: =H6+1 -> 2026 | J6: =I6+1 -> 2027 | K6: =J6+1 -> 2028 | L6: =K6+1 -> 2029
B7: (+) EBITDA | C7: ='DR Empresa'!C21 -> 52067.259 | D7: ='DR Empresa'!D21 -> 93897.528 | E7: ='DR Empresa'!E21 -> 87265.721 | F7: ='DR Empresa'!F21 -> 101993.65 | G7: ='DR Empresa'!G21 -> 104005.69 | H7: ='DR Empresa'!H21 -> 102796.21 | I7: ='DR Empresa'!I21 -> 104891.07 | J7: ='DR Empresa'!J21 -> 107028.6 | ... L7: ='DR Empresa'!L21 -> 111435.2
B8: (-) Imposto | C8: =-'DR Empresa'!C28 -> -7184.8061 | D8: =-'DR Empresa'!D28 -> -14350.049 | E8: =-'DR Empresa'!E28 -> -12871.62 | F8: =-'DR Empresa'!F28 -> -16199.133 | G8: =-'DR Empresa'!G28 -> -16665.569 | H8: =-'DR Empresa'!H28 -> -18653.733 | I8: =-'DR Empresa'!I28 -> -19125.075 | J8: =-'DR Empresa'!J28 -> -19606.019 | ... L8: =-'DR Empresa'!L28 -> -23168.851
B9: (-) Investimento em FML | C9: =-FM!H18 -> -247467.67 | D9: =-FM!I18 -> -32679.35 | E9: =-FM!J18 -> -37892.748 | F9: =-FM!K18 -> -38084.394 | G9: =-FM!L18 -> -14004.335 | H9: =-FM!M18 -> -12982.347 | I9: =-FM!N18 -> -14800.077 | J9: =-FM!O18 -> -15097.43 | ... L9: =-FM!Q18 -> -15710.178
B10: (-) Investimento em Ativos | C10: =-SUM(PlanoInvest!C96:C99) -> 0 | D10: =-SUM(PlanoInvest!D96:D99) -> -40000 | E10: =-SUM(PlanoInvest!E96:E99) -> 0 | F10: =-SUM(PlanoInvest!F96:F99) -> 0 | G10: =-SUM(PlanoInvest!G96:G99) -> 0 | H10: =-SUM(PlanoInvest!H96:H99) -> 0 | I10: =-SUM(PlanoInvest!I96:I99) -> 0 | J10: =-SUM(PlanoInvest!J96:J99) -> 0 | ... L10: =-SUM(PlanoInvest!L96:L99) -> 0
B11: (-) Custos de Financiamento | C11: =-'DR Empresa'!C26 -> -11672.263 | D11: =-'DR Empresa'!D26 -> -11657.01 | E11: =-'DR Empresa'!E26 -> -11595.996 | F11: =-'DR Empresa'!F26 -> -11534.983 | G11: =-'DR Empresa'!G26 -> -11473.97 | H11: =-'DR Empresa'!H26 -> -11428.21 | I11: =-'DR Empresa'!I26 -> -11428.21 | J11: =-'DR Empresa'!J26 -> -11428.21 | ... L11: =-'DR Empresa'!L26 -> 0
B12: (=) Free Cash Flow (FCF) | C12: =SUM(C7:C11) -> -214257.48 | D12: =SUM(D7:D11) -> -4788.8806 | E12: =SUM(E7:E11) -> 24905.357 | F12: =SUM(F7:F11) -> 36175.144 | G12: =SUM(G7:G11) -> 61861.814 | H12: =SUM(H7:H11) -> 59731.923 | I12: =SUM(I7:I11) -> 59537.704 | J12: =SUM(J7:J11) -> 60896.939 | ... L12: =SUM(L7:L11) -> 72556.167
B13: (+) Valor Residual / Perpetuidade | L13: =IF($C$4="Sim",L12*(1+Pressupostos!$M$17)/(Pressupostos!$C$35-Pressupostos!$M$17),'Balanço Futuro'!L19+FM!Q16) -> 1221362.1
B14: (=) Free Cash Flow Total | C14: =C12+C13 -> -214257.48 | D14: =D12+D13 -> -4788.8806 | E14: =E12+E13 -> 24905.357 | F14: =F12+F13 -> 36175.144 | G14: =G12+G13 -> 61861.814 | H14: =H12+H13 -> 59731.923 | I14: =I12+I13 -> 59537.704 | J14: =J12+J13 -> 60896.939 | ... L14: =L12+L13 -> 1293918.3
B15: Fator de desconto | C15: =1/((1+Pressupostos!$C$35)^(C$6-$C$6)) -> 1 | D15: =1/((1+Pressupostos!$C$35)^(D$6-$C$6)) -> 0.93457944 | E15: =1/((1+Pressupostos!$C$35)^(E$6-$C$6)) -> 0.87343873 | F15: =1/((1+Pressupostos!$C$35)^(F$6-$C$6)) -> 0.81629788 | G15: =1/((1+Pressupostos!$C$35)^(G$6-$C$6)) -> 0.76289521 | H15: =1/((1+Pressupostos!$C$35)^(H$6-$C$6)) -> 0.71298618 | I15: =1/((1+Pressupostos!$C$35)^(I$6-$C$6)) -> 0.66634222 | J15: =1/((1+Pressupostos!$C$35)^(J$6-$C$6)) -> 0.62274974 | ... L15: =1/((1+Pressupostos!$C$35)^(L$6-$C$6)) -> 0.54393374
B16: Valor Atual dos FCF | C16: =C14*C15 -> -214257.48 | D16: =D14*D15 -> -4475.5894 | E16: =E14*E15 -> 21753.303 | F16: =F14*F15 -> 29529.693 | G16: =G14*G15 -> 47194.082 | H16: =H14*H15 -> 42588.035 | I16: =I14*I15 -> 39672.486 | J16: =J14*J15 -> 37923.553 | ... L16: =L14*L15 -> 703805.83
B17: Valor Atual Líquido (VAL) | C17: =D14+NPV(Pressupostos!$C$35,C14:F14) -> -161284.28
B18: Taxa Interna de Rentabilidade (TIR) | C18: =IFERROR(IRR(C14:F14),"-") -> -0.38570335

Sheet Rácios
B2: INDICADORES DE GESTÃO
C3: =D3-1 -> 2017 | D3: =E3-1 -> 2018 | E3: =F3-1 -> 2019 | F3: =Pressupostos!C11 -> 2020 | G3: =F3+1 -> 2021 | H3: =G3+1 -> 2022 | I3: =H3+1 -> 2023 | J3: =I3+1 -> 2024 | K3: =J3+1 -> 2025 | L3: =K3+1 -> 2026 | M3: =L3+1 -> 2027 | N3: =M3+1 -> 2028 | O3: =N3+1 -> 2029
B4: Vendas + Prestação Serviços | C4: =DR_Form!B79 -> 0 | D4: =DR_Form!C79 -> 0 | E4: =DR_Form!D79 -> 3479532.1 | F4: =DR_Form!E79 -> 3690043.8 | G4: =DR_Form!F79 -> 3913291.5 | H4: =DR_Form!G79 -> 4150045.6 | I4: =DR_Form!H79 -> 4401123.4 | J4: =DR_Form!I79 -> 4489586 | ... M4: =DR_Form!L79 -> 4765786 | N4: - | O4: -
B5: Resultado Líquido | C5: =DR_Form!B110 -> 0 | D5: =DR_Form!C110 -> 0 | E5: =DR_Form!D110 -> 31854.57 | F5: =DR_Form!E110 -> 24747.67 | G5: =DR_Form!F110 -> 49427.95 | H5: =DR_Form!G110 -> 44335.58 | I5: =DR_Form!H110 -> 55797.01 | J5: =DR_Form!I110 -> 57403.62 | ... M5: =DR_Form!L110 -> 67531.84 | N5: - | O5: -
B6: Cash Flow
B7: Meios Libertos de Exploração | C7: =DR_Form!B114 -> 0 | D7: =DR_Form!C114 -> 0 | E7: =DR_Form!D114 -> 47101.82 | F7: =DR_Form!E114 -> 33210.19 | G7: =DR_Form!F114 -> 67890.47 | H7: =DR_Form!G114 -> 62798.1 | I7: =DR_Form!H114 -> 74259.53 | J7: =DR_Form!I114 -> 75866.14 | ... M7: =DR_Form!L114 -> 75994.36
B8: Capital Próprio | C8: =Balanço_Form!B186 -> 0 | D8: =Balanço_Form!C186 -> 0 | E8: =Balanço_Form!D186 -> 601267.33 | F8: =Balanço_Form!E186 -> 640459.67 | G8: =Balanço_Form!F186 -> 755283.84 | H8: =Balanço_Form!G186 -> 823622.82 | I8: =Balanço_Form!H186 -> 879419.83 | J8: =Balanço_Form!I186 -> 936823.46 | ... M8: =Balanço_Form!L186 -> 1134482.3 | N8: - | O8: -
B9: Ativo | C9: =SUM(Balanço_Form!B146:B170) -> 0 | D9: =SUM(Balanço_Form!C146:C170) -> 0 | E9: =SUM(Balanço_Form!D146:D170) -> 3027737.9 | F9: =SUM(Balanço_Form!E146:E170) -> 3141485.1 | G9: =SUM(Balanço_Form!F146:F170) -> 3453250.1 | H9: =SUM(Balanço_Form!G146:G170) -> 3706813.3 | I9: =SUM(Balanço_Form!H146:H170) -> 3948128.2 | J9: =SUM(Balanço_Form!I146:I170) -> 4119675.6 | ... M9: =SUM(Balanço_Form!L146:L170) -> 4661581.6 | N9: - | O9: -
B10: Capitais Permanentes | C10: =Balanço_Form!B186+(SUM(Balanço_Form!B189:B193)) -> 0 | D10: =Balanço_Form!C186+(SUM(Balanço_Form!C189:C193)) -> 0 | E10: =Balanço_Form!D186+(SUM(Balanço_Form!D189:D193)) -> 601267.33 | F10: =Balanço_Form!E186+(SUM(Balanço_Form!E189:E193)) -> 640459.67 | G10: =Balanço_Form!F186+(SUM(Balanço_Form!F189:F193)) -> 755283.84 | H10: =Balanço_Form!G186+(SUM(Balanço_Form!G189:G193)) -> 823622.82 | I10: =Balanço_Form!H186+(SUM(Balanço_Form!H189:H193)) -> 879419.83 | J10: =Balanço_Form!I186+(SUM(Balanço_Form!I189:I193)) -> 936823.46 | ... M10: =Balanço_Form!L186+(SUM(Balanço_Form!L189:L193)) -> 1134482.3
B11: Numero Trab | C11: - | D11: - | E11: =RH!D8 -> 0 | F11: =E11+RH!J13 -> 0 | G11: =F11+RH!J14 -> 2 | H11: =G11+RH!J15 -> 2 | I11: =H11+RH!J16 -> 2 | J11: =I11+RH!J17 -> 2 | K11: =J11+RH!J18 -> 2 | L11: =K11 -> 2 | M11: =L11 -> 2
B12: Vendas por trabalhador | C12: =IFERROR(C4/C11,"-") -> - | D12: =IFERROR(D4/D11,"-") -> - | E12: =E4/E11 -> #DIV/0! | F12: =F4/F11 -> #DIV/0! | G12: =G4/G11 -> 1956645.7 | H12: =H4/H11 -> 2075022.8 | I12: =I4/I11 -> 2200561.7 | J12: =J4/J11 -> 2244793 | K12: =K4/K11 -> 2289913.3 | L12: =L4/L11 -> 2335940.6 | M12: =M4/M11 -> 2382893
B14: ANÁLISE ECONOMICA
C15: =C3 -> 2017 | D15: =D3 -> 2018 | E15: =E3 -> 2019 | F15: =F3 -> 2020 | G15: =G3 -> 2021 | H15: =H3 -> 2022 | I15: =I3 -> 2023 | J15: =J3 -> 2024 | ... O15: =O3 -> 2029
B16: Rentab. Bruta Vendas | C16: =IFERROR((DR_Form!B79+DR_Form!B84)/(DR_Form!B79),"-") -> - | D16: =IFERROR((DR_Form!C79+DR_Form!C84)/(DR_Form!C79),"-") -> - | E16: =IFERROR((DR_Form!D79+DR_Form!D84)/(DR_Form!D79),"-") -> 1.7991279 | F16: =IFERROR((DR_Form!E79+DR_Form!E84)/(DR_Form!E79),"-") -> 1.785 | G16: =IFERROR((DR_Form!F79+DR_Form!F84)/(DR_Form!F79),"-") -> 1.785 | H16: =IFERROR((DR_Form!G79+DR_Form!G84)/(DR_Form!G79),"-") -> 1.78 | I16: =IFERROR((DR_Form!H79+DR_Form!H84)/(DR_Form!H79),"-") -> 1.78 | J16: =IFERROR((DR_Form!I79+DR_Form!I84)/(DR_Form!I79),"-") -> 1.78 | ... O16: =IFERROR((DR_Form!N79+DR_Form!N84)/(DR_Form!N79),"-") -> -
B17: Rentab. Exploração das vendas | C17: =C7/C4 -> #DIV/0! | D17: =D7/D4 -> #DIV/0! | E17: =E7/E4 -> 0.013536826 | F17: =F7/F4 -> 0.0089999446 | G17: =G7/G4 -> 0.017348687 | H17: =H7/H4 -> 0.015131906 | I17: =I7/I4 -> 0.016872858 | J17: =J7/J4 -> 0.016898249 | ... M17: =M7/M4 -> 0.015945819
B18: Rentab. Capitais Próprios | C18: =DR_Form!B107/Balanço_Form!B186 -> #DIV/0! | D18: =DR_Form!C107/Balanço_Form!C186 -> #DIV/0! | E18: =DR_Form!D107/Balanço_Form!D186 -> 0.052979047 | F18: =DR_Form!E107/Balanço_Form!E186 -> 0.038640481 | G18: =DR_Form!F107/Balanço_Form!F186 -> 0.06544288 | H18: =DR_Form!G107/Balanço_Form!G186 -> 0.053829956 | I18: =DR_Form!H107/Balanço_Form!H186 -> 0.063447523 | J18: =DR_Form!I107/Balanço_Form!I186 -> 0.061274746 | ... M18: =DR_Form!L107/Balanço_Form!L186 -> 0.05952657
B19: Rentab. Econ. Ativo | C19: =C7/C9 -> #DIV/0! | D19: =D7/D9 -> #DIV/0! | E19: =E7/E9 -> 0.01555677 | F19: =F7/F9 -> 0.010571494 | G19: =G7/G9 -> 0.019659877 | H19: =H7/H9 -> 0.016941263 | I19: =I7/I9 -> 0.018808794 | J19: =J7/J9 -> 0.018415562 | ... M19: =M7/M9 -> 0.016302269
B20: Rentab. Economica | C20: =DR_Form!B107/Balanço_Form!B207 -> #DIV/0! | D20: =DR_Form!C107/Balanço_Form!C207 -> #DIV/0! | E20: =DR_Form!D107/Balanço_Form!D207 -> 0.019817057 | F20: =DR_Form!E107/Balanço_Form!E207 -> 0.014907568 | G20: =DR_Form!F107/Balanço_Form!F207 -> 0.027058226 | H20: =DR_Form!G107/Balanço_Form!G207 -> 0.022803133 | I20: =DR_Form!H107/Balanço_Form!H207 -> 0.027142558 | J20: =DR_Form!I107/Balanço_Form!I207 -> 0.026921688 | ... M20: =DR_Form!L107/Balanço_Form!L207 -> 0.028250046
B21: Rentab. Vendas | C21: =DR_Form!B107/DR_Form!B79 -> #DIV/0! | D21: =DR_Form!C107/DR_Form!C79 -> #DIV/0! | E21: =DR_Form!D107/DR_Form!D79 -> 0.0091548429 | F21: =DR_Form!E107/DR_Form!E79 -> 0.006706606 | G21: =DR_Form!F107/DR_Form!F79 -> 0.012630787 | H21: =DR_Form!G107/DR_Form!G79 -> 0.010683155 | I21: =DR_Form!H107/DR_Form!H79 -> 0.012677902 | J21: =DR_Form!I107/DR_Form!I79 -> 0.01278595 | ... M21: =DR_Form!L107/DR_Form!L79 -> 0.014170137
B22: Rotação Ativo Total | C22: =C4/C9 -> #DIV/0! | D22: =D4/D9 -> #DIV/0! | E22: =E4/E9 -> 1.1492184 | F22: =F4/F9 -> 1.1746177 | G22: =G4/G9 -> 1.1332198 | H22: =H4/H9 -> 1.1195723 | I22: =I4/I9 -> 1.1147367 | J22: =J4/J9 -> 1.0897911 | ... M22: =M4/M9 -> 1.0223539
B23: Rotação Ativo Fixo | C23: =C4/Balanço_Form!B145 -> #DIV/0! | D23: =D4/Balanço_Form!C145 -> #DIV/0! | E23: =E4/Balanço_Form!D145 -> 18.594603 | F23: =F4/Balanço_Form!E145 -> 20.653608 | G23: =G4/Balanço_Form!F145 -> 19.546826 | H23: =H4/Balanço_Form!G145 -> 22.835277 | I23: =I4/Balanço_Form!H145 -> 26.955145 | J23: =J4/Balanço_Form!I145 -> 31.00258 | ... M23: =M4/Balanço_Form!L145 -> 39.905856
B24: Rotação Ativo Circulante | C24: =C4/Balanço_Form!B157 -> #DIV/0! | D24: =D4/Balanço_Form!C157 -> #DIV/0! | E24: =E4/Balanço_Form!D157 -> 2.4498469 | F24: =F4/Balanço_Form!E157 -> 2.4908984 | G24: =G4/Balanço_Form!F157 -> 2.4059221 | H24: =H4/Balanço_Form!G157 -> 2.3545858 | I24: =I4/Balanço_Form!H157 -> 2.3256513 | J24: =J4/Balanço_Form!I157 -> 2.2589894 | ... M24: =M4/Balanço_Form!L157 -> 2.0984687
B25: PMR | C25: =Balanço!C88 -> #DIV/0! | D25: =Balanço!D88 -> #DIV/0! | E25: =Balanço!E88 -> 78.433107 | F25: =Pressupostos!$C$42 -> 90 | G25: =Pressupostos!$C$42 -> 90 | H25: =Pressupostos!$C$42 -> 90 | I25: =Pressupostos!$C$42 -> 90 | J25: =Pressupostos!$C$42 -> 90 | K25: =Pressupostos!$C$42 -> 90 | L25: =Pressupostos!$C$42 -> 90 | M25: =Pressupostos!$C$42 -> 90
B26: PMP | C26: =Balanço!C89 -> #DIV/0! | D26: =Balanço!D89 -> #DIV/0! | E26: =Balanço!E89 -> 78.686925 | F26: =Pressupostos!$C$43 -> 60 | G26: =Pressupostos!$C$43 -> 60 | H26: =Pressupostos!$C$43 -> 60 | I26: =Pressupostos!$C$43 -> 60 | J26: =Pressupostos!$C$43 -> 60 | K26: =Pressupostos!$C$43 -> 60 | L26: =Pressupostos!$C$43 -> 60 | M26: =Pressupostos!$C$43 -> 60
B27: Rotação Existências | C27: =Balanço!C90 -> 0 | D27: =Balanço!D90 -> 0 | E27: =Balanço!E90 -> 0 | F27: =Pressupostos!C44 -> 30 | G27: =Pressupostos!D44 -> 0 | H27: =Pressupostos!E44 -> 0 | I27: =Pressupostos!F44 -> 0 | J27: =Pressupostos!G44 -> 0 | K27: =Pressupostos!H44 -> 0 | L27: =Pressupostos!I44 -> 0 | M27: =Pressupostos!J44 -> 0
B29: ANALISE FINANCEIRA
C30: =C15 -> 2017 | D30: =D15 -> 2018 | E30: =E15 -> 2019 | F30: =F15 -> 2020 | G30: =G15 -> 2021 | H30: =H15 -> 2022 | I30: =I15 -> 2023 | J30: =J15 -> 2024 | ... O30: =O15 -> 2029
B31: Autonomia Financeira | C31: =Balanço_Form!B186/Balanço_Form!B171 -> #DIV/0! | D31: =Balanço_Form!C186/Balanço_Form!C171 -> #DIV/0! | E31: =Balanço_Form!D186/Balanço_Form!D171 -> 0.37405462 | F31: =Balanço_Form!E186/Balanço_Form!E171 -> 0.38580183 | G31: =Balanço_Form!F186/Balanço_Form!F171 -> 0.41346324 | H31: =Balanço_Form!G186/Balanço_Form!G171 -> 0.42361419 | I31: =Balanço_Form!H186/Balanço_Form!H171 -> 0.42779539 | J31: =Balanço_Form!I186/Balanço_Form!I171 -> 0.43936025 | ... M31: =Balanço_Form!L186/Balanço_Form!L171 -> 0.47457877
B32: Grau de dependencia | C32: =Balanço_Form!B206/Balanço_Form!B207 -> #DIV/0! | D32: =Balanço_Form!C206/Balanço_Form!C207 -> #DIV/0! | E32: =Balanço_Form!D206/Balanço_Form!D207 -> 0.62594538 | F32: =Balanço_Form!E206/Balanço_Form!E207 -> 0.61419817 | G32: =Balanço_Form!F206/Balanço_Form!F207 -> 0.58653676 | H32: =Balanço_Form!G206/Balanço_Form!G207 -> 0.57638581 | I32: =Balanço_Form!H206/Balanço_Form!H207 -> 0.57220461 | J32: =Balanço_Form!I206/Balanço_Form!I207 -> 0.56063975 | ... M32: =Balanço_Form!L206/Balanço_Form!L207 -> 0.52542123
B33: Coefic Financ do Ativo Fixo | C33: =(Balanço_Form!B186+Balanço_Form!B188)/Balanço_Form!B145 -> #DIV/0! | D33: =(Balanço_Form!C186+Balanço_Form!C188)/Balanço_Form!C145 -> #DIV/0! | E33: =(Balanço_Form!D186+Balanço_Form!D188)/Balanço_Form!D145 -> 3.2131697 | F33: =(Balanço_Form!E186+Balanço_Form!E188)/Balanço_Form!E145 -> 3.5847279 | G33: =(Balanço_Form!F186+Balanço_Form!F188)/Balanço_Form!F145 -> 3.7726302 | H33: =(Balanço_Form!G186+Balanço_Form!G188)/Balanço_Form!G145 -> 4.5319154 | I33: =(Balanço_Form!H186+Balanço_Form!H188)/Balanço_Form!H145 -> 5.3860996 | J33: =(Balanço_Form!I186+Balanço_Form!I188)/Balanço_Form!I145 -> 6.4691811 | ... M33: =(Balanço_Form!L186+Balanço_Form!L188)/Balanço_Form!L145 -> 9.4994797
B34: Solvabilidade | C34: =Balanço_Form!B186/Balanço_Form!B206 -> #DIV/0! | D34: =Balanço_Form!C186/Balanço_Form!C206 -> #DIV/0! | E34: =Balanço_Form!D186/Balanço_Form!D206 -> 0.59758349 | F34: =Balanço_Form!E186/Balanço_Form!E206 -> 0.628139 | G34: =Balanço_Form!F186/Balanço_Form!F206 -> 0.70492299 | H34: =Balanço_Form!G186/Balanço_Form!G206 -> 0.73494902 | I34: =Balanço_Form!H186/Balanço_Form!H206 -> 0.7476266 | J34: =Balanço_Form!I186/Balanço_Form!I206 -> 0.7836766 | ... M34: =Balanço_Form!L186/Balanço_Form!L206 -> 0.90323486
B35: Custo médio do passivo | C35: =DR_Form!B104/Balanço_Form!B206 -> #DIV/0! | D35: =DR_Form!C104/Balanço_Form!C206 -> #DIV/0! | E35: =DR_Form!D104/Balanço_Form!D206 -> 0.0010465485 | F35: =DR_Form!E104/Balanço_Form!E206 -> 0.011447718 | G35: =DR_Form!F104/Balanço_Form!F206 -> 0.010879743 | H35: =DR_Form!G104/Balanço_Form!G206 -> 0.010347539 | I35: =DR_Form!H104/Balanço_Form!H206 -> 0.0098063036 | J35: =DR_Form!I104/Balanço_Form!I206 -> 0.0095982671 | ... M35: =DR_Form!L104/Balanço_Form!L206 -> 0.0090987384
B36: Liquidez Imediata | C36: =Balanço_Form!B170/Balanço_Form!B194 -> #DIV/0! | D36: =Balanço_Form!C170/Balanço_Form!C194 -> #DIV/0! | E36: =Balanço_Form!D170/Balanço_Form!D194 -> 0.21448322 | F36: =Balanço_Form!E170/Balanço_Form!E194 -> 0.023097395 | G36: =Balanço_Form!F170/Balanço_Form!F194 -> 0.079716382 | H36: =Balanço_Form!G170/Balanço_Form!G194 -> 0.12034405 | I36: =Balanço_Form!H170/Balanço_Form!H194 -> 0.14556556 | J36: =Balanço_Form!I170/Balanço_Form!I194 -> 0.19514367 | ... M36: =Balanço_Form!L170/Balanço_Form!L194 -> 0.32964498
B37: Liquidez reduzida | C37: =(Balanço_Form!B157-Balanço_Form!B158)/Balanço_Form!B194 -> #DIV/0! | D37: =(Balanço_Form!C157-Balanço_Form!C158)/Balanço_Form!C194 -> #DIV/0! | E37: =(Balanço_Form!D157-Balanço_Form!D158)/Balanço_Form!D194 -> 1.0700786 | F37: =(Balanço_Form!E157-Balanço_Form!E158)/Balanço_Form!E194 -> 1.2161659 | G37: =(Balanço_Form!F157-Balanço_Form!F158)/Balanço_Form!F194 -> 1.2791459 | H37: =(Balanço_Form!G157-Balanço_Form!G158)/Balanço_Form!G194 -> 1.3320667 | I37: =(Balanço_Form!H157-Balanço_Form!H158)/Balanço_Form!H194 -> 1.3656189 | J37: =(Balanço_Form!I157-Balanço_Form!I158)/Balanço_Form!I194 -> 1.4184192 | ... M37: =(Balanço_Form!L157-Balanço_Form!L158)/Balanço_Form!L194 -> 1.5615195
B38: Liquidez geral | C38: =Balanço_Form!B157/Balanço_Form!B194 -> #DIV/0! | D38: =Balanço_Form!C157/Balanço_Form!C194 -> #DIV/0! | E38: =Balanço_Form!D157/Balanço_Form!D194 -> 1.4116041 | F38: =Balanço_Form!E157/Balanço_Form!E194 -> 1.4529126 | G38: =Balanço_Form!F157/Balanço_Form!F194 -> 1.5180711 | H38: =Balanço_Form!G157/Balanço_Form!G194 -> 1.5727772 | I38: =Balanço_Form!H157/Balanço_Form!H194 -> 1.6088199 | J38: =Balanço_Form!I157/Balanço_Form!I194 -> 1.6625366 | ... M38: =Balanço_Form!L157/Balanço_Form!L194 -> 1.8081523
B39: CF/Vendas | C39: =C6/C4 -> #DIV/0! | D39: =D6/D4 -> #DIV/0! | E39: =E6/E4 -> 0 | F39: =F6/F4 -> 0 | G39: =G6/G4 -> 0 | H39: =H6/H4 -> 0 | I39: =I6/I4 -> 0 | J39: =J6/J4 -> 0 | ... M39: =M6/M4 -> 0
B41: OUTROS DADOS
C42: =C30 -> 2017 | D42: =D30 -> 2018 | E42: =E30 -> 2019 | F42: =F30 -> 2020 | G42: =G30 -> 2021 | H42: =H30 -> 2022 | I42: =I30 -> 2023 | J42: =J30 -> 2024 | ... O42: =O30 -> 2029
B43: Alavancagem Operacional
B44: Alavancagem Financeira
B45: Grau Combinada Alavanca
B46: Margem Contribuição | C46: =C4-DR_Form!B84-DR_Form!B85 -> 0 | D46: =D4-DR_Form!C84-DR_Form!C85 -> 0 | E46: =E4-DR_Form!D84-DR_Form!D85 -> 192158.13 | F46: =F4-DR_Form!E84-DR_Form!E85 -> 260883.48 | G46: =G4-DR_Form!F84-DR_Form!F85 -> 294723.32 | H46: =H4-DR_Form!G84-DR_Form!G85 -> 337953.88 | I46: =I4-DR_Form!H84-DR_Form!H85 -> 374095.48 | J46: =J4-DR_Form!I84-DR_Form!I85 -> 381614.81 | ... M46: =M4-DR_Form!L84-DR_Form!L85 -> 405091.81
B47: Resultado Operacional
B48: Resultado Corrente
B49: MS
B50: Cfixos
B51: ML/CP
B52: ML/Volume de Negócios
B53: VAB/Investimento Elegível)
B55: ANÁLISE DA ESTRUTURA DO BALANÇO
C56: =C42 -> 2017 | D56: =D42 -> 2018 | E56: =E42 -> 2019 | F56: =F42 -> 2020 | G56: =G42 -> 2021 | H56: =H42 -> 2022 | I56: =I42 -> 2023 | J56: =J42 -> 2024 | ... O56: =O42 -> 2029
B57: Imobilizado
B58: Ativo Circulante
B59: Capital Próprio
B60: Exígivel a MLP
B61: Exígivel a CP
B63: ANÁLISE DO VOLUME DE NEGÓCIOS E RESULTADOS
C64: =C56 -> 2017 | D64: =D56 -> 2018 | E64: =E56 -> 2019 | F64: =F56 -> 2020 | G64: =G56 -> 2021 | H64: =H56 -> 2022 | I64: =I56 -> 2023 | J64: =J56 -> 2024 | ... O64: =O56 -> 2029
B65: Volume de Negócios | C65: =C4 -> 0 | D65: =D4 -> 0 | E65: =E4 -> 3479532.1 | F65: =F4 -> 3690043.8 | G65: =G4 -> 3913291.5 | H65: =H4 -> 4150045.6 | I65: =I4 -> 4401123.4 | J65: =J4 -> 4489586 | ... O65: =O4 -> -
B66: Resultado Operacional
B67: Resultado antes de juros e impostos
B68: Resultado Líquido
B70: ANÁLISE ECONÓMICA-FINANCEIRA
C71: =C64 -> 2017 | D71: =D64 -> 2018 | E71: =E64 -> 2019 | F71: =F64 -> 2020 | G71: =G64 -> 2021 | H71: =H64 -> 2022 | I71: =I64 -> 2023 | J71: =J64 -> 2024 | ... O71: =O64 -> 2029
B72: Taxa de Crescimento do negócio
B73: VAB
B74: Produtividade do Trabalho
B75: Rendibilidade do Activo
B76: Rotação do Activo
B77: Solvabilidade
B78: Liquidez geral
B79: Liquidez reduzida
B80: Fundo Maneio
B81: Meios Libertos
B82: Grau de Alavanca Operacional
B83: Margem Económica
... B88: AUTONOMIA FINANCEIRA
C89: =C71 -> 2017 | D89: =D71 -> 2018 | E89: =E71 -> 2019 | F89: =F71 -> 2020 | G89: =G71 -> 2021 | H89: =H71 -> 2022 | I89: =I71 -> 2023 | J89: =J71 -> 2024 | ... O89: =O71 -> 2029
B90: Autonomia Financeira
B91: Resultado Operacional
B92: Rentabilidade de Exploração
B94: RENDIBILIDADE FINANCEIRA
C95: =C89 -> 2017 | D95: =D89 -> 2018 | E95: =E89 -> 2019 | F95: =F89 -> 2020 | G95: =G89 -> 2021 | H95: =H89 -> 2022 | I95: =I89 -> 2023 | J95: =J89 -> 2024 | ... O95: =O89 -> 2029
B96: Rentabilidade dos Capitais Próprios
B97: Meios Libertos/Capitais Próprios
B99: ANÁLISE DO RISCO ECONÓMICO
C100: =C95 -> 2017 | D100: =D95 -> 2018 | E100: =E95 -> 2019 | F100: =F95 -> 2020 | G100: =G95 -> 2021 | H100: =H95 -> 2022 | I100: =I95 -> 2023 | J100: =J95 -> 2024 | ... O100: =O95 -> 2029
B101: BEP
B102: Margem de Segurança
B103: EBITDA | C103: =DR_Form!B99 -> 0 | D103: =DR_Form!C99 -> 0 | E103: =DR_Form!D99 -> 58598.69 | F103: =DR_Form!E99 -> 52067.25 | G103: =DR_Form!F99 -> 93897.53 | H103: =DR_Form!G99 -> 87265.73 | I103: =DR_Form!H99 -> 101993.65 | J103: =DR_Form!I99 -> 104005.69 | ... M103: =DR_Form!L99 -> 107028.6
B104: EBITDA (económico)
B105: EBITDA (financeiro)
B106: Autonomia Financeira
B107: Cobertura do Imobilizado
B108: Liquidez Geral

Sheet EstruturaFinanciamento
A1: MAPA DE FINANCIAMENTO - INTERNACIONALIZAÇÃO
A2: Rubricas | B2: =Pressupostos!C11 -> 2020 | C2: =B2+1 -> 2021 | D2: =C2+1 -> 2022 | E2: =D2+1 -> 2023 | F2: =E2+1 -> 2024 | G2: =F2+1 -> 2025
A3: Capitais Próprios (1)
A4: Capital | B4: =IF(Faturas!G325=0,"",Faturas!G325) -> 2062.525 | C4: =IF(Faturas!G326=0,"",Faturas!G326) -> 5834 | D4: =IF(Faturas!G327=0,"",Faturas!G327) -> 1480 | E4: =IF(Faturas!G328=0,"",Faturas!G328) | I4: =SUM(B4:G4) -> 9376.525
A5: Prestações Suplementares Capital | B5: =IF(Faturas!H325=0,"",Faturas!H325) -> 4125.05 | C5: =IF(Faturas!H326=0,"",Faturas!H326) -> 11668 | D5: =IF(Faturas!H327=0,"",Faturas!H327) -> 2960 | E5: =IF(Faturas!H328=0,"",Faturas!H328) | I5: =SUM(B5:G5) -> 18753.05
A6: Autofinanciamento (2) | B6: =IF(Faturas!F325=0,"",Faturas!F325) | C6: =IF(Faturas!F326=0,"",Faturas!F326) | D6: =IF(Faturas!F237=0,"",Faturas!F327) -> 0 | E6: =IF(Faturas!F328=0,"",Faturas!F328) | I6: =SUM(B6:G6) -> 0
A7: Financiamentos | I7: =SUM(B7:G7) -> 0
A8: Financiamento de Instituições de Crédito | I8: =SUM(B8:G8) -> 0
A9: Empréstimos por Obrigações | I9: =SUM(B9:G9) -> 0
A10: Financiamento de Sócios/Acionistas | I10: =SUM(B10:G10) -> 0
A11: Suprimentos Consolidados (3) | I11: =SUM(B11:G11) -> 0
A12: Outras dívidas a Sócios/Acionistas | B12: =IF(Faturas!I325=0,"",Faturas!I325) -> 5156.3125 | C12: =IF(Faturas!I326=0,"",Faturas!I326) -> 14585 | D12: =IF(Faturas!I327=0,"",Faturas!I327) -> 3700 | E12: =IF(Faturas!I328=0,"",Faturas!I328) | I12: =SUM(B12:G12) -> 23441.312
A13: Fornecedores de Investimentos | I13: =SUM(B13:G13) -> 0
A14: Locação Financeira | I14: =SUM(B14:G14) -> 0
A15: Incentivo | I15: =SUM(B15:G15) -> 0
A16: Não Reembolsável (INR) | B16: =IF(Faturas!E325=0,"",Faturas!E325) -> 9281.3625 | C16: =IF(Faturas!E326=0,"",Faturas!E326) -> 26253 | D16: =IF(Faturas!E327=0,"",Faturas!E327) -> 6660 | E16: =IF(Faturas!E328=0,"",Faturas!E328) | I16: =SUM(B16:G16) -> 42194.363
A17: Outros
A18: FINANCIAMENTO TOTAL | I18: =SUM(I4:I17) -> 93765.25
A19: INVESTIMENTO TOTAL | I19: =Faturas!D329 -> 93765.25
A20: INVESTIMENTO ELEGÍVEL TOTAL
A23: MAPA DE FINANCIAMENTO - INOVAÇÃO
A24: Rubricas | B24: =Pressupostos!C33 -> 0.0665 | C24: =B24+1 -> 1.0665 | D24: =C24+1 -> 2.0665 | E24: =D24+1 -> 3.0665 | F24: =E24+1 -> 4.0665 | G24: =F24+1 -> 5.0665
A25: Capitais Próprios (1)
A26: Capital
A27: Prestações Suplementares Capital
A28: Autofinanciamento (2)
A29: Financiamentos
A30: Financiamento de Instituições de Crédito
A31: Empréstimos por Obrigações
A32: Financiamento de Sócios/Acionistas
A33: Suprimentos Consolidados (3)
A34: Outras dívidas a Sócios/Acionistas
A35: Fornecedores de Investimentos
A36: Locação Financeira
... A42: INVESTIMENTO ELEGÍVEL TOTAL

Sheet DR Empresa
B2: DEMONSTRAÇÃO DE RESULTADOS DO PROMOTOR
B3: DEMONSTRAÇÃO DOS RESULTADOS POR NATUREZAS
B4: RÚBRICAS | C4: =Pressupostos!C11 -> 2020 | D4: =C4+1 -> 2021 | E4: =D4+1 -> 2022 | F4: =E4+1 -> 2023 | G4: =F4+1 -> 2024 | H4: =G4+1 -> 2025 | I4: =H4+1 -> 2026 | J4: =I4+1 -> 2027 | K4: =J4+1 -> 2028 | L4: =K4+1 -> 2029
B5: Vendas e serviços prestados | C5: =C35+C38 -> 3690043.8 | D5: =D35+D38 -> 3913291.5 | E5: =E35+E38 -> 4150045.6 | F5: =F35+F38 -> 4401123.4 | G5: =G35+G38 -> 4489586 | H5: =H35+H38 -> 4579826.6 | I5: =I35+I38 -> 4671881.2 | J5: =J35+J38 -> 4765786 | ... L5: =L35+L38 -> 4959296
B6: Subsídios à exploração | C6: =Faturas!E340 -> 9281.3625 | D6: =Faturas!E341 -> 26253 | E6: =Faturas!E342 -> 6660 | F6: =Faturas!E343 -> 0 | G6: 0 | H6: 0 | I6: 0 | J6: 0 | K6: 0 | L6: 0
B7: Ganhos/perdas imputados de subsidiárias, associadas e empreendimentos conjuntos | C7: 0 | D7: 0 | E7: 0 | F7: 0 | G7: 0 | H7: 0 | I7: 0 | J7: 0 | K7: 0 | L7: 0
B8: Variação nos inventários da produção | C8: 0 | D8: 0 | E8: 0 | F8: 0 | G8: 0 | H8: 0 | I8: 0 | J8: 0 | K8: 0 | L8: 0
B9: Trabalhos para a própria entidade | C9: 0 | D9: 0 | E9: 0 | F9: 0 | G9: 0 | H9: 0 | I9: 0 | J9: 0 | K9: 0 | L9: 0
B10: Custo das mercadorias vendidas e das matérias consumidas | C10: =CMVMC!D6 -> 2896684.4 | D10: =CMVMC!E6 -> 3071933.8 | E10: =CMVMC!F6 -> 3237035.6 | F10: =CMVMC!G6 -> 3432876.2 | G10: =CMVMC!H6 -> 3501877 | H10: =CMVMC!I6 -> 3572264.8 | I10: =CMVMC!J6 -> 3644067.3 | J10: =CMVMC!K6 -> 3717313.1 | ... L10: =CMVMC!M6 -> 3868250.9
B11: Fornecimentos e serviços externos | C11: =FSE!D6 -> 532475.94 | D11: =FSE!E6 -> 546634.35 | E11: =FSE!F6 -> 575056.16 | F11: =FSE!G6 -> 594151.66 | G11: =FSE!H6 -> 606094.1 | H11: =FSE!I6 -> 618276.6 | I11: =FSE!J6 -> 630703.96 | J11: =FSE!K6 -> 643381.11 | ... L11: =FSE!M6 -> 669504.96
B12: Gastos com o pessoal | C12: =RH!D6 -> 218097.59 | D12: =RH!E6 -> 254274.54 | E12: =RH!F6 -> 269965.03 | F12: =RH!G6 -> 275364.33 | G12: =RH!H6 -> 280871.62 | H12: =RH!I6 -> 286489.05 | I12: =RH!J6 -> 292218.83 | J12: =RH!K6 -> 298063.21 | ... L12: =RH!M6 -> 310104.96
B13: Imparidade de inventários (perdas/reversões) | C13: 0 | D13: 0 | E13: 0 | F13: 0 | G13: 0 | H13: 0 | I13: 0 | J13: 0 | K13: 0 | L13: 0
B14: Imparidade de dívidas a receber (perdas/reversões) | C14: 0 | D14: 0 | E14: 0 | F14: 0 | G14: 0 | H14: 0 | I14: 0 | J14: 0 | K14: 0 | L14: 0
B15: Provisões (aumentos/reduções) | C15: 0 | D15: 0 | E15: 0 | F15: 0 | G15: 0 | H15: 0 | I15: 0 | J15: 0 | K15: 0 | L15: 0
B16: Imparidade de investimentos não depreciáveis/amortizáveis (perdas/reversões) | C16: 0 | D16: 0 | E16: 0 | F16: 0 | G16: 0 | H16: 0 | I16: 0 | J16: 0 | K16: 0 | L16: 0
B17: Outras imparidades (perdas/reversões)/Imparidades | C17: 0 | D17: 0 | E17: 0 | F17: 0 | G17: 0 | H17: 0 | I17: 0 | J17: 0 | K17: 0 | L17: 0
B18: Aumentos/reduções de justo valor | C18: 0 | D18: 0 | E18: 0 | F18: 0 | G18: 0 | H18: 0 | I18: 0 | J18: 0 | K18: 0 | L18: 0
B19: Outros rendimentos e ganhos | C19: 0 | D19: =+[2]Folha1!F61 -> 27195.75 | E19: =+[2]Folha1!G61 -> 12616.875 | F19: =+[2]Folha1!H61 -> 3262.5 | G19: =+[2]Folha1!I61 -> 3262.5 | H19: 0 | I19: 0 | J19: 0 | K19: 0 | L19: 0
B20: Outros gastos e perdas | C20: 0 | D20: 0 | E20: 0 | F20: 0 | G20: 0 | H20: 0 | I20: 0 | J20: 0 | K20: 0 | L20: 0
B21: Resultado antes de depreciações, gastos de financiamento e impostos | C21: =C5+C6+C7+C8+C9-C10-C11-C12-C13-C14-C15-C16-C17+C18+C19-C20 -> 52067.259 | D21: =D5+D6+D7+D8+D9-D10-D11-D12-D13-D14-D15-D16-D17+D18+D19-D20 -> 93897.528 | E21: =E5+E6+E7+E8+E9-E10-E11-E12-E13-E14-E15-E16-E17+E18+E19-E20 -> 87265.721 | F21: =F5+F6+F7+F8+F9-F10-F11-F12-F13-F14-F15-F16-F17+F18+F19-F20 -> 101993.65 | G21: =G5+G6+G7+G8+G9-G10-G11-G12-G13-G14-G15-G16-G17+G18+G19-G20 -> 104005.69 | H21: =H5+H6+H7+H8+H9-H10-H11-H12-H13-H14-H15-H16-H17+H18+H19-H20 -> 102796.21 | I21: =I5+I6+I7+I8+I9-I10-I11-I12-I13-I14-I15-I16-I17+I18+I19-I20 -> 104891.07 | J21: =J5+J6+J7+J8+J9-J10-J11-J12-J13-J14-J15-J16-J17+J18+J19-J20 -> 107028.6 | ... L21: =L5+L6+L7+L8+L9-L10-L11-L12-L13-L14-L15-L16-L17+L18+L19-L20 -> 111435.2
B22: Gastos/reversões de depreciação e de amortização | C22: =Amortização!E108-Amortização!D108 -> 8462.524 | D22: =Amortização!F108-Amortização!E108 -> 18462.524 | E22: =Amortização!G108-Amortização!F108 -> 18462.524 | F22: =Amortização!H108-Amortização!G108 -> 18462.524 | G22: =Amortização!I108-Amortização!H108 -> 18462.524 | H22: =Amortização!J108-Amortização!I108 -> 8462.524 | I22: =Amortização!K108-Amortização!J108 -> 8462.524 | J22: =Amortização!L108-Amortização!K108 -> 8462.524 | ... L22: =Amortização!N108-Amortização!M108 -> 8462.524
B23: Imparidade de investimentos depreciáveis/amortizáveis | C23: 0 | D23: 0 | E23: 0 | F23: 0 | G23: 0 | H23: 0 | I23: 0 | J23: 0 | K23: 0 | L23: 0
B24: Resultado operacional (antes de gastos de financiamento e impostos) | C24: =C21-C22-C23 -> 43604.735 | D24: =D21-D22-D23 -> 75435.004 | E24: =E21-E22-E23 -> 68803.197 | F24: =F21-F22-F23 -> 83531.131 | G24: =G21-G22-G23 -> 85543.163 | H24: =H21-H22-H23 -> 94333.688 | I24: =I21-I22-I23 -> 96428.541 | J24: =J21-J22-J23 -> 98566.074 | ... L24: =L21-L22-L23 -> 102972.67
B25: Juros e rendimentos similares obtidos | C25: =DR!F26*(1+Pressupostos!C17) -> 0 | D25: =DR!G26*(1+Pressupostos!D17) -> 0 | E25: =DR!H26*(1+Pressupostos!E17) -> 0 | F25: =DR!I26*(1+Pressupostos!F17) -> 0 | G25: =DR!J26*(1+Pressupostos!G17) -> 0 | H25: =DR!K26*(1+Pressupostos!H17) -> 0 | I25: =DR!L26*(1+Pressupostos!I17) -> 0 | J25: =DR!M26*(1+Pressupostos!J17) -> 0 | ... L25: =DR!O26*(1+Pressupostos!L17) -> 0
B26: Juros e gastos similares suportados | C26: =SaldosDivida!B72+SaldosDivida!B99+SaldosDivida!B86+SaldosDivida!B104+JurosSocios!I29 -> 11672.263 | D26: =SaldosDivida!C72+SaldosDivida!C99+SaldosDivida!C86+SaldosDivida!C104+JurosSocios!I30 -> 11657.01 | E26: =SaldosDivida!D72+SaldosDivida!D99+SaldosDivida!D86+SaldosDivida!D104+JurosSocios!I31 -> 11595.996 | F26: =SaldosDivida!E72+SaldosDivida!E99+SaldosDivida!E86+SaldosDivida!E104+JurosSocios!I32 -> 11534.983 | G26: =SaldosDivida!F72+SaldosDivida!F99+SaldosDivida!F86+SaldosDivida!F104+JurosSocios!I33 -> 11473.97 | H26: =SaldosDivida!G72+SaldosDivida!G99+SaldosDivida!G86+SaldosDivida!G104+JurosSocios!I34 -> 11428.21 | I26: =SaldosDivida!H72+SaldosDivida!H99+SaldosDivida!H86+SaldosDivida!H104+JurosSocios!I35 -> 11428.21 | J26: =SaldosDivida!I72+SaldosDivida!I99+SaldosDivida!I86+SaldosDivida!I104 -> 11428.21 | K26: =SaldosDivida!J72+SaldosDivida!J99+SaldosDivida!J86+SaldosDivida!J104 -> 0 | L26: =SaldosDivida!K72+SaldosDivida!K99+SaldosDivida!K86+SaldosDivida!K104 -> 0
B27: Resultado antes de impostos | C27: =C24+C25-C26 -> 31932.472 | D27: =D24+D25-D26 -> 63777.994 | E27: =E24+E25-E26 -> 57207.2 | F27: =F24+F25-F26 -> 71996.148 | G27: =G24+G25-G26 -> 74069.194 | H27: =H24+H25-H26 -> 82905.479 | I27: =I24+I25-I26 -> 85000.332 | J27: =J24+J25-J26 -> 87137.864 | ... L27: =L24+L25-L26 -> 102972.67
B28: Imposto sobre o rendimento do período | C28: =MAX(0,C27*Pressupostos!$C$39) -> 7184.8061 | D28: =MAX(0,D27*Pressupostos!$C$39) -> 14350.049 | E28: =MAX(0,E27*Pressupostos!$C$39) -> 12871.62 | F28: =MAX(0,F27*Pressupostos!$C$39) -> 16199.133 | G28: =MAX(0,G27*Pressupostos!$C$39) -> 16665.569 | H28: =MAX(0,H27*Pressupostos!$C$39) -> 18653.733 | I28: =MAX(0,I27*Pressupostos!$C$39) -> 19125.075 | J28: =MAX(0,J27*Pressupostos!$C$39) -> 19606.019 | ... L28: =MAX(0,L27*Pressupostos!$C$39) -> 23168.851
B29: Resultado líquido do período | C29: =C27-C28 -> 24747.666 | D29: =D27-D28 -> 49427.945 | E29: =E27-E28 -> 44335.58 | F29: =F27-F28 -> 55797.014 | G29: =G27-G28 -> 57403.625 | H29: =H27-H28 -> 64251.746 | I29: =I27-I28 -> 65875.257 | J29: =J27-J28 -> 67531.844 | ... L29: =L27-L28 -> 79803.821
B31: Compras | C31: =FM!H43 -> 2794444 | D31: =FM!I43 -> 3086537.9 | E31: =FM!J43 -> 3250794.1 | F31: =FM!K43 -> 3449196.3 | G31: =FM!L43 -> 3507627.1 | H31: =FM!M43 -> 3578130.4 | I31: =FM!N43 -> 3650050.8 | J31: =FM!O43 -> 3723416.9 | ... L31: =FM!Q43 -> 3874602.5
B33: Meios Libertos | C33: =C29+C22+C23+(C15-DR!F16) -> 33210.19 | D33: =D29+D22+D23+(D15-C15) -> 67890.469 | E33: =E29+E22+E23+(E15-D15) -> 62798.104 | F33: =F29+F22+F23+(F15-E15) -> 74259.538 | G33: =G29+G22+G23+(G15-F15) -> 75866.149 | H33: =H29+H22+H23+(H15-G15) -> 72714.27 | I33: =I29+I22+I23+(I15-H15) -> 74337.781 | J33: =J29+J22+J23+(J15-I15) -> 75994.368 | K33: =K29+K22+K23+(K15-J15) -> 86541.569 | L33: =L29+L22+L23+(L15-K15) -> 88266.345
B35: Vendas | C35: =C36+C37 -> 0 | D35: =D36+D37 -> 0 | E35: =E36+E37 -> 0 | F35: =F36+F37 -> 0 | G35: =G36+G37 -> 0 | H35: =H36+H37 -> 0 | I35: =I36+I37 -> 0 | J35: =J36+J37 -> 0 | ... L35: =L36+L37 -> 0
B36: Produtos | C36: ='Vendas+PrestServ'!D8 -> 0 | D36: ='Vendas+PrestServ'!E8 -> 0 | E36: ='Vendas+PrestServ'!F8 -> 0 | F36: ='Vendas+PrestServ'!G8 -> 0 | G36: ='Vendas+PrestServ'!H8 -> 0 | H36: ='Vendas+PrestServ'!I8 -> 0 | I36: ='Vendas+PrestServ'!J8 -> 0 | J36: ='Vendas+PrestServ'!K8 -> 0 | ... L36: ='Vendas+PrestServ'!M8 -> 0
B37: Mercadorias | C37: ='Vendas+PrestServ'!D16 -> 0 | D37: ='Vendas+PrestServ'!E16 -> 0 | E37: ='Vendas+PrestServ'!F16 -> 0 | F37: ='Vendas+PrestServ'!G16 -> 0 | G37: ='Vendas+PrestServ'!H16 -> 0 | H37: ='Vendas+PrestServ'!I16 -> 0 | I37: ='Vendas+PrestServ'!J16 -> 0 | J37: ='Vendas+PrestServ'!K16 -> 0 | ... L37: ='Vendas+PrestServ'!M16 -> 0
B38: Prestação de Serviços | C38: ='Vendas+PrestServ'!D27 -> 3690043.8 | D38: ='Vendas+PrestServ'!E27 -> 3913291.5 | E38: ='Vendas+PrestServ'!F27 -> 4150045.6 | F38: ='Vendas+PrestServ'!G27 -> 4401123.4 | G38: ='Vendas+PrestServ'!H27 -> 4489586 | H38: ='Vendas+PrestServ'!I27 -> 4579826.6 | I38: ='Vendas+PrestServ'!J27 -> 4671881.2 | J38: ='Vendas+PrestServ'!K27 -> 4765786 | ... L38: ='Vendas+PrestServ'!M27 -> 4959296
C41: =+C29/C5 -> 0.0067066048 | D41: =+D29/D5 -> 0.012630785 | E41: =+E29/E5 -> 0.010683155 | F41: =+F29/F5 -> 0.012677903 | G41: =+G29/G5 -> 0.012785951 | H41: =+H29/H5 -> 0.014029297 | I41: =+I29/I5 -> 0.014100371 | J41: =+J29/J5 -> 0.014170138 | ... L41: =+L29/L5 -> 0.016091764

Sheet Balanço Futuro
B2: BALANÇOS DO PROMOTOR
B3: UNIDADE: EUROS
B4: RÚBRICAS | C4: =Pressupostos!C11 -> 2020 | D4: =C4+1 -> 2021 | E4: =D4+1 -> 2022 | F4: =E4+1 -> 2023 | G4: =F4+1 -> 2024 | H4: =G4+1 -> 2025 | I4: =H4+1 -> 2026 | J4: =I4+1 -> 2027 | K4: =J4+1 -> 2028 | L4: =K4+1 -> 2029
B6: ATIVO
B7: Ativo não corrente
B8: Ativos fixos tangíveis | C8: =Balanço!E7+PlanoInvest!C96-(Amortização!E109-Amortização!D109)+'DR Empresa'!C18 -> 76162.716 | D8: =C8+PlanoInvest!D96-(Amortização!F109-Amortização!E109)+'DR Empresa'!D18 -> 97700.192 | E8: =D8+PlanoInvest!E96-(Amortização!G109-Amortização!F109)+'DR Empresa'!E18 -> 79237.668 | F8: =E8+PlanoInvest!F96-(Amortização!H109-Amortização!G109)+'DR Empresa'!F18 -> 60775.144 | G8: =F8+PlanoInvest!G96-(Amortização!I109-Amortização!H109)+'DR Empresa'!G18 -> 42312.62 | H8: =G8+PlanoInvest!H96-(Amortização!J109-Amortização!I109)+'DR Empresa'!H18 -> 33850.096 | I8: =H8+PlanoInvest!I96-(Amortização!K109-Amortização!J109)+'DR Empresa'!I18 -> 25387.572 | J8: =I8+PlanoInvest!J96-(Amortização!L109-Amortização!K109)+'DR Empresa'!J18 -> 16925.048 | K8: =J8+PlanoInvest!K96-(Amortização!M109-Amortização!L109)+'DR Empresa'!K18 -> 8462.524 | L8: =K8+PlanoInvest!L96-(Amortização!N109-Amortização!M109)+'DR Empresa'!L18 -> -2.910383e-11
B9: Propriedades de investimento | C9: =Balanço!E8 -> 102152.86 | D9: =C9 -> 102152.86 | E9: =D9 -> 102152.86 | F9: =E9 -> 102152.86 | G9: =F9 -> 102152.86 | H9: =G9 -> 102152.86 | I9: =H9 -> 102152.86 | J9: =I9 -> 102152.86 | K9: =J9 -> 102152.86 | L9: =K9 -> 102152.86
B10: Goodwill | C10: =Balanço!E9 -> 0 | D10: =C10 -> 0 | E10: =D10 -> 0 | F10: =E10 -> 0 | G10: =F10 -> 0 | H10: =G10 -> 0 | I10: =H10 -> 0 | J10: =I10 -> 0 | K10: =J10 -> 0 | L10: =K10 -> 0
B11: Ativos intangíveis | C11: =Balanço!E10+PlanoInvest!C98-(Amortização!E111-Amortização!D111) -> 0 | D11: =C11+PlanoInvest!D98-(Amortização!F111-Amortização!E111) -> 0 | E11: =D11+PlanoInvest!E98-(Amortização!G111-Amortização!F111) -> 0 | F11: =E11+PlanoInvest!F98-(Amortização!H111-Amortização!G111) -> 0 | G11: =F11+PlanoInvest!G98-(Amortização!I111-Amortização!H111) -> 0 | H11: =G11+PlanoInvest!H98-(Amortização!J111-Amortização!I111) -> 0 | I11: =H11+PlanoInvest!I98-(Amortização!K111-Amortização!J111) -> 0 | J11: =I11+PlanoInvest!J98-(Amortização!L111-Amortização!K111) -> 0 | K11: =J11+PlanoInvest!K98-(Amortização!M111-Amortização!L111) -> 0 | L11: =K11+PlanoInvest!L98-(Amortização!N111-Amortização!M111) -> 0
B12: Ativos biológicos | C12: =Balanço!E11+PlanoInvest!C97-(Amortização!E110-Amortização!D110) -> 0 | D12: =C12+PlanoInvest!D97-(Amortização!F110-Amortização!E110) -> 0 | E12: =D12+PlanoInvest!E97-(Amortização!G110-Amortização!F110) -> 0 | F12: =E12+PlanoInvest!F97-(Amortização!H110-Amortização!G110) -> 0 | G12: =F12+PlanoInvest!G97-(Amortização!I110-Amortização!H110) -> 0 | H12: =G12+PlanoInvest!H97-(Amortização!J110-Amortização!I110) -> 0 | I12: =H12+PlanoInvest!I97-(Amortização!K110-Amortização!J110) -> 0 | J12: =I12+PlanoInvest!J97-(Amortização!L110-Amortização!K110) -> 0 | K12: =J12+PlanoInvest!K97-(Amortização!M110-Amortização!L110) -> 0 | L12: =K12+PlanoInvest!L97-(Amortização!N110-Amortização!M110) -> 0
B13: Participações financeiras - método da equivalência patrimonial | C13: =Balanço!E12 -> 0 | D13: =C13 -> 0 | E13: =D13 -> 0 | F13: =E13 -> 0 | G13: =F13 -> 0 | H13: =G13 -> 0 | I13: =H13 -> 0 | J13: =I13 -> 0 | K13: =J13 -> 0 | L13: =K13 -> 0
B14: Participações financeiras - outros métodos | C14: =Balanço!E13 -> 0 | D14: =C14 -> 0 | E14: =D14 -> 0 | F14: =E14 -> 0 | G14: =F14 -> 0 | H14: =G14 -> 0 | I14: =H14 -> 0 | J14: =I14 -> 0 | K14: =J14 -> 0 | L14: =K14 -> 0
B15: Acionistas/sócios | C15: =Balanço!E14 -> 0 | D15: =C15 -> 0 | E15: =D15 -> 0 | F15: =E15 -> 0 | G15: =F15 -> 0 | H15: =G15 -> 0 | I15: =H15 -> 0 | J15: =I15 -> 0 | K15: =J15 -> 0 | L15: =K15 -> 0
B16: Outros ativos financeiros | C16: =Balanço!E15+PlanoInvest!C99 -> 347.82 | D16: =C16+PlanoInvest!D99 -> 347.82 | E16: =D16+PlanoInvest!E99 -> 347.82 | F16: =E16+PlanoInvest!F99 -> 347.82 | G16: =F16+PlanoInvest!G99 -> 347.82 | H16: =G16+PlanoInvest!H99 -> 347.82 | I16: =H16+PlanoInvest!I99 -> 347.82 | J16: =I16+PlanoInvest!J99 -> 347.82 | K16: =J16+PlanoInvest!K99 -> 347.82 | L16: =K16+PlanoInvest!L99 -> 347.82
B17: Ativos por impostos diferidos | C17: =Balanço!E16 -> 0 | D17: =C17 -> 0 | E17: =D17 -> 0 | F17: =E17 -> 0 | G17: =F17 -> 0 | H17: =G17 -> 0 | I17: =H17 -> 0 | J17: =I17 -> 0 | K17: =J17 -> 0 | L17: =K17 -> 0
B18: Investimentos financeiros (utilização exclusiva pelas pequenas entidades e microentidades) | C18: =Balanço!E17 -> 0 | D18: =C18 -> 0 | E18: =D18 -> 0 | F18: =E18 -> 0 | G18: =F18 -> 0 | H18: =G18 -> 0 | I18: =H18 -> 0 | J18: =I18 -> 0 | K18: =J18 -> 0 | L18: =K18 -> 0
B19: SOMA | C19: =SUM(C8:C18) -> 178663.4 | D19: =SUM(D8:D18) -> 200200.87 | E19: =SUM(E8:E18) -> 181738.35 | F19: =SUM(F8:F18) -> 163275.82 | G19: =SUM(G8:G18) -> 144813.3 | H19: =SUM(H8:H18) -> 136350.78 | I19: =SUM(I8:I18) -> 127888.25 | J19: =SUM(J8:J18) -> 119425.73 | ... L19: =SUM(L8:L18) -> 102500.68
B20: Ativo Corrente
B21: Inventários | C21: =FM!H6 -> 241390.37 | D21: =FM!I6 -> 255994.48 | E21: =FM!J6 -> 269752.97 | F21: =FM!K6 -> 286073.02 | G21: =FM!L6 -> 291823.09 | H21: =FM!M6 -> 297688.73 | I21: =FM!N6 -> 303672.28 | J21: =FM!O6 -> 309776.09 | ... L21: =FM!Q6 -> 322354.24
B22: Ativos biológicos | C22: =Balanço!E21 -> 0 | D22: =C22 -> 0 | E22: =D22 -> 0 | F22: =E22 -> 0 | G22: =F22 -> 0 | H22: =G22 -> 0 | I22: =H22 -> 0 | J22: =I22 -> 0 | K22: =J22 -> 0 | L22: =K22 -> 0
B23: Clientes | C23: =FM!H7 -> 1134688.5 | D23: =FM!I7 -> 1203337.1 | E23: =FM!J7 -> 1276139 | F23: =FM!K7 -> 1353345.4 | G23: =FM!L7 -> 1380547.7 | H23: =FM!M7 -> 1408296.7 | I23: =FM!N7 -> 1436603.5 | J23: =FM!O7 -> 1465479.2 | ... L23: =FM!Q7 -> 1524983.5
